{
  "generated_at": "2026-06-20T17:35:15.365600+00:00",
  "schema_version": 2,
  "universe": [
    "AAPL",
    "AMD",
    "AMZN",
    "AVGO",
    "CRM",
    "GOOG",
    "HD",
    "INTC",
    "INTU",
    "LOW",
    "META",
    "MSFT",
    "NFLX",
    "NVDA",
    "ORCL",
    "QQQ",
    "SPY",
    "TSLA",
    "WMT"
  ],
  "n_scored": 99,
  "filter": {
    "min_liquidity_usd": 500.0,
    "min_abs_edge_pp": 0
  },
  "signals": [
    {
      "ticker": "AAPL",
      "side": "above",
      "strike": 360.0,
      "close_date": "2026-06-30",
      "days": 7.21,
      "spot": 298.01,
      "sigma_used": 0.2299,
      "sigma_source": "iv_target",
      "rv_30d": 0.2193,
      "rv_60d": 0.2342,
      "iv_atm_target": 0.2299,
      "iv_atm_front": 0.1876,
      "iv_atm_back": 0.2271,
      "iv_term_slope": 0.0396,
      "iv_skew": 0.0879,
      "iv_target_expiry": "2026-06-29",
      "fair_yes": 0.0,
      "market_yes": 0.5,
      "edge_pp": -50.0,
      "spread_pp": 97.8,
      "tradeable_edge_pp": -0.0,
      "liquidity": 4141.0,
      "vol_24h": 0,
      "event_slug": "aapl-above-in-june-2026",
      "market_id": "2388616"
    },
    {
      "ticker": "AAPL",
      "side": "above",
      "strike": 350.0,
      "close_date": "2026-06-30",
      "days": 7.21,
      "spot": 298.01,
      "sigma_used": 0.2299,
      "sigma_source": "iv_target",
      "rv_30d": 0.2193,
      "rv_60d": 0.2342,
      "iv_atm_target": 0.2299,
      "iv_atm_front": 0.1876,
      "iv_atm_back": 0.2271,
      "iv_term_slope": 0.0396,
      "iv_skew": 0.0879,
      "iv_target_expiry": "2026-06-29",
      "fair_yes": 0.0,
      "market_yes": 0.4995,
      "edge_pp": -49.95,
      "spread_pp": 97.7,
      "tradeable_edge_pp": -0.0,
      "liquidity": 4141.0,
      "vol_24h": 0,
      "event_slug": "aapl-above-in-june-2026",
      "market_id": "2388611"
    },
    {
      "ticker": "AMZN",
      "side": "above",
      "strike": 290.0,
      "close_date": "2026-06-30",
      "days": 7.21,
      "spot": 244.39,
      "sigma_used": 0.3091,
      "sigma_source": "iv_target",
      "rv_30d": 0.2957,
      "rv_60d": 0.3123,
      "iv_atm_target": 0.3091,
      "iv_atm_front": 0.2624,
      "iv_atm_back": 0.3334,
      "iv_term_slope": 0.071,
      "iv_skew": 0.0244,
      "iv_target_expiry": "2026-06-29",
      "fair_yes": 0.0005,
      "market_yes": 0.5,
      "edge_pp": -49.95,
      "spread_pp": 97.8,
      "tradeable_edge_pp": -0.0,
      "liquidity": 531.0,
      "vol_24h": 0,
      "event_slug": "amzn-above-in-june-2026",
      "market_id": "2388746"
    },
    {
      "ticker": "MSFT",
      "side": "above",
      "strike": 450.0,
      "close_date": "2026-06-30",
      "days": 7.21,
      "spot": 379.4,
      "sigma_used": 0.3386,
      "sigma_source": "iv_target",
      "rv_30d": 0.3394,
      "rv_60d": 0.3259,
      "iv_atm_target": 0.3386,
      "iv_atm_front": 0.2652,
      "iv_atm_back": 0.3268,
      "iv_term_slope": 0.0616,
      "iv_skew": 0.0264,
      "iv_target_expiry": "2026-06-29",
      "fair_yes": 0.0013,
      "market_yes": 0.4995,
      "edge_pp": -49.82,
      "spread_pp": 97.5,
      "tradeable_edge_pp": -0.0,
      "liquidity": 9606.0,
      "vol_24h": 0,
      "event_slug": "msft-above-in-june-2026",
      "market_id": "2388685"
    },
    {
      "ticker": "META",
      "side": "above",
      "strike": 680.0,
      "close_date": "2026-06-30",
      "days": 7.21,
      "spot": 577.22,
      "sigma_used": 0.3423,
      "sigma_source": "iv_target",
      "rv_30d": 0.3822,
      "rv_60d": 0.4512,
      "iv_atm_target": 0.3423,
      "iv_atm_front": 0.2753,
      "iv_atm_back": 0.3558,
      "iv_term_slope": 0.0805,
      "iv_skew": 0.02,
      "iv_target_expiry": "2026-06-29",
      "fair_yes": 0.0021,
      "market_yes": 0.5,
      "edge_pp": -49.79,
      "spread_pp": 97.8,
      "tradeable_edge_pp": -0.0,
      "liquidity": 896.0,
      "vol_24h": 0,
      "event_slug": "meta-above-in-june-2026",
      "market_id": "2388859"
    },
    {
      "ticker": "AAPL",
      "side": "above",
      "strike": 330.0,
      "close_date": "2026-06-30",
      "days": 7.21,
      "spot": 298.01,
      "sigma_used": 0.2299,
      "sigma_source": "iv_target",
      "rv_30d": 0.2193,
      "rv_60d": 0.2342,
      "iv_atm_target": 0.2299,
      "iv_atm_front": 0.1876,
      "iv_atm_back": 0.2271,
      "iv_term_slope": 0.0396,
      "iv_skew": 0.0879,
      "iv_target_expiry": "2026-06-29",
      "fair_yes": 0.0041,
      "market_yes": 0.5,
      "edge_pp": -49.59,
      "spread_pp": 97.6,
      "tradeable_edge_pp": -0.0,
      "liquidity": 4141.0,
      "vol_24h": 0,
      "event_slug": "aapl-above-in-june-2026",
      "market_id": "2388599"
    },
    {
      "ticker": "AMZN",
      "side": "above",
      "strike": 280.0,
      "close_date": "2026-06-30",
      "days": 7.21,
      "spot": 244.39,
      "sigma_used": 0.3091,
      "sigma_source": "iv_target",
      "rv_30d": 0.2957,
      "rv_60d": 0.3123,
      "iv_atm_target": 0.3091,
      "iv_atm_front": 0.2624,
      "iv_atm_back": 0.3334,
      "iv_term_slope": 0.071,
      "iv_skew": 0.0244,
      "iv_target_expiry": "2026-06-29",
      "fair_yes": 0.0043,
      "market_yes": 0.5,
      "edge_pp": -49.57,
      "spread_pp": 97.8,
      "tradeable_edge_pp": -0.0,
      "liquidity": 531.0,
      "vol_24h": 0,
      "event_slug": "amzn-above-in-june-2026",
      "market_id": "2388742"
    },
    {
      "ticker": "MSFT",
      "side": "above",
      "strike": 435.0,
      "close_date": "2026-06-30",
      "days": 7.21,
      "spot": 379.4,
      "sigma_used": 0.3386,
      "sigma_source": "iv_target",
      "rv_30d": 0.3394,
      "rv_60d": 0.3259,
      "iv_atm_target": 0.3386,
      "iv_atm_front": 0.2652,
      "iv_atm_back": 0.3268,
      "iv_term_slope": 0.0616,
      "iv_skew": 0.0264,
      "iv_target_expiry": "2026-06-29",
      "fair_yes": 0.0079,
      "market_yes": 0.5,
      "edge_pp": -49.21,
      "spread_pp": 97.6,
      "tradeable_edge_pp": -0.0,
      "liquidity": 9606.0,
      "vol_24h": 0,
      "event_slug": "msft-above-in-june-2026",
      "market_id": "2388680"
    },
    {
      "ticker": "META",
      "side": "above",
      "strike": 660.0,
      "close_date": "2026-06-30",
      "days": 7.21,
      "spot": 577.22,
      "sigma_used": 0.3423,
      "sigma_source": "iv_target",
      "rv_30d": 0.3822,
      "rv_60d": 0.4512,
      "iv_atm_target": 0.3423,
      "iv_atm_front": 0.2753,
      "iv_atm_back": 0.3558,
      "iv_term_slope": 0.0805,
      "iv_skew": 0.02,
      "iv_target_expiry": "2026-06-29",
      "fair_yes": 0.0096,
      "market_yes": 0.5,
      "edge_pp": -49.04,
      "spread_pp": 97.8,
      "tradeable_edge_pp": -0.0,
      "liquidity": 896.0,
      "vol_24h": 0,
      "event_slug": "meta-above-in-june-2026",
      "market_id": "2388858"
    },
    {
      "ticker": "AAPL",
      "side": "above",
      "strike": 340.0,
      "close_date": "2026-06-30",
      "days": 7.21,
      "spot": 298.01,
      "sigma_used": 0.2299,
      "sigma_source": "iv_target",
      "rv_30d": 0.2193,
      "rv_60d": 0.2342,
      "iv_atm_target": 0.2299,
      "iv_atm_front": 0.1876,
      "iv_atm_back": 0.2271,
      "iv_term_slope": 0.0396,
      "iv_skew": 0.0879,
      "iv_target_expiry": "2026-06-29",
      "fair_yes": 0.0003,
      "market_yes": 0.49,
      "edge_pp": -48.97,
      "spread_pp": 95.4,
      "tradeable_edge_pp": -0.0,
      "liquidity": 4141.0,
      "vol_24h": 5.0,
      "event_slug": "aapl-above-in-june-2026",
      "market_id": "2388604"
    },
    {
      "ticker": "META",
      "side": "above",
      "strike": 700.0,
      "close_date": "2026-06-30",
      "days": 7.21,
      "spot": 577.22,
      "sigma_used": 0.3423,
      "sigma_source": "iv_target",
      "rv_30d": 0.3822,
      "rv_60d": 0.4512,
      "iv_atm_target": 0.3423,
      "iv_atm_front": 0.2753,
      "iv_atm_back": 0.3558,
      "iv_term_slope": 0.0805,
      "iv_skew": 0.02,
      "iv_target_expiry": "2026-06-29",
      "fair_yes": 0.0004,
      "market_yes": 0.4875,
      "edge_pp": -48.71,
      "spread_pp": 95.7,
      "tradeable_edge_pp": -0.0,
      "liquidity": 896.0,
      "vol_24h": 148.0,
      "event_slug": "meta-above-in-june-2026",
      "market_id": "2388861"
    },
    {
      "ticker": "AMZN",
      "side": "above",
      "strike": 300.0,
      "close_date": "2026-06-30",
      "days": 7.21,
      "spot": 244.39,
      "sigma_used": 0.3091,
      "sigma_source": "iv_target",
      "rv_30d": 0.2957,
      "rv_60d": 0.3123,
      "iv_atm_target": 0.3091,
      "iv_atm_front": 0.2624,
      "iv_atm_back": 0.3334,
      "iv_term_slope": 0.071,
      "iv_skew": 0.0244,
      "iv_target_expiry": "2026-06-29",
      "fair_yes": 0.0,
      "market_yes": 0.487,
      "edge_pp": -48.7,
      "spread_pp": 95.8,
      "tradeable_edge_pp": -0.0,
      "liquidity": 531.0,
      "vol_24h": 148.0,
      "event_slug": "amzn-above-in-june-2026",
      "market_id": "2388750"
    },
    {
      "ticker": "AMZN",
      "side": "above",
      "strike": 310.0,
      "close_date": "2026-06-30",
      "days": 7.21,
      "spot": 244.39,
      "sigma_used": 0.3091,
      "sigma_source": "iv_target",
      "rv_30d": 0.2957,
      "rv_60d": 0.3123,
      "iv_atm_target": 0.3091,
      "iv_atm_front": 0.2624,
      "iv_atm_back": 0.3334,
      "iv_term_slope": 0.071,
      "iv_skew": 0.0244,
      "iv_target_expiry": "2026-06-29",
      "fair_yes": 0.0,
      "market_yes": 0.4865,
      "edge_pp": -48.65,
      "spread_pp": 95.9,
      "tradeable_edge_pp": -0.0,
      "liquidity": 531.0,
      "vol_24h": 148.0,
      "event_slug": "amzn-above-in-june-2026",
      "market_id": "2388755"
    },
    {
      "ticker": "NFLX",
      "side": "above",
      "strike": 100.0,
      "close_date": "2026-06-30",
      "days": 7.21,
      "spot": 77.38,
      "sigma_used": 0.325,
      "sigma_source": "iv_target",
      "rv_30d": 0.2374,
      "rv_60d": 0.327,
      "iv_atm_target": 0.325,
      "iv_atm_front": 0.3123,
      "iv_atm_back": 0.4563,
      "iv_term_slope": 0.144,
      "iv_skew": 0.0005,
      "iv_target_expiry": "2026-07-02",
      "fair_yes": 0.0,
      "market_yes": 0.4845,
      "edge_pp": -48.45,
      "spread_pp": 92.9,
      "tradeable_edge_pp": -0.0,
      "liquidity": 7023.0,
      "vol_24h": 10,
      "event_slug": "nflx-above-in-june-2026",
      "market_id": "2389027"
    },
    {
      "ticker": "AMZN",
      "side": "above",
      "strike": 320.0,
      "close_date": "2026-06-30",
      "days": 7.21,
      "spot": 244.39,
      "sigma_used": 0.3091,
      "sigma_source": "iv_target",
      "rv_30d": 0.2957,
      "rv_60d": 0.3123,
      "iv_atm_target": 0.3091,
      "iv_atm_front": 0.2624,
      "iv_atm_back": 0.3334,
      "iv_term_slope": 0.071,
      "iv_skew": 0.0244,
      "iv_target_expiry": "2026-06-29",
      "fair_yes": 0.0,
      "market_yes": 0.4815,
      "edge_pp": -48.15,
      "spread_pp": 96.1,
      "tradeable_edge_pp": -0.0,
      "liquidity": 531.0,
      "vol_24h": 283.0,
      "event_slug": "amzn-above-in-june-2026",
      "market_id": "2388759"
    },
    {
      "ticker": "MSFT",
      "side": "above",
      "strike": 330.0,
      "close_date": "2026-06-30",
      "days": 7.21,
      "spot": 379.4,
      "sigma_used": 0.3386,
      "sigma_source": "iv_target",
      "rv_30d": 0.3394,
      "rv_60d": 0.3259,
      "iv_atm_target": 0.3386,
      "iv_atm_front": 0.2652,
      "iv_atm_back": 0.3268,
      "iv_term_slope": 0.0616,
      "iv_skew": 0.0264,
      "iv_target_expiry": "2026-06-29",
      "fair_yes": 0.9919,
      "market_yes": 0.5155,
      "edge_pp": 47.64,
      "spread_pp": 94.5,
      "tradeable_edge_pp": 0.0,
      "liquidity": 9606.0,
      "vol_24h": 0,
      "event_slug": "msft-above-in-june-2026",
      "market_id": "2388649"
    },
    {
      "ticker": "AMZN",
      "side": "above",
      "strike": 220.0,
      "close_date": "2026-06-30",
      "days": 7.21,
      "spot": 244.39,
      "sigma_used": 0.3091,
      "sigma_source": "iv_target",
      "rv_30d": 0.2957,
      "rv_60d": 0.3123,
      "iv_atm_target": 0.3091,
      "iv_atm_front": 0.2624,
      "iv_atm_back": 0.3334,
      "iv_term_slope": 0.071,
      "iv_skew": 0.0244,
      "iv_target_expiry": "2026-06-29",
      "fair_yes": 0.9764,
      "market_yes": 0.5,
      "edge_pp": 47.64,
      "spread_pp": 97.8,
      "tradeable_edge_pp": 0.0,
      "liquidity": 531.0,
      "vol_24h": 0,
      "event_slug": "amzn-above-in-june-2026",
      "market_id": "2388722"
    },
    {
      "ticker": "NVDA",
      "side": "above",
      "strike": 240.0,
      "close_date": "2026-06-30",
      "days": 7.21,
      "spot": 210.69,
      "sigma_used": 0.3631,
      "sigma_source": "iv_target",
      "rv_30d": 0.4323,
      "rv_60d": 0.413,
      "iv_atm_target": 0.3631,
      "iv_atm_front": 0.2975,
      "iv_atm_back": 0.3743,
      "iv_term_slope": 0.0768,
      "iv_skew": 0.0654,
      "iv_target_expiry": "2026-06-29",
      "fair_yes": 0.0157,
      "market_yes": 0.4905,
      "edge_pp": -47.48,
      "spread_pp": 94.9,
      "tradeable_edge_pp": -0.0,
      "liquidity": 7497.0,
      "vol_24h": 12.0,
      "event_slug": "nvda-above-in-june-2026",
      "market_id": "2388972"
    },
    {
      "ticker": "AMZN",
      "side": "above",
      "strike": 270.0,
      "close_date": "2026-06-30",
      "days": 7.21,
      "spot": 244.39,
      "sigma_used": 0.3091,
      "sigma_source": "iv_target",
      "rv_30d": 0.2957,
      "rv_60d": 0.3123,
      "iv_atm_target": 0.3091,
      "iv_atm_front": 0.2624,
      "iv_atm_back": 0.3334,
      "iv_term_slope": 0.071,
      "iv_skew": 0.0244,
      "iv_target_expiry": "2026-06-29",
      "fair_yes": 0.0267,
      "market_yes": 0.5,
      "edge_pp": -47.33,
      "spread_pp": 97.8,
      "tradeable_edge_pp": -0.0,
      "liquidity": 531.0,
      "vol_24h": 0,
      "event_slug": "amzn-above-in-june-2026",
      "market_id": "2388738"
    },
    {
      "ticker": "SPY",
      "side": "above",
      "strike": 760.0,
      "close_date": "2026-06-22",
      "days": 1.5,
      "spot": 746.74,
      "sigma_used": 0.1002,
      "sigma_source": "iv_target",
      "rv_30d": 0.1474,
      "rv_60d": 0.1534,
      "iv_atm_target": 0.1002,
      "iv_atm_front": 0.1002,
      "iv_atm_back": 0.1477,
      "iv_term_slope": 0.0475,
      "iv_skew": 0.0449,
      "iv_target_expiry": "2026-06-22",
      "fair_yes": 0.0113,
      "market_yes": 0.48,
      "edge_pp": -46.87,
      "spread_pp": 92.0,
      "tradeable_edge_pp": -0.0,
      "liquidity": 2057.0,
      "vol_24h": 0,
      "event_slug": "spy-closes-above-on-june-22-2026",
      "market_id": "2595282"
    },
    {
      "ticker": "NFLX",
      "side": "above",
      "strike": 120.0,
      "close_date": "2026-06-30",
      "days": 7.21,
      "spot": 77.38,
      "sigma_used": 0.325,
      "sigma_source": "iv_target",
      "rv_30d": 0.2374,
      "rv_60d": 0.327,
      "iv_atm_target": 0.325,
      "iv_atm_front": 0.3123,
      "iv_atm_back": 0.4563,
      "iv_term_slope": 0.144,
      "iv_skew": 0.0005,
      "iv_target_expiry": "2026-07-02",
      "fair_yes": 0.0,
      "market_yes": 0.4645,
      "edge_pp": -46.45,
      "spread_pp": 90.3,
      "tradeable_edge_pp": -0.0,
      "liquidity": 7023.0,
      "vol_24h": 114.0,
      "event_slug": "nflx-above-in-june-2026",
      "market_id": "2389029"
    },
    {
      "ticker": "TSLA",
      "side": "above",
      "strike": 450.0,
      "close_date": "2026-06-30",
      "days": 7.21,
      "spot": 400.49,
      "sigma_used": 0.3963,
      "sigma_source": "iv_target",
      "rv_30d": 0.4764,
      "rv_60d": 0.4475,
      "iv_atm_target": 0.3963,
      "iv_atm_front": 0.3296,
      "iv_atm_back": 0.462,
      "iv_term_slope": 0.1324,
      "iv_skew": 0.0273,
      "iv_target_expiry": "2026-06-29",
      "fair_yes": 0.0382,
      "market_yes": 0.5,
      "edge_pp": -46.18,
      "spread_pp": 92.0,
      "tradeable_edge_pp": -0.0,
      "liquidity": 10991.0,
      "vol_24h": 820,
      "event_slug": "tsla-above-in-june-2026",
      "market_id": "2388909"
    },
    {
      "ticker": "AMZN",
      "side": "above",
      "strike": 330.0,
      "close_date": "2026-06-30",
      "days": 7.21,
      "spot": 244.39,
      "sigma_used": 0.3091,
      "sigma_source": "iv_target",
      "rv_30d": 0.2957,
      "rv_60d": 0.3123,
      "iv_atm_target": 0.3091,
      "iv_atm_front": 0.2624,
      "iv_atm_back": 0.3334,
      "iv_term_slope": 0.071,
      "iv_skew": 0.0244,
      "iv_target_expiry": "2026-06-29",
      "fair_yes": 0.0,
      "market_yes": 0.4595,
      "edge_pp": -45.95,
      "spread_pp": 91.3,
      "tradeable_edge_pp": -0.0,
      "liquidity": 531.0,
      "vol_24h": 162.0,
      "event_slug": "amzn-above-in-june-2026",
      "market_id": "2388762"
    },
    {
      "ticker": "META",
      "side": "above",
      "strike": 640.0,
      "close_date": "2026-06-30",
      "days": 7.21,
      "spot": 577.22,
      "sigma_used": 0.3423,
      "sigma_source": "iv_target",
      "rv_30d": 0.3822,
      "rv_60d": 0.4512,
      "iv_atm_target": 0.3423,
      "iv_atm_front": 0.2753,
      "iv_atm_back": 0.3558,
      "iv_term_slope": 0.0805,
      "iv_skew": 0.02,
      "iv_target_expiry": "2026-06-29",
      "fair_yes": 0.035,
      "market_yes": 0.489,
      "edge_pp": -45.4,
      "spread_pp": 95.4,
      "tradeable_edge_pp": -0.0,
      "liquidity": 896.0,
      "vol_24h": 27.0,
      "event_slug": "meta-above-in-june-2026",
      "market_id": "2388857"
    },
    {
      "ticker": "META",
      "side": "above",
      "strike": 520.0,
      "close_date": "2026-06-30",
      "days": 7.21,
      "spot": 577.22,
      "sigma_used": 0.3423,
      "sigma_source": "iv_target",
      "rv_30d": 0.3822,
      "rv_60d": 0.4512,
      "iv_atm_target": 0.3423,
      "iv_atm_front": 0.2753,
      "iv_atm_back": 0.3558,
      "iv_term_slope": 0.0805,
      "iv_skew": 0.02,
      "iv_target_expiry": "2026-06-29",
      "fair_yes": 0.9619,
      "market_yes": 0.515,
      "edge_pp": 44.69,
      "spread_pp": 94.8,
      "tradeable_edge_pp": 0.0,
      "liquidity": 896.0,
      "vol_24h": 0,
      "event_slug": "meta-above-in-june-2026",
      "market_id": "2388850"
    },
    {
      "ticker": "TSLA",
      "side": "above",
      "strike": 460.0,
      "close_date": "2026-06-30",
      "days": 7.21,
      "spot": 400.49,
      "sigma_used": 0.3963,
      "sigma_source": "iv_target",
      "rv_30d": 0.4764,
      "rv_60d": 0.4475,
      "iv_atm_target": 0.3963,
      "iv_atm_front": 0.3296,
      "iv_atm_back": 0.462,
      "iv_term_slope": 0.1324,
      "iv_skew": 0.0273,
      "iv_target_expiry": "2026-06-29",
      "fair_yes": 0.0179,
      "market_yes": 0.4505,
      "edge_pp": -43.26,
      "spread_pp": 87.7,
      "tradeable_edge_pp": -0.0,
      "liquidity": 10991.0,
      "vol_24h": 691.0,
      "event_slug": "tsla-above-in-june-2026",
      "market_id": "2388910"
    },
    {
      "ticker": "NVDA",
      "side": "above",
      "strike": 230.0,
      "close_date": "2026-06-30",
      "days": 7.21,
      "spot": 210.69,
      "sigma_used": 0.3631,
      "sigma_source": "iv_target",
      "rv_30d": 0.4323,
      "rv_60d": 0.413,
      "iv_atm_target": 0.3631,
      "iv_atm_front": 0.2975,
      "iv_atm_back": 0.3743,
      "iv_term_slope": 0.0768,
      "iv_skew": 0.0654,
      "iv_target_expiry": "2026-06-29",
      "fair_yes": 0.0724,
      "market_yes": 0.5,
      "edge_pp": -42.76,
      "spread_pp": 98.0,
      "tradeable_edge_pp": -0.0,
      "liquidity": 7497.0,
      "vol_24h": 0,
      "event_slug": "nvda-above-in-june-2026",
      "market_id": "2388969"
    },
    {
      "ticker": "TSLA",
      "side": "above",
      "strike": 440.0,
      "close_date": "2026-06-30",
      "days": 7.21,
      "spot": 400.49,
      "sigma_used": 0.3963,
      "sigma_source": "iv_target",
      "rv_30d": 0.4764,
      "rv_60d": 0.4475,
      "iv_atm_target": 0.3963,
      "iv_atm_front": 0.3296,
      "iv_atm_back": 0.462,
      "iv_term_slope": 0.1324,
      "iv_skew": 0.0273,
      "iv_target_expiry": "2026-06-29",
      "fair_yes": 0.0754,
      "market_yes": 0.495,
      "edge_pp": -41.96,
      "spread_pp": 81.0,
      "tradeable_edge_pp": -0.0,
      "liquidity": 10991.0,
      "vol_24h": 1366.0,
      "event_slug": "tsla-above-in-june-2026",
      "market_id": "2388908"
    },
    {
      "ticker": "AMZN",
      "side": "above",
      "strike": 210.0,
      "close_date": "2026-06-30",
      "days": 7.21,
      "spot": 244.39,
      "sigma_used": 0.3091,
      "sigma_source": "iv_target",
      "rv_30d": 0.2957,
      "rv_60d": 0.3123,
      "iv_atm_target": 0.3091,
      "iv_atm_front": 0.2624,
      "iv_atm_back": 0.3334,
      "iv_term_slope": 0.071,
      "iv_skew": 0.0244,
      "iv_target_expiry": "2026-06-29",
      "fair_yes": 0.998,
      "market_yes": 0.5815,
      "edge_pp": 41.65,
      "spread_pp": 82.9,
      "tradeable_edge_pp": 0.0,
      "liquidity": 531.0,
      "vol_24h": 2.0,
      "event_slug": "amzn-above-in-june-2026",
      "market_id": "2388719"
    },
    {
      "ticker": "TSLA",
      "side": "above",
      "strike": 480.0,
      "close_date": "2026-06-30",
      "days": 7.21,
      "spot": 400.49,
      "sigma_used": 0.3963,
      "sigma_source": "iv_target",
      "rv_30d": 0.4764,
      "rv_60d": 0.4475,
      "iv_atm_target": 0.3963,
      "iv_atm_front": 0.3296,
      "iv_atm_back": 0.462,
      "iv_term_slope": 0.1324,
      "iv_skew": 0.0273,
      "iv_target_expiry": "2026-06-29",
      "fair_yes": 0.0031,
      "market_yes": 0.408,
      "edge_pp": -40.49,
      "spread_pp": 79.4,
      "tradeable_edge_pp": -0.0,
      "liquidity": 10991.0,
      "vol_24h": 897.0,
      "event_slug": "tsla-above-in-june-2026",
      "market_id": "2388914"
    },
    {
      "ticker": "AMZN",
      "side": "above",
      "strike": 260.0,
      "close_date": "2026-06-30",
      "days": 7.21,
      "spot": 244.39,
      "sigma_used": 0.3091,
      "sigma_source": "iv_target",
      "rv_30d": 0.2957,
      "rv_60d": 0.3123,
      "iv_atm_target": 0.3091,
      "iv_atm_front": 0.2624,
      "iv_atm_back": 0.3334,
      "iv_term_slope": 0.071,
      "iv_skew": 0.0244,
      "iv_target_expiry": "2026-06-29",
      "fair_yes": 0.1131,
      "market_yes": 0.515,
      "edge_pp": -40.19,
      "spread_pp": 91.0,
      "tradeable_edge_pp": -0.0,
      "liquidity": 531.0,
      "vol_24h": 14,
      "event_slug": "amzn-above-in-june-2026",
      "market_id": "2388734"
    },
    {
      "ticker": "MSFT",
      "side": "above",
      "strike": 405.0,
      "close_date": "2026-06-30",
      "days": 7.21,
      "spot": 379.4,
      "sigma_used": 0.3386,
      "sigma_source": "iv_target",
      "rv_30d": 0.3394,
      "rv_60d": 0.3259,
      "iv_atm_target": 0.3386,
      "iv_atm_front": 0.2652,
      "iv_atm_back": 0.3268,
      "iv_term_slope": 0.0616,
      "iv_skew": 0.0264,
      "iv_target_expiry": "2026-06-29",
      "fair_yes": 0.1214,
      "market_yes": 0.52,
      "edge_pp": -39.86,
      "spread_pp": 94.0,
      "tradeable_edge_pp": -0.0,
      "liquidity": 9606.0,
      "vol_24h": 0,
      "event_slug": "msft-above-in-june-2026",
      "market_id": "2388670"
    },
    {
      "ticker": "TSLA",
      "side": "above",
      "strike": 430.0,
      "close_date": "2026-06-30",
      "days": 7.21,
      "spot": 400.49,
      "sigma_used": 0.3963,
      "sigma_source": "iv_target",
      "rv_30d": 0.4764,
      "rv_60d": 0.4475,
      "iv_atm_target": 0.3963,
      "iv_atm_front": 0.3296,
      "iv_atm_back": 0.462,
      "iv_term_slope": 0.1324,
      "iv_skew": 0.0273,
      "iv_target_expiry": "2026-06-29",
      "fair_yes": 0.137,
      "market_yes": 0.535,
      "edge_pp": -39.8,
      "spread_pp": 91.0,
      "tradeable_edge_pp": -0.0,
      "liquidity": 10991.0,
      "vol_24h": 63.0,
      "event_slug": "tsla-above-in-june-2026",
      "market_id": "2388907"
    },
    {
      "ticker": "AAPL",
      "side": "above",
      "strike": 280.0,
      "close_date": "2026-06-30",
      "days": 7.21,
      "spot": 298.01,
      "sigma_used": 0.2299,
      "sigma_source": "iv_target",
      "rv_30d": 0.2193,
      "rv_60d": 0.2342,
      "iv_atm_target": 0.2299,
      "iv_atm_front": 0.1876,
      "iv_atm_back": 0.2271,
      "iv_term_slope": 0.0396,
      "iv_skew": 0.0879,
      "iv_target_expiry": "2026-06-29",
      "fair_yes": 0.9433,
      "market_yes": 0.55,
      "edge_pp": 39.33,
      "spread_pp": 88.0,
      "tradeable_edge_pp": 0.0,
      "liquidity": 4141.0,
      "vol_24h": 24.0,
      "event_slug": "aapl-above-in-june-2026",
      "market_id": "2388567"
    },
    {
      "ticker": "AMZN",
      "side": "above",
      "strike": 230.0,
      "close_date": "2026-06-30",
      "days": 7.21,
      "spot": 244.39,
      "sigma_used": 0.3091,
      "sigma_source": "iv_target",
      "rv_30d": 0.2957,
      "rv_60d": 0.3123,
      "iv_atm_target": 0.3091,
      "iv_atm_front": 0.2624,
      "iv_atm_back": 0.3334,
      "iv_term_slope": 0.071,
      "iv_skew": 0.0244,
      "iv_target_expiry": "2026-06-29",
      "fair_yes": 0.8716,
      "market_yes": 0.48,
      "edge_pp": 39.16,
      "spread_pp": 90.0,
      "tradeable_edge_pp": 0.0,
      "liquidity": 531.0,
      "vol_24h": 104.0,
      "event_slug": "amzn-above-in-june-2026",
      "market_id": "2388725"
    },
    {
      "ticker": "SPY",
      "side": "above",
      "strike": 735.0,
      "close_date": "2026-06-22",
      "days": 1.5,
      "spot": 746.74,
      "sigma_used": 0.1002,
      "sigma_source": "iv_target",
      "rv_30d": 0.1474,
      "rv_60d": 0.1534,
      "iv_atm_target": 0.1002,
      "iv_atm_front": 0.1002,
      "iv_atm_back": 0.1477,
      "iv_term_slope": 0.0475,
      "iv_skew": 0.0449,
      "iv_target_expiry": "2026-06-22",
      "fair_yes": 0.9796,
      "market_yes": 0.605,
      "edge_pp": 37.46,
      "spread_pp": 67.0,
      "tradeable_edge_pp": 0.0,
      "liquidity": 2057.0,
      "vol_24h": 0,
      "event_slug": "spy-closes-above-on-june-22-2026",
      "market_id": "2595291"
    },
    {
      "ticker": "SPY",
      "side": "above",
      "strike": 740.0,
      "close_date": "2026-06-22",
      "days": 1.5,
      "spot": 746.74,
      "sigma_used": 0.1002,
      "sigma_source": "iv_target",
      "rv_30d": 0.1474,
      "rv_60d": 0.1534,
      "iv_atm_target": 0.1002,
      "iv_atm_front": 0.1002,
      "iv_atm_back": 0.1477,
      "iv_term_slope": 0.0475,
      "iv_skew": 0.0449,
      "iv_target_expiry": "2026-06-22",
      "fair_yes": 0.8787,
      "market_yes": 0.52,
      "edge_pp": 35.87,
      "spread_pp": 80.0,
      "tradeable_edge_pp": 0.0,
      "liquidity": 2057.0,
      "vol_24h": 0,
      "event_slug": "spy-closes-above-on-june-22-2026",
      "market_id": "2595288"
    },
    {
      "ticker": "META",
      "side": "above",
      "strike": 620.0,
      "close_date": "2026-06-30",
      "days": 7.21,
      "spot": 577.22,
      "sigma_used": 0.3423,
      "sigma_source": "iv_target",
      "rv_30d": 0.3822,
      "rv_60d": 0.4512,
      "iv_atm_target": 0.3423,
      "iv_atm_front": 0.2753,
      "iv_atm_back": 0.3558,
      "iv_term_slope": 0.0805,
      "iv_skew": 0.02,
      "iv_target_expiry": "2026-06-29",
      "fair_yes": 0.1032,
      "market_yes": 0.46,
      "edge_pp": -35.68,
      "spread_pp": 84.0,
      "tradeable_edge_pp": -0.0,
      "liquidity": 896.0,
      "vol_24h": 24.0,
      "event_slug": "meta-above-in-june-2026",
      "market_id": "2388856"
    },
    {
      "ticker": "AAPL",
      "side": "above",
      "strike": 310.0,
      "close_date": "2026-06-30",
      "days": 7.21,
      "spot": 298.01,
      "sigma_used": 0.2299,
      "sigma_source": "iv_target",
      "rv_30d": 0.2193,
      "rv_60d": 0.2342,
      "iv_atm_target": 0.2299,
      "iv_atm_front": 0.1876,
      "iv_atm_back": 0.2271,
      "iv_term_slope": 0.0396,
      "iv_skew": 0.0879,
      "iv_target_expiry": "2026-06-29",
      "fair_yes": 0.1507,
      "market_yes": 0.505,
      "edge_pp": -35.43,
      "spread_pp": 89.0,
      "tradeable_edge_pp": -0.0,
      "liquidity": 4141.0,
      "vol_24h": 0,
      "event_slug": "aapl-above-in-june-2026",
      "market_id": "2388591"
    },
    {
      "ticker": "NFLX",
      "side": "above",
      "strike": 80.0,
      "close_date": "2026-06-30",
      "days": 7.21,
      "spot": 77.38,
      "sigma_used": 0.325,
      "sigma_source": "iv_target",
      "rv_30d": 0.2374,
      "rv_60d": 0.327,
      "iv_atm_target": 0.325,
      "iv_atm_front": 0.3123,
      "iv_atm_back": 0.4563,
      "iv_term_slope": 0.144,
      "iv_skew": 0.0005,
      "iv_target_expiry": "2026-07-02",
      "fair_yes": 0.2633,
      "market_yes": 0.605,
      "edge_pp": -34.17,
      "spread_pp": 69.0,
      "tradeable_edge_pp": -0.0,
      "liquidity": 7023.0,
      "vol_24h": 160.0,
      "event_slug": "nflx-above-in-june-2026",
      "market_id": "2389025"
    },
    {
      "ticker": "SPY",
      "side": "above",
      "strike": 755.0,
      "close_date": "2026-06-22",
      "days": 1.5,
      "spot": 746.74,
      "sigma_used": 0.1002,
      "sigma_source": "iv_target",
      "rv_30d": 0.1474,
      "rv_60d": 0.1534,
      "iv_atm_target": 0.1002,
      "iv_atm_front": 0.1002,
      "iv_atm_back": 0.1477,
      "iv_term_slope": 0.0475,
      "iv_skew": 0.0449,
      "iv_target_expiry": "2026-06-22",
      "fair_yes": 0.0769,
      "market_yes": 0.405,
      "edge_pp": -32.81,
      "spread_pp": 71.0,
      "tradeable_edge_pp": -0.0,
      "liquidity": 2057.0,
      "vol_24h": 0,
      "event_slug": "spy-closes-above-on-june-22-2026",
      "market_id": "2595283"
    },
    {
      "ticker": "NVDA",
      "side": "above",
      "strike": 180.0,
      "close_date": "2026-06-30",
      "days": 7.21,
      "spot": 210.69,
      "sigma_used": 0.3631,
      "sigma_source": "iv_target",
      "rv_30d": 0.4323,
      "rv_60d": 0.413,
      "iv_atm_target": 0.3631,
      "iv_atm_front": 0.2975,
      "iv_atm_back": 0.3743,
      "iv_term_slope": 0.0768,
      "iv_skew": 0.0654,
      "iv_target_expiry": "2026-06-29",
      "fair_yes": 0.9943,
      "market_yes": 0.716,
      "edge_pp": 27.83,
      "spread_pp": 42.0,
      "tradeable_edge_pp": 0.0,
      "liquidity": 7497.0,
      "vol_24h": 4788.0,
      "event_slug": "nvda-above-in-june-2026",
      "market_id": "2388957"
    },
    {
      "ticker": "TSLA",
      "side": "above",
      "strike": 420.0,
      "close_date": "2026-06-30",
      "days": 7.21,
      "spot": 400.49,
      "sigma_used": 0.3963,
      "sigma_source": "iv_target",
      "rv_30d": 0.4764,
      "rv_60d": 0.4475,
      "iv_atm_target": 0.3963,
      "iv_atm_front": 0.3296,
      "iv_atm_back": 0.462,
      "iv_term_slope": 0.1324,
      "iv_skew": 0.0273,
      "iv_target_expiry": "2026-06-29",
      "fair_yes": 0.2288,
      "market_yes": 0.5,
      "edge_pp": -27.12,
      "spread_pp": 74.0,
      "tradeable_edge_pp": -0.0,
      "liquidity": 10991.0,
      "vol_24h": 29.0,
      "event_slug": "tsla-above-in-june-2026",
      "market_id": "2388906"
    },
    {
      "ticker": "MSFT",
      "side": "above",
      "strike": 390.0,
      "close_date": "2026-06-30",
      "days": 7.21,
      "spot": 379.4,
      "sigma_used": 0.3386,
      "sigma_source": "iv_target",
      "rv_30d": 0.3394,
      "rv_60d": 0.3259,
      "iv_atm_target": 0.3386,
      "iv_atm_front": 0.2652,
      "iv_atm_back": 0.3268,
      "iv_term_slope": 0.0616,
      "iv_skew": 0.0264,
      "iv_target_expiry": "2026-06-29",
      "fair_yes": 0.3052,
      "market_yes": 0.575,
      "edge_pp": -26.98,
      "spread_pp": 81.0,
      "tradeable_edge_pp": -0.0,
      "liquidity": 9606.0,
      "vol_24h": 0,
      "event_slug": "msft-above-in-june-2026",
      "market_id": "2388664"
    },
    {
      "ticker": "TSLA",
      "side": "above",
      "strike": 490.0,
      "close_date": "2026-06-30",
      "days": 7.21,
      "spot": 400.49,
      "sigma_used": 0.3963,
      "sigma_source": "iv_target",
      "rv_30d": 0.4764,
      "rv_60d": 0.4475,
      "iv_atm_target": 0.3963,
      "iv_atm_front": 0.3296,
      "iv_atm_back": 0.462,
      "iv_term_slope": 0.1324,
      "iv_skew": 0.0273,
      "iv_target_expiry": "2026-06-29",
      "fair_yes": 0.0012,
      "market_yes": 0.258,
      "edge_pp": -25.68,
      "spread_pp": 44.2,
      "tradeable_edge_pp": -0.0,
      "liquidity": 10991.0,
      "vol_24h": 1203.0,
      "event_slug": "tsla-above-in-june-2026",
      "market_id": "2388916"
    },
    {
      "ticker": "TSLA",
      "side": "above",
      "strike": 410.0,
      "close_date": "2026-06-30",
      "days": 7.21,
      "spot": 400.49,
      "sigma_used": 0.3963,
      "sigma_source": "iv_target",
      "rv_30d": 0.4764,
      "rv_60d": 0.4475,
      "iv_atm_target": 0.3963,
      "iv_atm_front": 0.3296,
      "iv_atm_back": 0.462,
      "iv_term_slope": 0.1324,
      "iv_skew": 0.0273,
      "iv_target_expiry": "2026-06-29",
      "fair_yes": 0.3507,
      "market_yes": 0.545,
      "edge_pp": -19.43,
      "spread_pp": 69.0,
      "tradeable_edge_pp": -0.0,
      "liquidity": 10991.0,
      "vol_24h": 0,
      "event_slug": "tsla-above-in-june-2026",
      "market_id": "2388905"
    },
    {
      "ticker": "TSLA",
      "side": "above",
      "strike": 400.0,
      "close_date": "2026-06-30",
      "days": 7.21,
      "spot": 400.49,
      "sigma_used": 0.3963,
      "sigma_source": "iv_target",
      "rv_30d": 0.4764,
      "rv_60d": 0.4475,
      "iv_atm_target": 0.3963,
      "iv_atm_front": 0.3296,
      "iv_atm_back": 0.462,
      "iv_term_slope": 0.1324,
      "iv_skew": 0.0273,
      "iv_target_expiry": "2026-06-29",
      "fair_yes": 0.4939,
      "market_yes": 0.32,
      "edge_pp": 17.39,
      "spread_pp": 54.0,
      "tradeable_edge_pp": 0.0,
      "liquidity": 10991.0,
      "vol_24h": 1007.0,
      "event_slug": "tsla-above-in-june-2026",
      "market_id": "2388904"
    },
    {
      "ticker": "META",
      "side": "above",
      "strike": 580.0,
      "close_date": "2026-06-30",
      "days": 7.21,
      "spot": 577.22,
      "sigma_used": 0.3423,
      "sigma_source": "iv_target",
      "rv_30d": 0.3822,
      "rv_60d": 0.4512,
      "iv_atm_target": 0.3423,
      "iv_atm_front": 0.2753,
      "iv_atm_back": 0.3558,
      "iv_term_slope": 0.0805,
      "iv_skew": 0.02,
      "iv_target_expiry": "2026-06-29",
      "fair_yes": 0.4554,
      "market_yes": 0.625,
      "edge_pp": -16.96,
      "spread_pp": 73.0,
      "tradeable_edge_pp": -0.0,
      "liquidity": 896.0,
      "vol_24h": 89,
      "event_slug": "meta-above-in-june-2026",
      "market_id": "2388854"
    },
    {
      "ticker": "AMZN",
      "side": "above",
      "strike": 250.0,
      "close_date": "2026-06-30",
      "days": 7.21,
      "spot": 244.39,
      "sigma_used": 0.3091,
      "sigma_source": "iv_target",
      "rv_30d": 0.2957,
      "rv_60d": 0.3123,
      "iv_atm_target": 0.3091,
      "iv_atm_front": 0.2624,
      "iv_atm_back": 0.3334,
      "iv_term_slope": 0.071,
      "iv_skew": 0.0244,
      "iv_target_expiry": "2026-06-29",
      "fair_yes": 0.3227,
      "market_yes": 0.48,
      "edge_pp": -15.73,
      "spread_pp": 58.0,
      "tradeable_edge_pp": -0.0,
      "liquidity": 531.0,
      "vol_24h": 52.0,
      "event_slug": "amzn-above-in-june-2026",
      "market_id": "2388731"
    },
    {
      "ticker": "SPY",
      "side": "above",
      "strike": 750.0,
      "close_date": "2026-06-22",
      "days": 1.5,
      "spot": 746.74,
      "sigma_used": 0.1002,
      "sigma_source": "iv_target",
      "rv_30d": 0.1474,
      "rv_60d": 0.1534,
      "iv_atm_target": 0.1002,
      "iv_atm_front": 0.1002,
      "iv_atm_back": 0.1477,
      "iv_term_slope": 0.0475,
      "iv_skew": 0.0449,
      "iv_target_expiry": "2026-06-22",
      "fair_yes": 0.2853,
      "market_yes": 0.415,
      "edge_pp": -12.97,
      "spread_pp": 49.0,
      "tradeable_edge_pp": -0.0,
      "liquidity": 2057.0,
      "vol_24h": 0,
      "event_slug": "spy-closes-above-on-june-22-2026",
      "market_id": "2595284"
    },
    {
      "ticker": "MSFT",
      "side": "above",
      "strike": 375.0,
      "close_date": "2026-06-30",
      "days": 7.21,
      "spot": 379.4,
      "sigma_used": 0.3386,
      "sigma_source": "iv_target",
      "rv_30d": 0.3394,
      "rv_60d": 0.3259,
      "iv_atm_target": 0.3386,
      "iv_atm_front": 0.2652,
      "iv_atm_back": 0.3268,
      "iv_term_slope": 0.0616,
      "iv_skew": 0.0264,
      "iv_target_expiry": "2026-06-29",
      "fair_yes": 0.5694,
      "market_yes": 0.6695,
      "edge_pp": -10.01,
      "spread_pp": 27.9,
      "tradeable_edge_pp": -0.0,
      "liquidity": 9606.0,
      "vol_24h": 5297.0,
      "event_slug": "msft-above-in-june-2026",
      "market_id": "2388659"
    },
    {
      "ticker": "NFLX",
      "side": "above",
      "strike": 40.0,
      "close_date": "2026-06-30",
      "days": 7.21,
      "spot": 77.38,
      "sigma_used": 0.325,
      "sigma_source": "iv_target",
      "rv_30d": 0.2374,
      "rv_60d": 0.327,
      "iv_atm_target": 0.325,
      "iv_atm_front": 0.3123,
      "iv_atm_back": 0.4563,
      "iv_term_slope": 0.144,
      "iv_skew": 0.0005,
      "iv_target_expiry": "2026-07-02",
      "fair_yes": 1.0,
      "market_yes": 0.901,
      "edge_pp": 9.9,
      "spread_pp": 19.6,
      "tradeable_edge_pp": 0.0,
      "liquidity": 7023.0,
      "vol_24h": 156.0,
      "event_slug": "nflx-above-in-june-2026",
      "market_id": "2389019"
    },
    {
      "ticker": "NFLX",
      "side": "above",
      "strike": 60.0,
      "close_date": "2026-06-30",
      "days": 7.21,
      "spot": 77.38,
      "sigma_used": 0.325,
      "sigma_source": "iv_target",
      "rv_30d": 0.2374,
      "rv_60d": 0.327,
      "iv_atm_target": 0.325,
      "iv_atm_front": 0.3123,
      "iv_atm_back": 0.4563,
      "iv_term_slope": 0.144,
      "iv_skew": 0.0005,
      "iv_target_expiry": "2026-07-02",
      "fair_yes": 1.0,
      "market_yes": 0.901,
      "edge_pp": 9.9,
      "spread_pp": 19.6,
      "tradeable_edge_pp": 0.0,
      "liquidity": 7023.0,
      "vol_24h": 15,
      "event_slug": "nflx-above-in-june-2026",
      "market_id": "2389022"
    },
    {
      "ticker": "NVDA",
      "side": "above",
      "strike": 190.0,
      "close_date": "2026-06-30",
      "days": 7.21,
      "spot": 210.69,
      "sigma_used": 0.3631,
      "sigma_source": "iv_target",
      "rv_30d": 0.4323,
      "rv_60d": 0.413,
      "iv_atm_target": 0.3631,
      "iv_atm_front": 0.2975,
      "iv_atm_back": 0.3743,
      "iv_term_slope": 0.0768,
      "iv_skew": 0.0654,
      "iv_target_expiry": "2026-06-29",
      "fair_yes": 0.9507,
      "market_yes": 0.86,
      "edge_pp": 9.07,
      "spread_pp": 8.0,
      "tradeable_edge_pp": 1.07,
      "liquidity": 7497.0,
      "vol_24h": 2657.0,
      "event_slug": "nvda-above-in-june-2026",
      "market_id": "2388959"
    },
    {
      "ticker": "AAPL",
      "side": "above",
      "strike": 250.0,
      "close_date": "2026-06-30",
      "days": 7.21,
      "spot": 298.01,
      "sigma_used": 0.2299,
      "sigma_source": "iv_target",
      "rv_30d": 0.2193,
      "rv_60d": 0.2342,
      "iv_atm_target": 0.2299,
      "iv_atm_front": 0.1876,
      "iv_atm_back": 0.2271,
      "iv_term_slope": 0.0396,
      "iv_skew": 0.0879,
      "iv_target_expiry": "2026-06-29",
      "fair_yes": 1.0,
      "market_yes": 0.919,
      "edge_pp": 8.1,
      "spread_pp": 13.8,
      "tradeable_edge_pp": 0.0,
      "liquidity": 4141.0,
      "vol_24h": 21.0,
      "event_slug": "aapl-above-in-june-2026",
      "market_id": "2388559"
    },
    {
      "ticker": "AAPL",
      "side": "above",
      "strike": 260.0,
      "close_date": "2026-06-30",
      "days": 7.21,
      "spot": 298.01,
      "sigma_used": 0.2299,
      "sigma_source": "iv_target",
      "rv_30d": 0.2193,
      "rv_60d": 0.2342,
      "iv_atm_target": 0.2299,
      "iv_atm_front": 0.1876,
      "iv_atm_back": 0.2271,
      "iv_term_slope": 0.0396,
      "iv_skew": 0.0879,
      "iv_target_expiry": "2026-06-29",
      "fair_yes": 0.9998,
      "market_yes": 0.919,
      "edge_pp": 8.08,
      "spread_pp": 13.8,
      "tradeable_edge_pp": 0.0,
      "liquidity": 4141.0,
      "vol_24h": 0,
      "event_slug": "aapl-above-in-june-2026",
      "market_id": "2388562"
    },
    {
      "ticker": "NVDA",
      "side": "above",
      "strike": 170.0,
      "close_date": "2026-06-30",
      "days": 7.21,
      "spot": 210.69,
      "sigma_used": 0.3631,
      "sigma_source": "iv_target",
      "rv_30d": 0.4323,
      "rv_60d": 0.413,
      "iv_atm_target": 0.3631,
      "iv_atm_front": 0.2975,
      "iv_atm_back": 0.3743,
      "iv_term_slope": 0.0768,
      "iv_skew": 0.0654,
      "iv_target_expiry": "2026-06-29",
      "fair_yes": 0.9997,
      "market_yes": 0.919,
      "edge_pp": 8.07,
      "spread_pp": 13.8,
      "tradeable_edge_pp": 0.0,
      "liquidity": 7497.0,
      "vol_24h": 100,
      "event_slug": "nvda-above-in-june-2026",
      "market_id": "2388955"
    },
    {
      "ticker": "AAPL",
      "side": "above",
      "strike": 270.0,
      "close_date": "2026-06-30",
      "days": 7.21,
      "spot": 298.01,
      "sigma_used": 0.2299,
      "sigma_source": "iv_target",
      "rv_30d": 0.2193,
      "rv_60d": 0.2342,
      "iv_atm_target": 0.2299,
      "iv_atm_front": 0.1876,
      "iv_atm_back": 0.2271,
      "iv_term_slope": 0.0396,
      "iv_skew": 0.0879,
      "iv_target_expiry": "2026-06-29",
      "fair_yes": 0.9941,
      "market_yes": 0.914,
      "edge_pp": 8.01,
      "spread_pp": 12.8,
      "tradeable_edge_pp": 0.0,
      "liquidity": 4141.0,
      "vol_24h": 0,
      "event_slug": "aapl-above-in-june-2026",
      "market_id": "2388564"
    },
    {
      "ticker": "NVDA",
      "side": "above",
      "strike": 150.0,
      "close_date": "2026-06-30",
      "days": 7.21,
      "spot": 210.69,
      "sigma_used": 0.3631,
      "sigma_source": "iv_target",
      "rv_30d": 0.4323,
      "rv_60d": 0.413,
      "iv_atm_target": 0.3631,
      "iv_atm_front": 0.2975,
      "iv_atm_back": 0.3743,
      "iv_term_slope": 0.0768,
      "iv_skew": 0.0654,
      "iv_target_expiry": "2026-06-29",
      "fair_yes": 1.0,
      "market_yes": 0.925,
      "edge_pp": 7.5,
      "spread_pp": 14.8,
      "tradeable_edge_pp": 0.0,
      "liquidity": 7497.0,
      "vol_24h": 248.0,
      "event_slug": "nvda-above-in-june-2026",
      "market_id": "2388953"
    },
    {
      "ticker": "MSFT",
      "side": "above",
      "strike": 420.0,
      "close_date": "2026-06-30",
      "days": 7.21,
      "spot": 379.4,
      "sigma_used": 0.3386,
      "sigma_source": "iv_target",
      "rv_30d": 0.3394,
      "rv_60d": 0.3259,
      "iv_atm_target": 0.3386,
      "iv_atm_front": 0.2652,
      "iv_atm_back": 0.3268,
      "iv_term_slope": 0.0616,
      "iv_skew": 0.0264,
      "iv_target_expiry": "2026-06-29",
      "fair_yes": 0.0357,
      "market_yes": 0.11,
      "edge_pp": -7.43,
      "spread_pp": 20.0,
      "tradeable_edge_pp": -0.0,
      "liquidity": 9606.0,
      "vol_24h": 0,
      "event_slug": "msft-above-in-june-2026",
      "market_id": "2388675"
    },
    {
      "ticker": "TSLA",
      "side": "above",
      "strike": 380.0,
      "close_date": "2026-06-30",
      "days": 7.21,
      "spot": 400.49,
      "sigma_used": 0.3963,
      "sigma_source": "iv_target",
      "rv_30d": 0.4764,
      "rv_60d": 0.4475,
      "iv_atm_target": 0.3963,
      "iv_atm_front": 0.3296,
      "iv_atm_back": 0.462,
      "iv_term_slope": 0.1324,
      "iv_skew": 0.0273,
      "iv_target_expiry": "2026-06-29",
      "fair_yes": 0.7733,
      "market_yes": 0.7,
      "edge_pp": 7.33,
      "spread_pp": 18.0,
      "tradeable_edge_pp": 0.0,
      "liquidity": 10991.0,
      "vol_24h": 4057.0,
      "event_slug": "tsla-above-in-june-2026",
      "market_id": "2388902"
    },
    {
      "ticker": "AAPL",
      "side": "above",
      "strike": 290.0,
      "close_date": "2026-06-30",
      "days": 7.21,
      "spot": 298.01,
      "sigma_used": 0.2299,
      "sigma_source": "iv_target",
      "rv_30d": 0.2193,
      "rv_60d": 0.2342,
      "iv_atm_target": 0.2299,
      "iv_atm_front": 0.1876,
      "iv_atm_back": 0.2271,
      "iv_term_slope": 0.0396,
      "iv_skew": 0.0879,
      "iv_target_expiry": "2026-06-29",
      "fair_yes": 0.752,
      "market_yes": 0.825,
      "edge_pp": -7.3,
      "spread_pp": 15.0,
      "tradeable_edge_pp": -0.0,
      "liquidity": 4141.0,
      "vol_24h": 567.0,
      "event_slug": "aapl-above-in-june-2026",
      "market_id": "2388573"
    },
    {
      "ticker": "AAPL",
      "side": "above",
      "strike": 320.0,
      "close_date": "2026-06-30",
      "days": 7.21,
      "spot": 298.01,
      "sigma_used": 0.2299,
      "sigma_source": "iv_target",
      "rv_30d": 0.2193,
      "rv_60d": 0.2342,
      "iv_atm_target": 0.2299,
      "iv_atm_front": 0.1876,
      "iv_atm_back": 0.2271,
      "iv_term_slope": 0.0396,
      "iv_skew": 0.0879,
      "iv_target_expiry": "2026-06-29",
      "fair_yes": 0.0322,
      "market_yes": 0.0995,
      "edge_pp": -6.73,
      "spread_pp": 15.9,
      "tradeable_edge_pp": -0.0,
      "liquidity": 4141.0,
      "vol_24h": 2952.0,
      "event_slug": "aapl-above-in-june-2026",
      "market_id": "2388595"
    },
    {
      "ticker": "MSFT",
      "side": "above",
      "strike": 360.0,
      "close_date": "2026-06-30",
      "days": 7.21,
      "spot": 379.4,
      "sigma_used": 0.3386,
      "sigma_source": "iv_target",
      "rv_30d": 0.3394,
      "rv_60d": 0.3259,
      "iv_atm_target": 0.3386,
      "iv_atm_front": 0.2652,
      "iv_atm_back": 0.3268,
      "iv_term_slope": 0.0616,
      "iv_skew": 0.0264,
      "iv_target_expiry": "2026-06-29",
      "fair_yes": 0.8126,
      "market_yes": 0.748,
      "edge_pp": 6.46,
      "spread_pp": 25.4,
      "tradeable_edge_pp": 0.0,
      "liquidity": 9606.0,
      "vol_24h": 2758.0,
      "event_slug": "msft-above-in-june-2026",
      "market_id": "2388656"
    },
    {
      "ticker": "NVDA",
      "side": "above",
      "strike": 200.0,
      "close_date": "2026-06-30",
      "days": 7.21,
      "spot": 210.69,
      "sigma_used": 0.3631,
      "sigma_source": "iv_target",
      "rv_30d": 0.4323,
      "rv_60d": 0.413,
      "iv_atm_target": 0.3631,
      "iv_atm_front": 0.2975,
      "iv_atm_back": 0.3743,
      "iv_term_slope": 0.0768,
      "iv_skew": 0.0654,
      "iv_target_expiry": "2026-06-29",
      "fair_yes": 0.793,
      "market_yes": 0.73,
      "edge_pp": 6.3,
      "spread_pp": 32.0,
      "tradeable_edge_pp": 0.0,
      "liquidity": 7497.0,
      "vol_24h": 1869.0,
      "event_slug": "nvda-above-in-june-2026",
      "market_id": "2388961"
    },
    {
      "ticker": "META",
      "side": "above",
      "strike": 760.0,
      "close_date": "2026-06-30",
      "days": 7.21,
      "spot": 577.22,
      "sigma_used": 0.3423,
      "sigma_source": "iv_target",
      "rv_30d": 0.3822,
      "rv_60d": 0.4512,
      "iv_atm_target": 0.3423,
      "iv_atm_front": 0.2753,
      "iv_atm_back": 0.3558,
      "iv_term_slope": 0.0805,
      "iv_skew": 0.02,
      "iv_target_expiry": "2026-06-29",
      "fair_yes": 0.0,
      "market_yes": 0.054,
      "edge_pp": -5.4,
      "spread_pp": 9.6,
      "tradeable_edge_pp": -0.0,
      "liquidity": 896.0,
      "vol_24h": 191.0,
      "event_slug": "meta-above-in-june-2026",
      "market_id": "2388867"
    },
    {
      "ticker": "NVDA",
      "side": "above",
      "strike": 210.0,
      "close_date": "2026-06-30",
      "days": 7.21,
      "spot": 210.69,
      "sigma_used": 0.3631,
      "sigma_source": "iv_target",
      "rv_30d": 0.4323,
      "rv_60d": 0.413,
      "iv_atm_target": 0.3631,
      "iv_atm_front": 0.2975,
      "iv_atm_back": 0.3743,
      "iv_term_slope": 0.0768,
      "iv_skew": 0.0654,
      "iv_target_expiry": "2026-06-29",
      "fair_yes": 0.509,
      "market_yes": 0.455,
      "edge_pp": 5.4,
      "spread_pp": 43.0,
      "tradeable_edge_pp": 0.0,
      "liquidity": 7497.0,
      "vol_24h": 268.0,
      "event_slug": "nvda-above-in-june-2026",
      "market_id": "2388963"
    },
    {
      "ticker": "AAPL",
      "side": "above",
      "strike": 300.0,
      "close_date": "2026-06-30",
      "days": 7.21,
      "spot": 298.01,
      "sigma_used": 0.2299,
      "sigma_source": "iv_target",
      "rv_30d": 0.2193,
      "rv_60d": 0.2342,
      "iv_atm_target": 0.2299,
      "iv_atm_front": 0.1876,
      "iv_atm_back": 0.2271,
      "iv_term_slope": 0.0396,
      "iv_skew": 0.0879,
      "iv_target_expiry": "2026-06-29",
      "fair_yes": 0.4244,
      "market_yes": 0.38,
      "edge_pp": 4.44,
      "spread_pp": 40.0,
      "tradeable_edge_pp": 0.0,
      "liquidity": 4141.0,
      "vol_24h": 124.0,
      "event_slug": "aapl-above-in-june-2026",
      "market_id": "2388584"
    },
    {
      "ticker": "MSFT",
      "side": "above",
      "strike": 345.0,
      "close_date": "2026-06-30",
      "days": 7.21,
      "spot": 379.4,
      "sigma_used": 0.3386,
      "sigma_source": "iv_target",
      "rv_30d": 0.3394,
      "rv_60d": 0.3259,
      "iv_atm_target": 0.3386,
      "iv_atm_front": 0.2652,
      "iv_atm_back": 0.3268,
      "iv_term_slope": 0.0616,
      "iv_skew": 0.0264,
      "iv_target_expiry": "2026-06-29",
      "fair_yes": 0.9485,
      "market_yes": 0.912,
      "edge_pp": 3.65,
      "spread_pp": 4.4,
      "tradeable_edge_pp": 0.0,
      "liquidity": 9606.0,
      "vol_24h": 10645.0,
      "event_slug": "msft-above-in-june-2026",
      "market_id": "2388653"
    },
    {
      "ticker": "TSLA",
      "side": "above",
      "strike": 390.0,
      "close_date": "2026-06-30",
      "days": 7.21,
      "spot": 400.49,
      "sigma_used": 0.3963,
      "sigma_source": "iv_target",
      "rv_30d": 0.4764,
      "rv_60d": 0.4475,
      "iv_atm_target": 0.3963,
      "iv_atm_front": 0.3296,
      "iv_atm_back": 0.462,
      "iv_term_slope": 0.1324,
      "iv_skew": 0.0273,
      "iv_target_expiry": "2026-06-29",
      "fair_yes": 0.6414,
      "market_yes": 0.605,
      "edge_pp": 3.64,
      "spread_pp": 29.0,
      "tradeable_edge_pp": 0.0,
      "liquidity": 10991.0,
      "vol_24h": 988.0,
      "event_slug": "tsla-above-in-june-2026",
      "market_id": "2388903"
    },
    {
      "ticker": "NVDA",
      "side": "above",
      "strike": 260.0,
      "close_date": "2026-06-30",
      "days": 7.21,
      "spot": 210.69,
      "sigma_used": 0.3631,
      "sigma_source": "iv_target",
      "rv_30d": 0.4323,
      "rv_60d": 0.413,
      "iv_atm_target": 0.3631,
      "iv_atm_front": 0.2975,
      "iv_atm_back": 0.3743,
      "iv_term_slope": 0.0768,
      "iv_skew": 0.0654,
      "iv_target_expiry": "2026-06-29",
      "fair_yes": 0.0003,
      "market_yes": 0.0355,
      "edge_pp": -3.52,
      "spread_pp": 6.9,
      "tradeable_edge_pp": -0.0,
      "liquidity": 7497.0,
      "vol_24h": 348.0,
      "event_slug": "nvda-above-in-june-2026",
      "market_id": "2388978"
    },
    {
      "ticker": "SPY",
      "side": "above",
      "strike": 730.0,
      "close_date": "2026-06-22",
      "days": 1.5,
      "spot": 746.74,
      "sigma_used": 0.1002,
      "sigma_source": "iv_target",
      "rv_30d": 0.1474,
      "rv_60d": 0.1534,
      "iv_atm_target": 0.1002,
      "iv_atm_front": 0.1002,
      "iv_atm_back": 0.1477,
      "iv_term_slope": 0.0475,
      "iv_skew": 0.0449,
      "iv_target_expiry": "2026-06-22",
      "fair_yes": 0.9983,
      "market_yes": 0.9635,
      "edge_pp": 3.48,
      "spread_pp": 4.7,
      "tradeable_edge_pp": 0.0,
      "liquidity": 2057.0,
      "vol_24h": 6.0,
      "event_slug": "spy-closes-above-on-june-22-2026",
      "market_id": "2595293"
    },
    {
      "ticker": "NVDA",
      "side": "above",
      "strike": 220.0,
      "close_date": "2026-06-30",
      "days": 7.21,
      "spot": 210.69,
      "sigma_used": 0.3631,
      "sigma_source": "iv_target",
      "rv_30d": 0.4323,
      "rv_60d": 0.413,
      "iv_atm_target": 0.3631,
      "iv_atm_front": 0.2975,
      "iv_atm_back": 0.3743,
      "iv_term_slope": 0.0768,
      "iv_skew": 0.0654,
      "iv_target_expiry": "2026-06-29",
      "fair_yes": 0.2313,
      "market_yes": 0.265,
      "edge_pp": -3.37,
      "spread_pp": 37.0,
      "tradeable_edge_pp": -0.0,
      "liquidity": 7497.0,
      "vol_24h": 0,
      "event_slug": "nvda-above-in-june-2026",
      "market_id": "2388966"
    },
    {
      "ticker": "AAPL",
      "side": "above",
      "strike": 370.0,
      "close_date": "2026-06-30",
      "days": 7.21,
      "spot": 298.01,
      "sigma_used": 0.2299,
      "sigma_source": "iv_target",
      "rv_30d": 0.2193,
      "rv_60d": 0.2342,
      "iv_atm_target": 0.2299,
      "iv_atm_front": 0.1876,
      "iv_atm_back": 0.2271,
      "iv_term_slope": 0.0396,
      "iv_skew": 0.0879,
      "iv_target_expiry": "2026-06-29",
      "fair_yes": 0.0,
      "market_yes": 0.03,
      "edge_pp": -3.0,
      "spread_pp": 4.0,
      "tradeable_edge_pp": -0.0,
      "liquidity": 4141.0,
      "vol_24h": 151.0,
      "event_slug": "aapl-above-in-june-2026",
      "market_id": "2388619"
    },
    {
      "ticker": "MSFT",
      "side": "above",
      "strike": 465.0,
      "close_date": "2026-06-30",
      "days": 7.21,
      "spot": 379.4,
      "sigma_used": 0.3386,
      "sigma_source": "iv_target",
      "rv_30d": 0.3394,
      "rv_60d": 0.3259,
      "iv_atm_target": 0.3386,
      "iv_atm_front": 0.2652,
      "iv_atm_back": 0.3268,
      "iv_term_slope": 0.0616,
      "iv_skew": 0.0264,
      "iv_target_expiry": "2026-06-29",
      "fair_yes": 0.0002,
      "market_yes": 0.03,
      "edge_pp": -2.98,
      "spread_pp": 3.8,
      "tradeable_edge_pp": -0.0,
      "liquidity": 9606.0,
      "vol_24h": 156.0,
      "event_slug": "msft-above-in-june-2026",
      "market_id": "2388687"
    },
    {
      "ticker": "SPY",
      "side": "above",
      "strike": 725.0,
      "close_date": "2026-06-22",
      "days": 1.5,
      "spot": 746.74,
      "sigma_used": 0.1002,
      "sigma_source": "iv_target",
      "rv_30d": 0.1474,
      "rv_60d": 0.1534,
      "iv_atm_target": 0.1002,
      "iv_atm_front": 0.1002,
      "iv_atm_back": 0.1477,
      "iv_term_slope": 0.0475,
      "iv_skew": 0.0449,
      "iv_target_expiry": "2026-06-22",
      "fair_yes": 0.9999,
      "market_yes": 0.976,
      "edge_pp": 2.39,
      "spread_pp": 2.8,
      "tradeable_edge_pp": 0.0,
      "liquidity": 2057.0,
      "vol_24h": 30.0,
      "event_slug": "spy-closes-above-on-june-22-2026",
      "market_id": "2595295"
    },
    {
      "ticker": "TSLA",
      "side": "above",
      "strike": 470.0,
      "close_date": "2026-06-30",
      "days": 7.21,
      "spot": 400.49,
      "sigma_used": 0.3963,
      "sigma_source": "iv_target",
      "rv_30d": 0.4764,
      "rv_60d": 0.4475,
      "iv_atm_target": 0.3963,
      "iv_atm_front": 0.3296,
      "iv_atm_back": 0.462,
      "iv_term_slope": 0.1324,
      "iv_skew": 0.0273,
      "iv_target_expiry": "2026-06-29",
      "fair_yes": 0.0078,
      "market_yes": 0.031,
      "edge_pp": -2.32,
      "spread_pp": 5.8,
      "tradeable_edge_pp": -0.0,
      "liquidity": 10991.0,
      "vol_24h": 1089.0,
      "event_slug": "tsla-above-in-june-2026",
      "market_id": "2388912"
    },
    {
      "ticker": "SPY",
      "side": "above",
      "strike": 745.0,
      "close_date": "2026-06-22",
      "days": 1.5,
      "spot": 746.74,
      "sigma_used": 0.1002,
      "sigma_source": "iv_target",
      "rv_30d": 0.1474,
      "rv_60d": 0.1534,
      "iv_atm_target": 0.1002,
      "iv_atm_front": 0.1002,
      "iv_atm_back": 0.1477,
      "iv_term_slope": 0.0475,
      "iv_skew": 0.0449,
      "iv_target_expiry": "2026-06-22",
      "fair_yes": 0.6171,
      "market_yes": 0.595,
      "edge_pp": 2.21,
      "spread_pp": 49.0,
      "tradeable_edge_pp": 0.0,
      "liquidity": 2057.0,
      "vol_24h": 0,
      "event_slug": "spy-closes-above-on-june-22-2026",
      "market_id": "2595286"
    },
    {
      "ticker": "SPY",
      "side": "above",
      "strike": 765.0,
      "close_date": "2026-06-22",
      "days": 1.5,
      "spot": 746.74,
      "sigma_used": 0.1002,
      "sigma_source": "iv_target",
      "rv_30d": 0.1474,
      "rv_60d": 0.1534,
      "iv_atm_target": 0.1002,
      "iv_atm_front": 0.1002,
      "iv_atm_back": 0.1477,
      "iv_term_slope": 0.0475,
      "iv_skew": 0.0449,
      "iv_target_expiry": "2026-06-22",
      "fair_yes": 0.0009,
      "market_yes": 0.023,
      "edge_pp": -2.21,
      "spread_pp": 3.0,
      "tradeable_edge_pp": -0.0,
      "liquidity": 2057.0,
      "vol_24h": 57.0,
      "event_slug": "spy-closes-above-on-june-22-2026",
      "market_id": "2595281"
    },
    {
      "ticker": "SPY",
      "side": "above",
      "strike": 720.0,
      "close_date": "2026-06-22",
      "days": 1.5,
      "spot": 746.74,
      "sigma_used": 0.1002,
      "sigma_source": "iv_target",
      "rv_30d": 0.1474,
      "rv_60d": 0.1534,
      "iv_atm_target": 0.1002,
      "iv_atm_front": 0.1002,
      "iv_atm_back": 0.1477,
      "iv_term_slope": 0.0475,
      "iv_skew": 0.0449,
      "iv_target_expiry": "2026-06-22",
      "fair_yes": 1.0,
      "market_yes": 0.979,
      "edge_pp": 2.1,
      "spread_pp": 2.2,
      "tradeable_edge_pp": 0.0,
      "liquidity": 2057.0,
      "vol_24h": 101.0,
      "event_slug": "spy-closes-above-on-june-22-2026",
      "market_id": "2595296"
    },
    {
      "ticker": "META",
      "side": "above",
      "strike": 540.0,
      "close_date": "2026-06-30",
      "days": 7.21,
      "spot": 577.22,
      "sigma_used": 0.3423,
      "sigma_source": "iv_target",
      "rv_30d": 0.3822,
      "rv_60d": 0.4512,
      "iv_atm_target": 0.3423,
      "iv_atm_front": 0.2753,
      "iv_atm_back": 0.3558,
      "iv_term_slope": 0.0805,
      "iv_skew": 0.02,
      "iv_target_expiry": "2026-06-29",
      "fair_yes": 0.869,
      "market_yes": 0.85,
      "edge_pp": 1.9,
      "spread_pp": 24.0,
      "tradeable_edge_pp": 0.0,
      "liquidity": 896.0,
      "vol_24h": 90.0,
      "event_slug": "meta-above-in-june-2026",
      "market_id": "2388852"
    },
    {
      "ticker": "META",
      "side": "above",
      "strike": 600.0,
      "close_date": "2026-06-30",
      "days": 7.21,
      "spot": 577.22,
      "sigma_used": 0.3423,
      "sigma_source": "iv_target",
      "rv_30d": 0.3822,
      "rv_60d": 0.4512,
      "iv_atm_target": 0.3423,
      "iv_atm_front": 0.2753,
      "iv_atm_back": 0.3558,
      "iv_term_slope": 0.0805,
      "iv_skew": 0.02,
      "iv_target_expiry": "2026-06-29",
      "fair_yes": 0.2428,
      "market_yes": 0.26,
      "edge_pp": -1.72,
      "spread_pp": 44.0,
      "tradeable_edge_pp": -0.0,
      "liquidity": 896.0,
      "vol_24h": 22.0,
      "event_slug": "meta-above-in-june-2026",
      "market_id": "2388855"
    },
    {
      "ticker": "NVDA",
      "side": "above",
      "strike": 250.0,
      "close_date": "2026-06-30",
      "days": 7.21,
      "spot": 210.69,
      "sigma_used": 0.3631,
      "sigma_source": "iv_target",
      "rv_30d": 0.4323,
      "rv_60d": 0.413,
      "iv_atm_target": 0.3631,
      "iv_atm_front": 0.2975,
      "iv_atm_back": 0.3743,
      "iv_term_slope": 0.0768,
      "iv_skew": 0.0654,
      "iv_target_expiry": "2026-06-29",
      "fair_yes": 0.0024,
      "market_yes": 0.017,
      "edge_pp": -1.46,
      "spread_pp": 1.4,
      "tradeable_edge_pp": -0.06,
      "liquidity": 7497.0,
      "vol_24h": 302.0,
      "event_slug": "nvda-above-in-june-2026",
      "market_id": "2388975"
    },
    {
      "ticker": "SPY",
      "side": "above",
      "strike": 770.0,
      "close_date": "2026-06-22",
      "days": 1.5,
      "spot": 746.74,
      "sigma_used": 0.1002,
      "sigma_source": "iv_target",
      "rv_30d": 0.1474,
      "rv_60d": 0.1534,
      "iv_atm_target": 0.1002,
      "iv_atm_front": 0.1002,
      "iv_atm_back": 0.1477,
      "iv_term_slope": 0.0475,
      "iv_skew": 0.0449,
      "iv_target_expiry": "2026-06-22",
      "fair_yes": 0.0,
      "market_yes": 0.0145,
      "edge_pp": -1.45,
      "spread_pp": 2.3,
      "tradeable_edge_pp": -0.0,
      "liquidity": 2057.0,
      "vol_24h": 137.0,
      "event_slug": "spy-closes-above-on-june-22-2026",
      "market_id": "2595278"
    },
    {
      "ticker": "AMZN",
      "side": "above",
      "strike": 240.0,
      "close_date": "2026-06-30",
      "days": 7.21,
      "spot": 244.39,
      "sigma_used": 0.3091,
      "sigma_source": "iv_target",
      "rv_30d": 0.2957,
      "rv_60d": 0.3123,
      "iv_atm_target": 0.3091,
      "iv_atm_front": 0.2624,
      "iv_atm_back": 0.3334,
      "iv_term_slope": 0.071,
      "iv_skew": 0.0244,
      "iv_target_expiry": "2026-06-29",
      "fair_yes": 0.6257,
      "market_yes": 0.615,
      "edge_pp": 1.07,
      "spread_pp": 41.0,
      "tradeable_edge_pp": 0.0,
      "liquidity": 531.0,
      "vol_24h": 19.0,
      "event_slug": "amzn-above-in-june-2026",
      "market_id": "2388728"
    },
    {
      "ticker": "META",
      "side": "above",
      "strike": 740.0,
      "close_date": "2026-06-30",
      "days": 7.21,
      "spot": 577.22,
      "sigma_used": 0.3423,
      "sigma_source": "iv_target",
      "rv_30d": 0.3822,
      "rv_60d": 0.4512,
      "iv_atm_target": 0.3423,
      "iv_atm_front": 0.2753,
      "iv_atm_back": 0.3558,
      "iv_term_slope": 0.0805,
      "iv_skew": 0.02,
      "iv_target_expiry": "2026-06-29",
      "fair_yes": 0.0,
      "market_yes": 0.009,
      "edge_pp": -0.9,
      "spread_pp": 1.4,
      "tradeable_edge_pp": -0.0,
      "liquidity": 896.0,
      "vol_24h": 191.0,
      "event_slug": "meta-above-in-june-2026",
      "market_id": "2388865"
    },
    {
      "ticker": "MSFT",
      "side": "above",
      "strike": 480.0,
      "close_date": "2026-06-30",
      "days": 7.21,
      "spot": 379.4,
      "sigma_used": 0.3386,
      "sigma_source": "iv_target",
      "rv_30d": 0.3394,
      "rv_60d": 0.3259,
      "iv_atm_target": 0.3386,
      "iv_atm_front": 0.2652,
      "iv_atm_back": 0.3268,
      "iv_term_slope": 0.0616,
      "iv_skew": 0.0264,
      "iv_target_expiry": "2026-06-29",
      "fair_yes": 0.0,
      "market_yes": 0.007,
      "edge_pp": -0.7,
      "spread_pp": 1.0,
      "tradeable_edge_pp": -0.0,
      "liquidity": 9606.0,
      "vol_24h": 631.0,
      "event_slug": "msft-above-in-june-2026",
      "market_id": "2388690"
    },
    {
      "ticker": "NFLX",
      "side": "above",
      "strike": 180.0,
      "close_date": "2026-06-30",
      "days": 7.21,
      "spot": 77.38,
      "sigma_used": 0.325,
      "sigma_source": "iv_target",
      "rv_30d": 0.2374,
      "rv_60d": 0.327,
      "iv_atm_target": 0.325,
      "iv_atm_front": 0.3123,
      "iv_atm_back": 0.4563,
      "iv_term_slope": 0.144,
      "iv_skew": 0.0005,
      "iv_target_expiry": "2026-07-02",
      "fair_yes": 0.0,
      "market_yes": 0.007,
      "edge_pp": -0.7,
      "spread_pp": 1.0,
      "tradeable_edge_pp": -0.0,
      "liquidity": 7023.0,
      "vol_24h": 1541.0,
      "event_slug": "nflx-above-in-june-2026",
      "market_id": "2389035"
    },
    {
      "ticker": "META",
      "side": "above",
      "strike": 720.0,
      "close_date": "2026-06-30",
      "days": 7.21,
      "spot": 577.22,
      "sigma_used": 0.3423,
      "sigma_source": "iv_target",
      "rv_30d": 0.3822,
      "rv_60d": 0.4512,
      "iv_atm_target": 0.3423,
      "iv_atm_front": 0.2753,
      "iv_atm_back": 0.3558,
      "iv_term_slope": 0.0805,
      "iv_skew": 0.02,
      "iv_target_expiry": "2026-06-29",
      "fair_yes": 0.0001,
      "market_yes": 0.0065,
      "edge_pp": -0.64,
      "spread_pp": 0.9,
      "tradeable_edge_pp": -0.0,
      "liquidity": 896.0,
      "vol_24h": 191.0,
      "event_slug": "meta-above-in-june-2026",
      "market_id": "2388863"
    },
    {
      "ticker": "NVDA",
      "side": "above",
      "strike": 270.0,
      "close_date": "2026-06-30",
      "days": 7.21,
      "spot": 210.69,
      "sigma_used": 0.3631,
      "sigma_source": "iv_target",
      "rv_30d": 0.4323,
      "rv_60d": 0.413,
      "iv_atm_target": 0.3631,
      "iv_atm_front": 0.2975,
      "iv_atm_back": 0.3743,
      "iv_term_slope": 0.0768,
      "iv_skew": 0.0654,
      "iv_target_expiry": "2026-06-29",
      "fair_yes": 0.0,
      "market_yes": 0.006,
      "edge_pp": -0.6,
      "spread_pp": 0.8,
      "tradeable_edge_pp": -0.0,
      "liquidity": 7497.0,
      "vol_24h": 606.0,
      "event_slug": "nvda-above-in-june-2026",
      "market_id": "2388981"
    },
    {
      "ticker": "NFLX",
      "side": "above",
      "strike": 160.0,
      "close_date": "2026-06-30",
      "days": 7.21,
      "spot": 77.38,
      "sigma_used": 0.325,
      "sigma_source": "iv_target",
      "rv_30d": 0.2374,
      "rv_60d": 0.327,
      "iv_atm_target": 0.325,
      "iv_atm_front": 0.3123,
      "iv_atm_back": 0.4563,
      "iv_term_slope": 0.144,
      "iv_skew": 0.0005,
      "iv_target_expiry": "2026-07-02",
      "fair_yes": 0.0,
      "market_yes": 0.006,
      "edge_pp": -0.6,
      "spread_pp": 0.8,
      "tradeable_edge_pp": -0.0,
      "liquidity": 7023.0,
      "vol_24h": 192.0,
      "event_slug": "nflx-above-in-june-2026",
      "market_id": "2389033"
    },
    {
      "ticker": "NVDA",
      "side": "above",
      "strike": 160.0,
      "close_date": "2026-06-30",
      "days": 7.21,
      "spot": 210.69,
      "sigma_used": 0.3631,
      "sigma_source": "iv_target",
      "rv_30d": 0.4323,
      "rv_60d": 0.413,
      "iv_atm_target": 0.3631,
      "iv_atm_front": 0.2975,
      "iv_atm_back": 0.3743,
      "iv_term_slope": 0.0768,
      "iv_skew": 0.0654,
      "iv_target_expiry": "2026-06-29",
      "fair_yes": 1.0,
      "market_yes": 0.9945,
      "edge_pp": 0.55,
      "spread_pp": 0.9,
      "tradeable_edge_pp": 0.0,
      "liquidity": 7497.0,
      "vol_24h": 210.0,
      "event_slug": "nvda-above-in-june-2026",
      "market_id": "2388954"
    },
    {
      "ticker": "NFLX",
      "side": "above",
      "strike": 140.0,
      "close_date": "2026-06-30",
      "days": 7.21,
      "spot": 77.38,
      "sigma_used": 0.325,
      "sigma_source": "iv_target",
      "rv_30d": 0.2374,
      "rv_60d": 0.327,
      "iv_atm_target": 0.325,
      "iv_atm_front": 0.3123,
      "iv_atm_back": 0.4563,
      "iv_term_slope": 0.144,
      "iv_skew": 0.0005,
      "iv_target_expiry": "2026-07-02",
      "fair_yes": 0.0,
      "market_yes": 0.0055,
      "edge_pp": -0.55,
      "spread_pp": 0.7,
      "tradeable_edge_pp": -0.0,
      "liquidity": 7023.0,
      "vol_24h": 248.0,
      "event_slug": "nflx-above-in-june-2026",
      "market_id": "2389030"
    },
    {
      "ticker": "NFLX",
      "side": "above",
      "strike": 20.0,
      "close_date": "2026-06-30",
      "days": 7.21,
      "spot": 77.38,
      "sigma_used": 0.325,
      "sigma_source": "iv_target",
      "rv_30d": 0.2374,
      "rv_60d": 0.327,
      "iv_atm_target": 0.325,
      "iv_atm_front": 0.3123,
      "iv_atm_back": 0.4563,
      "iv_term_slope": 0.144,
      "iv_skew": 0.0005,
      "iv_target_expiry": "2026-07-02",
      "fair_yes": 1.0,
      "market_yes": 0.997,
      "edge_pp": 0.3,
      "spread_pp": 0.6,
      "tradeable_edge_pp": 0.0,
      "liquidity": 7023.0,
      "vol_24h": 631.0,
      "event_slug": "nflx-above-in-june-2026",
      "market_id": "2389015"
    },
    {
      "ticker": "TSLA",
      "side": "above",
      "strike": 500.0,
      "close_date": "2026-06-30",
      "days": 7.21,
      "spot": 400.49,
      "sigma_used": 0.3963,
      "sigma_source": "iv_target",
      "rv_30d": 0.4764,
      "rv_60d": 0.4475,
      "iv_atm_target": 0.3963,
      "iv_atm_front": 0.3296,
      "iv_atm_back": 0.462,
      "iv_term_slope": 0.1324,
      "iv_skew": 0.0273,
      "iv_target_expiry": "2026-06-29",
      "fair_yes": 0.0004,
      "market_yes": 0.002,
      "edge_pp": -0.16,
      "spread_pp": 0.2,
      "tradeable_edge_pp": -0.0,
      "liquidity": 10991.0,
      "vol_24h": 336.0,
      "event_slug": "tsla-above-in-june-2026",
      "market_id": "2388918"
    },
    {
      "ticker": "MSFT",
      "side": "above",
      "strike": 495.0,
      "close_date": "2026-06-30",
      "days": 7.21,
      "spot": 379.4,
      "sigma_used": 0.3386,
      "sigma_source": "iv_target",
      "rv_30d": 0.3394,
      "rv_60d": 0.3259,
      "iv_atm_target": 0.3386,
      "iv_atm_front": 0.2652,
      "iv_atm_back": 0.3268,
      "iv_term_slope": 0.0616,
      "iv_skew": 0.0264,
      "iv_target_expiry": "2026-06-29",
      "fair_yes": 0.0,
      "market_yes": 0.0015,
      "edge_pp": -0.15,
      "spread_pp": 0.1,
      "tradeable_edge_pp": -0.05,
      "liquidity": 9606.0,
      "vol_24h": 258.0,
      "event_slug": "msft-above-in-june-2026",
      "market_id": "2388693"
    },
    {
      "ticker": "MSFT",
      "side": "above",
      "strike": 510.0,
      "close_date": "2026-06-30",
      "days": 7.21,
      "spot": 379.4,
      "sigma_used": 0.3386,
      "sigma_source": "iv_target",
      "rv_30d": 0.3394,
      "rv_60d": 0.3259,
      "iv_atm_target": 0.3386,
      "iv_atm_front": 0.2652,
      "iv_atm_back": 0.3268,
      "iv_term_slope": 0.0616,
      "iv_skew": 0.0264,
      "iv_target_expiry": "2026-06-29",
      "fair_yes": 0.0,
      "market_yes": 0.001,
      "edge_pp": -0.1,
      "spread_pp": null,
      "tradeable_edge_pp": null,
      "liquidity": 9606.0,
      "vol_24h": 751.0,
      "event_slug": "msft-above-in-june-2026",
      "market_id": "2388697"
    },
    {
      "ticker": "META",
      "side": "above",
      "strike": 560.0,
      "close_date": "2026-06-30",
      "days": 7.21,
      "spot": 577.22,
      "sigma_used": 0.3423,
      "sigma_source": "iv_target",
      "rv_30d": 0.3822,
      "rv_60d": 0.4512,
      "iv_atm_target": 0.3423,
      "iv_atm_front": 0.2753,
      "iv_atm_back": 0.3558,
      "iv_term_slope": 0.0805,
      "iv_skew": 0.02,
      "iv_target_expiry": "2026-06-29",
      "fair_yes": 0.6893,
      "market_yes": 0.69,
      "edge_pp": -0.07,
      "spread_pp": 46.0,
      "tradeable_edge_pp": -0.0,
      "liquidity": 896.0,
      "vol_24h": 72.0,
      "event_slug": "meta-above-in-june-2026",
      "market_id": "2388853"
    },
    {
      "ticker": "NFLX",
      "side": "above",
      "strike": 200.0,
      "close_date": "2026-06-30",
      "days": 7.21,
      "spot": 77.38,
      "sigma_used": 0.325,
      "sigma_source": "iv_target",
      "rv_30d": 0.2374,
      "rv_60d": 0.327,
      "iv_atm_target": 0.325,
      "iv_atm_front": 0.3123,
      "iv_atm_back": 0.4563,
      "iv_term_slope": 0.144,
      "iv_skew": 0.0005,
      "iv_target_expiry": "2026-07-02",
      "fair_yes": 0.0,
      "market_yes": 0.0005,
      "edge_pp": -0.05,
      "spread_pp": null,
      "tradeable_edge_pp": null,
      "liquidity": 7023.0,
      "vol_24h": 1422.0,
      "event_slug": "nflx-above-in-june-2026",
      "market_id": "2389036"
    }
  ]
}