{
  "generated_at": "2026-06-05T23:57:51.587455+00:00",
  "schema_version": 2,
  "universe": [
    "AAPL",
    "AMD",
    "AMZN",
    "AVGO",
    "CRM",
    "GOOG",
    "HD",
    "INTC",
    "INTU",
    "LOW",
    "META",
    "MSFT",
    "NFLX",
    "NVDA",
    "ORCL",
    "QQQ",
    "SPY",
    "TSLA",
    "WMT"
  ],
  "n_scored": 129,
  "filter": {
    "min_liquidity_usd": 500.0,
    "min_abs_edge_pp": 0
  },
  "signals": [
    {
      "ticker": "NVDA",
      "side": "above",
      "strike": 150.0,
      "close_date": "2026-06-30",
      "days": 17.74,
      "spot": 205.1,
      "sigma_used": 0.4151,
      "sigma_source": "iv_target",
      "rv_30d": 0.4744,
      "rv_60d": 0.4013,
      "iv_atm_target": 0.4151,
      "iv_atm_front": 0.0542,
      "iv_atm_back": 0.4051,
      "iv_term_slope": 0.3509,
      "iv_skew": 0.0312,
      "iv_target_expiry": "2026-07-02",
      "fair_yes": 0.9973,
      "market_yes": 0.5,
      "edge_pp": 49.73,
      "spread_pp": 97.8,
      "tradeable_edge_pp": 0.0,
      "liquidity": 1030.0,
      "vol_24h": 0,
      "event_slug": "nvda-above-in-june-2026",
      "market_id": "2388953"
    },
    {
      "ticker": "META",
      "side": "above",
      "strike": 760.0,
      "close_date": "2026-06-30",
      "days": 17.74,
      "spot": 593.0,
      "sigma_used": 0.3633,
      "sigma_source": "iv_target",
      "rv_30d": 0.4073,
      "rv_60d": 0.4398,
      "iv_atm_target": 0.3633,
      "iv_atm_front": 0.1119,
      "iv_atm_back": 0.3524,
      "iv_term_slope": 0.2405,
      "iv_skew": 0.0312,
      "iv_target_expiry": "2026-07-02",
      "fair_yes": 0.0044,
      "market_yes": 0.5,
      "edge_pp": -49.56,
      "spread_pp": 97.8,
      "tradeable_edge_pp": -0.0,
      "liquidity": 888.0,
      "vol_24h": 0,
      "event_slug": "meta-above-in-june-2026",
      "market_id": "2388867"
    },
    {
      "ticker": "AMZN",
      "side": "above",
      "strike": 310.0,
      "close_date": "2026-06-30",
      "days": 17.74,
      "spot": 246.03,
      "sigma_used": 0.3417,
      "sigma_source": "iv_target",
      "rv_30d": 0.2697,
      "rv_60d": 0.3027,
      "iv_atm_target": 0.3417,
      "iv_atm_front": 0.1113,
      "iv_atm_back": 0.3385,
      "iv_term_slope": 0.2272,
      "iv_skew": 0.0078,
      "iv_target_expiry": "2026-07-02",
      "fair_yes": 0.0047,
      "market_yes": 0.5,
      "edge_pp": -49.53,
      "spread_pp": 97.8,
      "tradeable_edge_pp": -0.0,
      "liquidity": 723.0,
      "vol_24h": 0,
      "event_slug": "amzn-above-in-june-2026",
      "market_id": "2388755"
    },
    {
      "ticker": "MSFT",
      "side": "above",
      "strike": 510.0,
      "close_date": "2026-06-30",
      "days": 17.74,
      "spot": 416.67,
      "sigma_used": 0.3017,
      "sigma_source": "iv_target",
      "rv_30d": 0.3332,
      "rv_60d": 0.3166,
      "iv_atm_target": 0.3017,
      "iv_atm_front": 0.0761,
      "iv_atm_back": 0.3118,
      "iv_term_slope": 0.2357,
      "iv_skew": 0.1738,
      "iv_target_expiry": "2026-07-02",
      "fair_yes": 0.0052,
      "market_yes": 0.5,
      "edge_pp": -49.48,
      "spread_pp": 97.8,
      "tradeable_edge_pp": -0.0,
      "liquidity": 731.0,
      "vol_24h": 0,
      "event_slug": "msft-above-in-june-2026",
      "market_id": "2388697"
    },
    {
      "ticker": "NVDA",
      "side": "above",
      "strike": 270.0,
      "close_date": "2026-06-30",
      "days": 17.74,
      "spot": 205.1,
      "sigma_used": 0.4151,
      "sigma_source": "iv_target",
      "rv_30d": 0.4744,
      "rv_60d": 0.4013,
      "iv_atm_target": 0.4151,
      "iv_atm_front": 0.0542,
      "iv_atm_back": 0.4051,
      "iv_term_slope": 0.3509,
      "iv_skew": 0.0312,
      "iv_target_expiry": "2026-07-02",
      "fair_yes": 0.0054,
      "market_yes": 0.5,
      "edge_pp": -49.46,
      "spread_pp": 97.8,
      "tradeable_edge_pp": -0.0,
      "liquidity": 1030.0,
      "vol_24h": 0,
      "event_slug": "nvda-above-in-june-2026",
      "market_id": "2388981"
    },
    {
      "ticker": "AAPL",
      "side": "above",
      "strike": 250.0,
      "close_date": "2026-06-30",
      "days": 17.74,
      "spot": 307.34,
      "sigma_used": 0.258,
      "sigma_source": "iv_target",
      "rv_30d": 0.2027,
      "rv_60d": 0.223,
      "iv_atm_target": 0.258,
      "iv_atm_front": 0.0679,
      "iv_atm_back": 0.2557,
      "iv_term_slope": 0.1878,
      "iv_skew": 0.0078,
      "iv_target_expiry": "2026-07-02",
      "fair_yes": 0.9986,
      "market_yes": 0.5045,
      "edge_pp": 49.41,
      "spread_pp": 96.7,
      "tradeable_edge_pp": 0.0,
      "liquidity": 634.0,
      "vol_24h": 10.0,
      "event_slug": "aapl-above-in-june-2026",
      "market_id": "2388559"
    },
    {
      "ticker": "AAPL",
      "side": "above",
      "strike": 260.0,
      "close_date": "2026-06-30",
      "days": 17.74,
      "spot": 307.34,
      "sigma_used": 0.258,
      "sigma_source": "iv_target",
      "rv_30d": 0.2027,
      "rv_60d": 0.223,
      "iv_atm_target": 0.258,
      "iv_atm_front": 0.0679,
      "iv_atm_back": 0.2557,
      "iv_term_slope": 0.1878,
      "iv_skew": 0.0078,
      "iv_target_expiry": "2026-07-02",
      "fair_yes": 0.992,
      "market_yes": 0.5,
      "edge_pp": 49.2,
      "spread_pp": 97.8,
      "tradeable_edge_pp": 0.0,
      "liquidity": 634.0,
      "vol_24h": 0,
      "event_slug": "aapl-above-in-june-2026",
      "market_id": "2388562"
    },
    {
      "ticker": "AMZN",
      "side": "above",
      "strike": 330.0,
      "close_date": "2026-06-30",
      "days": 17.74,
      "spot": 246.03,
      "sigma_used": 0.3417,
      "sigma_source": "iv_target",
      "rv_30d": 0.2697,
      "rv_60d": 0.3027,
      "iv_atm_target": 0.3417,
      "iv_atm_front": 0.1113,
      "iv_atm_back": 0.3385,
      "iv_term_slope": 0.2272,
      "iv_skew": 0.0078,
      "iv_target_expiry": "2026-07-02",
      "fair_yes": 0.0005,
      "market_yes": 0.4925,
      "edge_pp": -49.2,
      "spread_pp": 97.9,
      "tradeable_edge_pp": -0.0,
      "liquidity": 723.0,
      "vol_24h": 162.0,
      "event_slug": "amzn-above-in-june-2026",
      "market_id": "2388762"
    },
    {
      "ticker": "META",
      "side": "above",
      "strike": 740.0,
      "close_date": "2026-06-30",
      "days": 17.74,
      "spot": 593.0,
      "sigma_used": 0.3633,
      "sigma_source": "iv_target",
      "rv_30d": 0.4073,
      "rv_60d": 0.4398,
      "iv_atm_target": 0.3633,
      "iv_atm_front": 0.1119,
      "iv_atm_back": 0.3524,
      "iv_term_slope": 0.2405,
      "iv_skew": 0.0312,
      "iv_target_expiry": "2026-07-02",
      "fair_yes": 0.0095,
      "market_yes": 0.501,
      "edge_pp": -49.15,
      "spread_pp": 97.6,
      "tradeable_edge_pp": -0.0,
      "liquidity": 888.0,
      "vol_24h": 0,
      "event_slug": "meta-above-in-june-2026",
      "market_id": "2388865"
    },
    {
      "ticker": "AMZN",
      "side": "above",
      "strike": 320.0,
      "close_date": "2026-06-30",
      "days": 17.74,
      "spot": 246.03,
      "sigma_used": 0.3417,
      "sigma_source": "iv_target",
      "rv_30d": 0.2697,
      "rv_60d": 0.3027,
      "iv_atm_target": 0.3417,
      "iv_atm_front": 0.1113,
      "iv_atm_back": 0.3385,
      "iv_term_slope": 0.2272,
      "iv_skew": 0.0078,
      "iv_target_expiry": "2026-07-02",
      "fair_yes": 0.0016,
      "market_yes": 0.493,
      "edge_pp": -49.14,
      "spread_pp": 97.2,
      "tradeable_edge_pp": -0.0,
      "liquidity": 723.0,
      "vol_24h": 178.0,
      "event_slug": "amzn-above-in-june-2026",
      "market_id": "2388759"
    },
    {
      "ticker": "AAPL",
      "side": "above",
      "strike": 360.0,
      "close_date": "2026-06-30",
      "days": 17.74,
      "spot": 307.34,
      "sigma_used": 0.258,
      "sigma_source": "iv_target",
      "rv_30d": 0.2027,
      "rv_60d": 0.223,
      "iv_atm_target": 0.258,
      "iv_atm_front": 0.0679,
      "iv_atm_back": 0.2557,
      "iv_term_slope": 0.1878,
      "iv_skew": 0.0078,
      "iv_target_expiry": "2026-07-02",
      "fair_yes": 0.0095,
      "market_yes": 0.5,
      "edge_pp": -49.05,
      "spread_pp": 97.8,
      "tradeable_edge_pp": -0.0,
      "liquidity": 634.0,
      "vol_24h": 0,
      "event_slug": "aapl-above-in-june-2026",
      "market_id": "2388616"
    },
    {
      "ticker": "MSFT",
      "side": "above",
      "strike": 330.0,
      "close_date": "2026-06-30",
      "days": 17.74,
      "spot": 416.67,
      "sigma_used": 0.3017,
      "sigma_source": "iv_target",
      "rv_30d": 0.3332,
      "rv_60d": 0.3166,
      "iv_atm_target": 0.3017,
      "iv_atm_front": 0.0761,
      "iv_atm_back": 0.3118,
      "iv_term_slope": 0.2357,
      "iv_skew": 0.1738,
      "iv_target_expiry": "2026-07-02",
      "fair_yes": 0.998,
      "market_yes": 0.51,
      "edge_pp": 48.8,
      "spread_pp": 95.8,
      "tradeable_edge_pp": 0.0,
      "liquidity": 731.0,
      "vol_24h": 0,
      "event_slug": "msft-above-in-june-2026",
      "market_id": "2388649"
    },
    {
      "ticker": "AMZN",
      "side": "above",
      "strike": 300.0,
      "close_date": "2026-06-30",
      "days": 17.74,
      "spot": 246.03,
      "sigma_used": 0.3417,
      "sigma_source": "iv_target",
      "rv_30d": 0.2697,
      "rv_60d": 0.3027,
      "iv_atm_target": 0.3417,
      "iv_atm_front": 0.1113,
      "iv_atm_back": 0.3385,
      "iv_term_slope": 0.2272,
      "iv_skew": 0.0078,
      "iv_target_expiry": "2026-07-02",
      "fair_yes": 0.0128,
      "market_yes": 0.5,
      "edge_pp": -48.72,
      "spread_pp": 97.8,
      "tradeable_edge_pp": -0.0,
      "liquidity": 723.0,
      "vol_24h": 0,
      "event_slug": "amzn-above-in-june-2026",
      "market_id": "2388750"
    },
    {
      "ticker": "NVDA",
      "side": "above",
      "strike": 260.0,
      "close_date": "2026-06-30",
      "days": 17.74,
      "spot": 205.1,
      "sigma_used": 0.4151,
      "sigma_source": "iv_target",
      "rv_30d": 0.4744,
      "rv_60d": 0.4013,
      "iv_atm_target": 0.4151,
      "iv_atm_front": 0.0542,
      "iv_atm_back": 0.4051,
      "iv_term_slope": 0.3509,
      "iv_skew": 0.0312,
      "iv_target_expiry": "2026-07-02",
      "fair_yes": 0.0136,
      "market_yes": 0.5,
      "edge_pp": -48.64,
      "spread_pp": 97.8,
      "tradeable_edge_pp": -0.0,
      "liquidity": 1030.0,
      "vol_24h": 0,
      "event_slug": "nvda-above-in-june-2026",
      "market_id": "2388978"
    },
    {
      "ticker": "MSFT",
      "side": "above",
      "strike": 495.0,
      "close_date": "2026-06-30",
      "days": 17.74,
      "spot": 416.67,
      "sigma_used": 0.3017,
      "sigma_source": "iv_target",
      "rv_30d": 0.3332,
      "rv_60d": 0.3166,
      "iv_atm_target": 0.3017,
      "iv_atm_front": 0.0761,
      "iv_atm_back": 0.3118,
      "iv_term_slope": 0.2357,
      "iv_skew": 0.1738,
      "iv_target_expiry": "2026-07-02",
      "fair_yes": 0.0142,
      "market_yes": 0.5,
      "edge_pp": -48.58,
      "spread_pp": 97.8,
      "tradeable_edge_pp": -0.0,
      "liquidity": 731.0,
      "vol_24h": 0,
      "event_slug": "msft-above-in-june-2026",
      "market_id": "2388693"
    },
    {
      "ticker": "META",
      "side": "above",
      "strike": 720.0,
      "close_date": "2026-06-30",
      "days": 17.74,
      "spot": 593.0,
      "sigma_used": 0.3633,
      "sigma_source": "iv_target",
      "rv_30d": 0.4073,
      "rv_60d": 0.4398,
      "iv_atm_target": 0.3633,
      "iv_atm_front": 0.1119,
      "iv_atm_back": 0.3524,
      "iv_term_slope": 0.2405,
      "iv_skew": 0.0312,
      "iv_target_expiry": "2026-07-02",
      "fair_yes": 0.0196,
      "market_yes": 0.5,
      "edge_pp": -48.04,
      "spread_pp": 97.8,
      "tradeable_edge_pp": -0.0,
      "liquidity": 888.0,
      "vol_24h": 0,
      "event_slug": "meta-above-in-june-2026",
      "market_id": "2388863"
    },
    {
      "ticker": "NFLX",
      "side": "above",
      "strike": 100.0,
      "close_date": "2026-06-30",
      "days": 17.74,
      "spot": 82.18,
      "sigma_used": 0.3026,
      "sigma_source": "iv_target",
      "rv_30d": 0.2292,
      "rv_60d": 0.3247,
      "iv_atm_target": 0.3026,
      "iv_atm_front": 0.0962,
      "iv_atm_back": 0.3219,
      "iv_term_slope": 0.2257,
      "iv_skew": 0.0469,
      "iv_target_expiry": "2026-07-02",
      "fair_yes": 0.0065,
      "market_yes": 0.4865,
      "edge_pp": -48.0,
      "spread_pp": 92.5,
      "tradeable_edge_pp": -0.0,
      "liquidity": 558.0,
      "vol_24h": 0,
      "event_slug": "nflx-above-in-june-2026",
      "market_id": "2389027"
    },
    {
      "ticker": "NVDA",
      "side": "above",
      "strike": 250.0,
      "close_date": "2026-06-30",
      "days": 17.74,
      "spot": 205.1,
      "sigma_used": 0.4151,
      "sigma_source": "iv_target",
      "rv_30d": 0.4744,
      "rv_60d": 0.4013,
      "iv_atm_target": 0.4151,
      "iv_atm_front": 0.0542,
      "iv_atm_back": 0.4051,
      "iv_term_slope": 0.3509,
      "iv_skew": 0.0312,
      "iv_target_expiry": "2026-07-02",
      "fair_yes": 0.032,
      "market_yes": 0.51,
      "edge_pp": -47.8,
      "spread_pp": 96.0,
      "tradeable_edge_pp": -0.0,
      "liquidity": 1030.0,
      "vol_24h": 0,
      "event_slug": "nvda-above-in-june-2026",
      "market_id": "2388975"
    },
    {
      "ticker": "NFLX",
      "side": "above",
      "strike": 60.0,
      "close_date": "2026-06-30",
      "days": 17.74,
      "spot": 82.18,
      "sigma_used": 0.3026,
      "sigma_source": "iv_target",
      "rv_30d": 0.2292,
      "rv_60d": 0.3247,
      "iv_atm_target": 0.3026,
      "iv_atm_front": 0.0962,
      "iv_atm_back": 0.3219,
      "iv_term_slope": 0.2257,
      "iv_skew": 0.0469,
      "iv_target_expiry": "2026-07-02",
      "fair_yes": 0.9999,
      "market_yes": 0.523,
      "edge_pp": 47.69,
      "spread_pp": 94.0,
      "tradeable_edge_pp": 0.0,
      "liquidity": 558.0,
      "vol_24h": 0,
      "event_slug": "nflx-above-in-june-2026",
      "market_id": "2389022"
    },
    {
      "ticker": "TSLA",
      "side": "above",
      "strike": 500.0,
      "close_date": "2026-06-30",
      "days": 17.74,
      "spot": 391.0,
      "sigma_used": 0.4881,
      "sigma_source": "iv_target",
      "rv_30d": 0.42,
      "rv_60d": 0.434,
      "iv_atm_target": 0.4881,
      "iv_atm_front": 0.0779,
      "iv_atm_back": 0.4817,
      "iv_term_slope": 0.4039,
      "iv_skew": 0.0742,
      "iv_target_expiry": "2026-07-02",
      "fair_yes": 0.0248,
      "market_yes": 0.5,
      "edge_pp": -47.52,
      "spread_pp": 98.0,
      "tradeable_edge_pp": -0.0,
      "liquidity": 1668.0,
      "vol_24h": 3.0,
      "event_slug": "tsla-above-in-june-2026",
      "market_id": "2388918"
    },
    {
      "ticker": "AAPL",
      "side": "above",
      "strike": 350.0,
      "close_date": "2026-06-30",
      "days": 17.74,
      "spot": 307.34,
      "sigma_used": 0.258,
      "sigma_source": "iv_target",
      "rv_30d": 0.2027,
      "rv_60d": 0.223,
      "iv_atm_target": 0.258,
      "iv_atm_front": 0.0679,
      "iv_atm_back": 0.2557,
      "iv_term_slope": 0.1878,
      "iv_skew": 0.0078,
      "iv_target_expiry": "2026-07-02",
      "fair_yes": 0.0266,
      "market_yes": 0.5005,
      "edge_pp": -47.39,
      "spread_pp": 97.7,
      "tradeable_edge_pp": -0.0,
      "liquidity": 634.0,
      "vol_24h": 0,
      "event_slug": "aapl-above-in-june-2026",
      "market_id": "2388611"
    },
    {
      "ticker": "TSLA",
      "side": "above",
      "strike": 480.0,
      "close_date": "2026-06-30",
      "days": 17.74,
      "spot": 391.0,
      "sigma_used": 0.4881,
      "sigma_source": "iv_target",
      "rv_30d": 0.42,
      "rv_60d": 0.434,
      "iv_atm_target": 0.4881,
      "iv_atm_front": 0.0779,
      "iv_atm_back": 0.4817,
      "iv_term_slope": 0.4039,
      "iv_skew": 0.0742,
      "iv_target_expiry": "2026-07-02",
      "fair_yes": 0.0497,
      "market_yes": 0.52,
      "edge_pp": -47.03,
      "spread_pp": 94.0,
      "tradeable_edge_pp": -0.0,
      "liquidity": 1668.0,
      "vol_24h": 0,
      "event_slug": "tsla-above-in-june-2026",
      "market_id": "2388914"
    },
    {
      "ticker": "NFLX",
      "side": "above",
      "strike": 140.0,
      "close_date": "2026-06-30",
      "days": 17.74,
      "spot": 82.18,
      "sigma_used": 0.3026,
      "sigma_source": "iv_target",
      "rv_30d": 0.2292,
      "rv_60d": 0.3247,
      "iv_atm_target": 0.3026,
      "iv_atm_front": 0.0962,
      "iv_atm_back": 0.3219,
      "iv_term_slope": 0.2257,
      "iv_skew": 0.0469,
      "iv_target_expiry": "2026-07-02",
      "fair_yes": 0.0,
      "market_yes": 0.47,
      "edge_pp": -47.0,
      "spread_pp": 92.8,
      "tradeable_edge_pp": -0.0,
      "liquidity": 558.0,
      "vol_24h": 90,
      "event_slug": "nflx-above-in-june-2026",
      "market_id": "2389030"
    },
    {
      "ticker": "MSFT",
      "side": "above",
      "strike": 345.0,
      "close_date": "2026-06-30",
      "days": 17.74,
      "spot": 416.67,
      "sigma_used": 0.3017,
      "sigma_source": "iv_target",
      "rv_30d": 0.3332,
      "rv_60d": 0.3166,
      "iv_atm_target": 0.3017,
      "iv_atm_front": 0.0761,
      "iv_atm_back": 0.3118,
      "iv_term_slope": 0.2357,
      "iv_skew": 0.1738,
      "iv_target_expiry": "2026-07-02",
      "fair_yes": 0.9898,
      "market_yes": 0.52,
      "edge_pp": 46.98,
      "spread_pp": 93.8,
      "tradeable_edge_pp": 0.0,
      "liquidity": 731.0,
      "vol_24h": 0,
      "event_slug": "msft-above-in-june-2026",
      "market_id": "2388653"
    },
    {
      "ticker": "TSLA",
      "side": "above",
      "strike": 490.0,
      "close_date": "2026-06-30",
      "days": 17.74,
      "spot": 391.0,
      "sigma_used": 0.4881,
      "sigma_source": "iv_target",
      "rv_30d": 0.42,
      "rv_60d": 0.434,
      "iv_atm_target": 0.4881,
      "iv_atm_front": 0.0779,
      "iv_atm_back": 0.4817,
      "iv_term_slope": 0.4039,
      "iv_skew": 0.0742,
      "iv_target_expiry": "2026-07-02",
      "fair_yes": 0.0353,
      "market_yes": 0.505,
      "edge_pp": -46.97,
      "spread_pp": 93.0,
      "tradeable_edge_pp": -0.0,
      "liquidity": 1668.0,
      "vol_24h": 194.0,
      "event_slug": "tsla-above-in-june-2026",
      "market_id": "2388916"
    },
    {
      "ticker": "AMZN",
      "side": "above",
      "strike": 290.0,
      "close_date": "2026-06-30",
      "days": 17.74,
      "spot": 246.03,
      "sigma_used": 0.3417,
      "sigma_source": "iv_target",
      "rv_30d": 0.2697,
      "rv_60d": 0.3027,
      "iv_atm_target": 0.3417,
      "iv_atm_front": 0.1113,
      "iv_atm_back": 0.3385,
      "iv_term_slope": 0.2272,
      "iv_skew": 0.0078,
      "iv_target_expiry": "2026-07-02",
      "fair_yes": 0.0315,
      "market_yes": 0.5,
      "edge_pp": -46.85,
      "spread_pp": 98.0,
      "tradeable_edge_pp": -0.0,
      "liquidity": 723.0,
      "vol_24h": 0,
      "event_slug": "amzn-above-in-june-2026",
      "market_id": "2388746"
    },
    {
      "ticker": "AAPL",
      "side": "above",
      "strike": 270.0,
      "close_date": "2026-06-30",
      "days": 17.74,
      "spot": 307.34,
      "sigma_used": 0.258,
      "sigma_source": "iv_target",
      "rv_30d": 0.2027,
      "rv_60d": 0.223,
      "iv_atm_target": 0.258,
      "iv_atm_front": 0.0679,
      "iv_atm_back": 0.2557,
      "iv_term_slope": 0.1878,
      "iv_skew": 0.0078,
      "iv_target_expiry": "2026-07-02",
      "fair_yes": 0.9684,
      "market_yes": 0.5,
      "edge_pp": 46.84,
      "spread_pp": 95.8,
      "tradeable_edge_pp": 0.0,
      "liquidity": 634.0,
      "vol_24h": 0,
      "event_slug": "aapl-above-in-june-2026",
      "market_id": "2388564"
    },
    {
      "ticker": "NVDA",
      "side": "above",
      "strike": 160.0,
      "close_date": "2026-06-30",
      "days": 17.74,
      "spot": 205.1,
      "sigma_used": 0.4151,
      "sigma_source": "iv_target",
      "rv_30d": 0.4744,
      "rv_60d": 0.4013,
      "iv_atm_target": 0.4151,
      "iv_atm_front": 0.0542,
      "iv_atm_back": 0.4051,
      "iv_term_slope": 0.3509,
      "iv_skew": 0.0312,
      "iv_target_expiry": "2026-07-02",
      "fair_yes": 0.9861,
      "market_yes": 0.518,
      "edge_pp": 46.81,
      "spread_pp": 92.0,
      "tradeable_edge_pp": 0.0,
      "liquidity": 1030.0,
      "vol_24h": 0,
      "event_slug": "nvda-above-in-june-2026",
      "market_id": "2388954"
    },
    {
      "ticker": "NFLX",
      "side": "above",
      "strike": 160.0,
      "close_date": "2026-06-30",
      "days": 17.74,
      "spot": 82.18,
      "sigma_used": 0.3026,
      "sigma_source": "iv_target",
      "rv_30d": 0.2292,
      "rv_60d": 0.3247,
      "iv_atm_target": 0.3026,
      "iv_atm_front": 0.0962,
      "iv_atm_back": 0.3219,
      "iv_term_slope": 0.2257,
      "iv_skew": 0.0469,
      "iv_target_expiry": "2026-07-02",
      "fair_yes": 0.0,
      "market_yes": 0.4665,
      "edge_pp": -46.65,
      "spread_pp": 92.7,
      "tradeable_edge_pp": -0.0,
      "liquidity": 558.0,
      "vol_24h": 78.0,
      "event_slug": "nflx-above-in-june-2026",
      "market_id": "2389033"
    },
    {
      "ticker": "META",
      "side": "above",
      "strike": 700.0,
      "close_date": "2026-06-30",
      "days": 17.74,
      "spot": 593.0,
      "sigma_used": 0.3633,
      "sigma_source": "iv_target",
      "rv_30d": 0.4073,
      "rv_60d": 0.4398,
      "iv_atm_target": 0.3633,
      "iv_atm_front": 0.1119,
      "iv_atm_back": 0.3524,
      "iv_term_slope": 0.2405,
      "iv_skew": 0.0312,
      "iv_target_expiry": "2026-07-02",
      "fair_yes": 0.0384,
      "market_yes": 0.5,
      "edge_pp": -46.16,
      "spread_pp": 97.8,
      "tradeable_edge_pp": -0.0,
      "liquidity": 888.0,
      "vol_24h": 0,
      "event_slug": "meta-above-in-june-2026",
      "market_id": "2388861"
    },
    {
      "ticker": "TSLA",
      "side": "above",
      "strike": 470.0,
      "close_date": "2026-06-30",
      "days": 17.74,
      "spot": 391.0,
      "sigma_used": 0.4881,
      "sigma_source": "iv_target",
      "rv_30d": 0.42,
      "rv_60d": 0.434,
      "iv_atm_target": 0.4881,
      "iv_atm_front": 0.0779,
      "iv_atm_back": 0.4817,
      "iv_term_slope": 0.4039,
      "iv_skew": 0.0742,
      "iv_target_expiry": "2026-07-02",
      "fair_yes": 0.0687,
      "market_yes": 0.53,
      "edge_pp": -46.13,
      "spread_pp": 92.0,
      "tradeable_edge_pp": -0.0,
      "liquidity": 1668.0,
      "vol_24h": 0,
      "event_slug": "tsla-above-in-june-2026",
      "market_id": "2388912"
    },
    {
      "ticker": "NFLX",
      "side": "above",
      "strike": 120.0,
      "close_date": "2026-06-30",
      "days": 17.74,
      "spot": 82.18,
      "sigma_used": 0.3026,
      "sigma_source": "iv_target",
      "rv_30d": 0.2292,
      "rv_60d": 0.3247,
      "iv_atm_target": 0.3026,
      "iv_atm_front": 0.0962,
      "iv_atm_back": 0.3219,
      "iv_term_slope": 0.2257,
      "iv_skew": 0.0469,
      "iv_target_expiry": "2026-07-02",
      "fair_yes": 0.0,
      "market_yes": 0.461,
      "edge_pp": -46.1,
      "spread_pp": 89.8,
      "tradeable_edge_pp": -0.0,
      "liquidity": 558.0,
      "vol_24h": 44.0,
      "event_slug": "nflx-above-in-june-2026",
      "market_id": "2389029"
    },
    {
      "ticker": "MSFT",
      "side": "above",
      "strike": 360.0,
      "close_date": "2026-06-30",
      "days": 17.74,
      "spot": 416.67,
      "sigma_used": 0.3017,
      "sigma_source": "iv_target",
      "rv_30d": 0.3332,
      "rv_60d": 0.3166,
      "iv_atm_target": 0.3017,
      "iv_atm_front": 0.0761,
      "iv_atm_back": 0.3118,
      "iv_term_slope": 0.2357,
      "iv_skew": 0.1738,
      "iv_target_expiry": "2026-07-02",
      "fair_yes": 0.963,
      "market_yes": 0.506,
      "edge_pp": 45.7,
      "spread_pp": 94.6,
      "tradeable_edge_pp": 0.0,
      "liquidity": 731.0,
      "vol_24h": 0,
      "event_slug": "msft-above-in-june-2026",
      "market_id": "2388656"
    },
    {
      "ticker": "NVDA",
      "side": "above",
      "strike": 240.0,
      "close_date": "2026-06-30",
      "days": 17.74,
      "spot": 205.1,
      "sigma_used": 0.4151,
      "sigma_source": "iv_target",
      "rv_30d": 0.4744,
      "rv_60d": 0.4013,
      "iv_atm_target": 0.4151,
      "iv_atm_front": 0.0542,
      "iv_atm_back": 0.4051,
      "iv_term_slope": 0.3509,
      "iv_skew": 0.0312,
      "iv_target_expiry": "2026-07-02",
      "fair_yes": 0.0692,
      "market_yes": 0.52,
      "edge_pp": -45.08,
      "spread_pp": 94.0,
      "tradeable_edge_pp": -0.0,
      "liquidity": 1030.0,
      "vol_24h": 12.0,
      "event_slug": "nvda-above-in-june-2026",
      "market_id": "2388972"
    },
    {
      "ticker": "AAPL",
      "side": "above",
      "strike": 340.0,
      "close_date": "2026-06-30",
      "days": 17.74,
      "spot": 307.34,
      "sigma_used": 0.258,
      "sigma_source": "iv_target",
      "rv_30d": 0.2027,
      "rv_60d": 0.223,
      "iv_atm_target": 0.258,
      "iv_atm_front": 0.0679,
      "iv_atm_back": 0.2557,
      "iv_term_slope": 0.1878,
      "iv_skew": 0.0078,
      "iv_target_expiry": "2026-07-02",
      "fair_yes": 0.0656,
      "market_yes": 0.515,
      "edge_pp": -44.94,
      "spread_pp": 95.0,
      "tradeable_edge_pp": -0.0,
      "liquidity": 634.0,
      "vol_24h": 0,
      "event_slug": "aapl-above-in-june-2026",
      "market_id": "2388604"
    },
    {
      "ticker": "TSLA",
      "side": "above",
      "strike": 460.0,
      "close_date": "2026-06-30",
      "days": 17.74,
      "spot": 391.0,
      "sigma_used": 0.4881,
      "sigma_source": "iv_target",
      "rv_30d": 0.42,
      "rv_60d": 0.434,
      "iv_atm_target": 0.4881,
      "iv_atm_front": 0.0779,
      "iv_atm_back": 0.4817,
      "iv_term_slope": 0.4039,
      "iv_skew": 0.0742,
      "iv_target_expiry": "2026-07-02",
      "fair_yes": 0.0935,
      "market_yes": 0.54,
      "edge_pp": -44.65,
      "spread_pp": 90.0,
      "tradeable_edge_pp": -0.0,
      "liquidity": 1668.0,
      "vol_24h": 0,
      "event_slug": "tsla-above-in-june-2026",
      "market_id": "2388910"
    },
    {
      "ticker": "MSFT",
      "side": "above",
      "strike": 465.0,
      "close_date": "2026-06-30",
      "days": 17.74,
      "spot": 416.67,
      "sigma_used": 0.3017,
      "sigma_source": "iv_target",
      "rv_30d": 0.3332,
      "rv_60d": 0.3166,
      "iv_atm_target": 0.3017,
      "iv_atm_front": 0.0761,
      "iv_atm_back": 0.3118,
      "iv_term_slope": 0.2357,
      "iv_skew": 0.1738,
      "iv_target_expiry": "2026-07-02",
      "fair_yes": 0.0791,
      "market_yes": 0.525,
      "edge_pp": -44.59,
      "spread_pp": 93.0,
      "tradeable_edge_pp": -0.0,
      "liquidity": 731.0,
      "vol_24h": 0,
      "event_slug": "msft-above-in-june-2026",
      "market_id": "2388687"
    },
    {
      "ticker": "AMZN",
      "side": "above",
      "strike": 280.0,
      "close_date": "2026-06-30",
      "days": 17.74,
      "spot": 246.03,
      "sigma_used": 0.3417,
      "sigma_source": "iv_target",
      "rv_30d": 0.2697,
      "rv_60d": 0.3027,
      "iv_atm_target": 0.3417,
      "iv_atm_front": 0.1113,
      "iv_atm_back": 0.3385,
      "iv_term_slope": 0.2272,
      "iv_skew": 0.0078,
      "iv_target_expiry": "2026-07-02",
      "fair_yes": 0.0705,
      "market_yes": 0.515,
      "edge_pp": -44.45,
      "spread_pp": 95.0,
      "tradeable_edge_pp": -0.0,
      "liquidity": 723.0,
      "vol_24h": 0,
      "event_slug": "amzn-above-in-june-2026",
      "market_id": "2388742"
    },
    {
      "ticker": "META",
      "side": "above",
      "strike": 680.0,
      "close_date": "2026-06-30",
      "days": 17.74,
      "spot": 593.0,
      "sigma_used": 0.3633,
      "sigma_source": "iv_target",
      "rv_30d": 0.4073,
      "rv_60d": 0.4398,
      "iv_atm_target": 0.3633,
      "iv_atm_front": 0.1119,
      "iv_atm_back": 0.3524,
      "iv_term_slope": 0.2405,
      "iv_skew": 0.0312,
      "iv_target_expiry": "2026-07-02",
      "fair_yes": 0.071,
      "market_yes": 0.515,
      "edge_pp": -44.4,
      "spread_pp": 95.0,
      "tradeable_edge_pp": -0.0,
      "liquidity": 888.0,
      "vol_24h": 0,
      "event_slug": "meta-above-in-june-2026",
      "market_id": "2388859"
    },
    {
      "ticker": "AMZN",
      "side": "above",
      "strike": 210.0,
      "close_date": "2026-06-30",
      "days": 17.74,
      "spot": 246.03,
      "sigma_used": 0.3417,
      "sigma_source": "iv_target",
      "rv_30d": 0.2697,
      "rv_60d": 0.3027,
      "iv_atm_target": 0.3417,
      "iv_atm_front": 0.1113,
      "iv_atm_back": 0.3385,
      "iv_term_slope": 0.2272,
      "iv_skew": 0.0078,
      "iv_target_expiry": "2026-07-02",
      "fair_yes": 0.9556,
      "market_yes": 0.5145,
      "edge_pp": 44.11,
      "spread_pp": 90.9,
      "tradeable_edge_pp": 0.0,
      "liquidity": 723.0,
      "vol_24h": 2.0,
      "event_slug": "amzn-above-in-june-2026",
      "market_id": "2388719"
    },
    {
      "ticker": "TSLA",
      "side": "above",
      "strike": 450.0,
      "close_date": "2026-06-30",
      "days": 17.74,
      "spot": 391.0,
      "sigma_used": 0.4881,
      "sigma_source": "iv_target",
      "rv_30d": 0.42,
      "rv_60d": 0.434,
      "iv_atm_target": 0.4881,
      "iv_atm_front": 0.0779,
      "iv_atm_back": 0.4817,
      "iv_term_slope": 0.4039,
      "iv_skew": 0.0742,
      "iv_target_expiry": "2026-07-02",
      "fair_yes": 0.1251,
      "market_yes": 0.55,
      "edge_pp": -42.49,
      "spread_pp": 88.0,
      "tradeable_edge_pp": -0.0,
      "liquidity": 1668.0,
      "vol_24h": 0,
      "event_slug": "tsla-above-in-june-2026",
      "market_id": "2388909"
    },
    {
      "ticker": "META",
      "side": "above",
      "strike": 660.0,
      "close_date": "2026-06-30",
      "days": 17.74,
      "spot": 593.0,
      "sigma_used": 0.3633,
      "sigma_source": "iv_target",
      "rv_30d": 0.4073,
      "rv_60d": 0.4398,
      "iv_atm_target": 0.3633,
      "iv_atm_front": 0.1119,
      "iv_atm_back": 0.3524,
      "iv_term_slope": 0.2405,
      "iv_skew": 0.0312,
      "iv_target_expiry": "2026-07-02",
      "fair_yes": 0.1233,
      "market_yes": 0.535,
      "edge_pp": -41.17,
      "spread_pp": 91.0,
      "tradeable_edge_pp": -0.0,
      "liquidity": 888.0,
      "vol_24h": 0,
      "event_slug": "meta-above-in-june-2026",
      "market_id": "2388858"
    },
    {
      "ticker": "META",
      "side": "above",
      "strike": 520.0,
      "close_date": "2026-06-30",
      "days": 17.74,
      "spot": 593.0,
      "sigma_used": 0.3633,
      "sigma_source": "iv_target",
      "rv_30d": 0.4073,
      "rv_60d": 0.4398,
      "iv_atm_target": 0.3633,
      "iv_atm_front": 0.1119,
      "iv_atm_back": 0.3524,
      "iv_term_slope": 0.2405,
      "iv_skew": 0.0312,
      "iv_target_expiry": "2026-07-02",
      "fair_yes": 0.9057,
      "market_yes": 0.495,
      "edge_pp": 41.07,
      "spread_pp": 92.8,
      "tradeable_edge_pp": 0.0,
      "liquidity": 888.0,
      "vol_24h": 0,
      "event_slug": "meta-above-in-june-2026",
      "market_id": "2388850"
    },
    {
      "ticker": "AMZN",
      "side": "above",
      "strike": 220.0,
      "close_date": "2026-06-30",
      "days": 17.74,
      "spot": 246.03,
      "sigma_used": 0.3417,
      "sigma_source": "iv_target",
      "rv_30d": 0.2697,
      "rv_60d": 0.3027,
      "iv_atm_target": 0.3417,
      "iv_atm_front": 0.1113,
      "iv_atm_back": 0.3385,
      "iv_term_slope": 0.2272,
      "iv_skew": 0.0078,
      "iv_target_expiry": "2026-07-02",
      "fair_yes": 0.8826,
      "market_yes": 0.475,
      "edge_pp": 40.76,
      "spread_pp": 92.8,
      "tradeable_edge_pp": 0.0,
      "liquidity": 723.0,
      "vol_24h": 0,
      "event_slug": "amzn-above-in-june-2026",
      "market_id": "2388722"
    },
    {
      "ticker": "MSFT",
      "side": "above",
      "strike": 375.0,
      "close_date": "2026-06-30",
      "days": 17.74,
      "spot": 416.67,
      "sigma_used": 0.3017,
      "sigma_source": "iv_target",
      "rv_30d": 0.3332,
      "rv_60d": 0.3166,
      "iv_atm_target": 0.3017,
      "iv_atm_front": 0.0761,
      "iv_atm_back": 0.3118,
      "iv_term_slope": 0.2357,
      "iv_skew": 0.1738,
      "iv_target_expiry": "2026-07-02",
      "fair_yes": 0.8991,
      "market_yes": 0.5,
      "edge_pp": 39.91,
      "spread_pp": 87.8,
      "tradeable_edge_pp": 0.0,
      "liquidity": 731.0,
      "vol_24h": 32.0,
      "event_slug": "msft-above-in-june-2026",
      "market_id": "2388659"
    },
    {
      "ticker": "AAPL",
      "side": "above",
      "strike": 330.0,
      "close_date": "2026-06-30",
      "days": 17.74,
      "spot": 307.34,
      "sigma_used": 0.258,
      "sigma_source": "iv_target",
      "rv_30d": 0.2027,
      "rv_60d": 0.223,
      "iv_atm_target": 0.258,
      "iv_atm_front": 0.0679,
      "iv_atm_back": 0.2557,
      "iv_term_slope": 0.1878,
      "iv_skew": 0.0078,
      "iv_target_expiry": "2026-07-02",
      "fair_yes": 0.1415,
      "market_yes": 0.54,
      "edge_pp": -39.85,
      "spread_pp": 90.0,
      "tradeable_edge_pp": -0.0,
      "liquidity": 634.0,
      "vol_24h": 0,
      "event_slug": "aapl-above-in-june-2026",
      "market_id": "2388599"
    },
    {
      "ticker": "NVDA",
      "side": "above",
      "strike": 230.0,
      "close_date": "2026-06-30",
      "days": 17.74,
      "spot": 205.1,
      "sigma_used": 0.4151,
      "sigma_source": "iv_target",
      "rv_30d": 0.4744,
      "rv_60d": 0.4013,
      "iv_atm_target": 0.4151,
      "iv_atm_front": 0.0542,
      "iv_atm_back": 0.4051,
      "iv_term_slope": 0.3509,
      "iv_skew": 0.0312,
      "iv_target_expiry": "2026-07-02",
      "fair_yes": 0.1367,
      "market_yes": 0.535,
      "edge_pp": -39.83,
      "spread_pp": 91.0,
      "tradeable_edge_pp": -0.0,
      "liquidity": 1030.0,
      "vol_24h": 0,
      "event_slug": "nvda-above-in-june-2026",
      "market_id": "2388969"
    },
    {
      "ticker": "TSLA",
      "side": "above",
      "strike": 440.0,
      "close_date": "2026-06-30",
      "days": 17.74,
      "spot": 391.0,
      "sigma_used": 0.4881,
      "sigma_source": "iv_target",
      "rv_30d": 0.42,
      "rv_60d": 0.434,
      "iv_atm_target": 0.4881,
      "iv_atm_front": 0.0779,
      "iv_atm_back": 0.4817,
      "iv_term_slope": 0.4039,
      "iv_skew": 0.0742,
      "iv_target_expiry": "2026-07-02",
      "fair_yes": 0.1644,
      "market_yes": 0.56,
      "edge_pp": -39.56,
      "spread_pp": 86.0,
      "tradeable_edge_pp": -0.0,
      "liquidity": 1668.0,
      "vol_24h": 0,
      "event_slug": "tsla-above-in-june-2026",
      "market_id": "2388908"
    },
    {
      "ticker": "AAPL",
      "side": "above",
      "strike": 280.0,
      "close_date": "2026-06-30",
      "days": 17.74,
      "spot": 307.34,
      "sigma_used": 0.258,
      "sigma_source": "iv_target",
      "rv_30d": 0.2027,
      "rv_60d": 0.223,
      "iv_atm_target": 0.258,
      "iv_atm_front": 0.0679,
      "iv_atm_back": 0.2557,
      "iv_term_slope": 0.1878,
      "iv_skew": 0.0078,
      "iv_target_expiry": "2026-07-02",
      "fair_yes": 0.9077,
      "market_yes": 0.515,
      "edge_pp": 39.27,
      "spread_pp": 83.0,
      "tradeable_edge_pp": 0.0,
      "liquidity": 634.0,
      "vol_24h": 0,
      "event_slug": "aapl-above-in-june-2026",
      "market_id": "2388567"
    },
    {
      "ticker": "AMZN",
      "side": "above",
      "strike": 270.0,
      "close_date": "2026-06-30",
      "days": 17.74,
      "spot": 246.03,
      "sigma_used": 0.3417,
      "sigma_source": "iv_target",
      "rv_30d": 0.2697,
      "rv_60d": 0.3027,
      "iv_atm_target": 0.3417,
      "iv_atm_front": 0.1113,
      "iv_atm_back": 0.3385,
      "iv_term_slope": 0.2272,
      "iv_skew": 0.0078,
      "iv_target_expiry": "2026-07-02",
      "fair_yes": 0.1421,
      "market_yes": 0.525,
      "edge_pp": -38.29,
      "spread_pp": 93.0,
      "tradeable_edge_pp": -0.0,
      "liquidity": 723.0,
      "vol_24h": 0,
      "event_slug": "amzn-above-in-june-2026",
      "market_id": "2388738"
    },
    {
      "ticker": "MSFT",
      "side": "above",
      "strike": 450.0,
      "close_date": "2026-06-30",
      "days": 17.74,
      "spot": 416.67,
      "sigma_used": 0.3017,
      "sigma_source": "iv_target",
      "rv_30d": 0.3332,
      "rv_60d": 0.3166,
      "iv_atm_target": 0.3017,
      "iv_atm_front": 0.0761,
      "iv_atm_back": 0.3118,
      "iv_term_slope": 0.2357,
      "iv_skew": 0.1738,
      "iv_target_expiry": "2026-07-02",
      "fair_yes": 0.1583,
      "market_yes": 0.53,
      "edge_pp": -37.17,
      "spread_pp": 92.0,
      "tradeable_edge_pp": -0.0,
      "liquidity": 731.0,
      "vol_24h": 0,
      "event_slug": "msft-above-in-june-2026",
      "market_id": "2388685"
    },
    {
      "ticker": "AAPL",
      "side": "above",
      "strike": 320.0,
      "close_date": "2026-06-30",
      "days": 17.74,
      "spot": 307.34,
      "sigma_used": 0.258,
      "sigma_source": "iv_target",
      "rv_30d": 0.2027,
      "rv_60d": 0.223,
      "iv_atm_target": 0.258,
      "iv_atm_front": 0.0679,
      "iv_atm_back": 0.2557,
      "iv_term_slope": 0.1878,
      "iv_skew": 0.0078,
      "iv_target_expiry": "2026-07-02",
      "fair_yes": 0.2663,
      "market_yes": 0.615,
      "edge_pp": -34.87,
      "spread_pp": 73.0,
      "tradeable_edge_pp": -0.0,
      "liquidity": 634.0,
      "vol_24h": 2834.0,
      "event_slug": "aapl-above-in-june-2026",
      "market_id": "2388595"
    },
    {
      "ticker": "AAPL",
      "side": "above",
      "strike": 290.0,
      "close_date": "2026-06-30",
      "days": 17.74,
      "spot": 307.34,
      "sigma_used": 0.258,
      "sigma_source": "iv_target",
      "rv_30d": 0.2027,
      "rv_60d": 0.223,
      "iv_atm_target": 0.258,
      "iv_atm_front": 0.0679,
      "iv_atm_back": 0.2557,
      "iv_term_slope": 0.1878,
      "iv_skew": 0.0078,
      "iv_target_expiry": "2026-07-02",
      "fair_yes": 0.7923,
      "market_yes": 0.445,
      "edge_pp": 34.73,
      "spread_pp": 87.0,
      "tradeable_edge_pp": 0.0,
      "liquidity": 634.0,
      "vol_24h": 0,
      "event_slug": "aapl-above-in-june-2026",
      "market_id": "2388573"
    },
    {
      "ticker": "MSFT",
      "side": "above",
      "strike": 480.0,
      "close_date": "2026-06-30",
      "days": 17.74,
      "spot": 416.67,
      "sigma_used": 0.3017,
      "sigma_source": "iv_target",
      "rv_30d": 0.3332,
      "rv_60d": 0.3166,
      "iv_atm_target": 0.3017,
      "iv_atm_front": 0.0761,
      "iv_atm_back": 0.3118,
      "iv_term_slope": 0.2357,
      "iv_skew": 0.1738,
      "iv_target_expiry": "2026-07-02",
      "fair_yes": 0.0353,
      "market_yes": 0.38,
      "edge_pp": -34.47,
      "spread_pp": 70.0,
      "tradeable_edge_pp": -0.0,
      "liquidity": 731.0,
      "vol_24h": 428.0,
      "event_slug": "msft-above-in-june-2026",
      "market_id": "2388690"
    },
    {
      "ticker": "META",
      "side": "above",
      "strike": 640.0,
      "close_date": "2026-06-30",
      "days": 17.74,
      "spot": 593.0,
      "sigma_used": 0.3633,
      "sigma_source": "iv_target",
      "rv_30d": 0.4073,
      "rv_60d": 0.4398,
      "iv_atm_target": 0.3633,
      "iv_atm_front": 0.1119,
      "iv_atm_back": 0.3524,
      "iv_term_slope": 0.2405,
      "iv_skew": 0.0312,
      "iv_target_expiry": "2026-07-02",
      "fair_yes": 0.2006,
      "market_yes": 0.54,
      "edge_pp": -33.94,
      "spread_pp": 84.0,
      "tradeable_edge_pp": -0.0,
      "liquidity": 888.0,
      "vol_24h": 8.0,
      "event_slug": "meta-above-in-june-2026",
      "market_id": "2388857"
    },
    {
      "ticker": "TSLA",
      "side": "above",
      "strike": 430.0,
      "close_date": "2026-06-30",
      "days": 17.74,
      "spot": 391.0,
      "sigma_used": 0.4881,
      "sigma_source": "iv_target",
      "rv_30d": 0.42,
      "rv_60d": 0.434,
      "iv_atm_target": 0.4881,
      "iv_atm_front": 0.0779,
      "iv_atm_back": 0.4817,
      "iv_term_slope": 0.4039,
      "iv_skew": 0.0742,
      "iv_target_expiry": "2026-07-02",
      "fair_yes": 0.2122,
      "market_yes": 0.55,
      "edge_pp": -33.78,
      "spread_pp": 88.0,
      "tradeable_edge_pp": -0.0,
      "liquidity": 1668.0,
      "vol_24h": 0,
      "event_slug": "tsla-above-in-june-2026",
      "market_id": "2388907"
    },
    {
      "ticker": "AMZN",
      "side": "above",
      "strike": 230.0,
      "close_date": "2026-06-30",
      "days": 17.74,
      "spot": 246.03,
      "sigma_used": 0.3417,
      "sigma_source": "iv_target",
      "rv_30d": 0.2697,
      "rv_60d": 0.3027,
      "iv_atm_target": 0.3417,
      "iv_atm_front": 0.1113,
      "iv_atm_back": 0.3385,
      "iv_term_slope": 0.2272,
      "iv_skew": 0.0078,
      "iv_target_expiry": "2026-07-02",
      "fair_yes": 0.7574,
      "market_yes": 0.425,
      "edge_pp": 33.24,
      "spread_pp": 83.0,
      "tradeable_edge_pp": 0.0,
      "liquidity": 723.0,
      "vol_24h": 0,
      "event_slug": "amzn-above-in-june-2026",
      "market_id": "2388725"
    },
    {
      "ticker": "META",
      "side": "above",
      "strike": 540.0,
      "close_date": "2026-06-30",
      "days": 17.74,
      "spot": 593.0,
      "sigma_used": 0.3633,
      "sigma_source": "iv_target",
      "rv_30d": 0.4073,
      "rv_60d": 0.4398,
      "iv_atm_target": 0.3633,
      "iv_atm_front": 0.1119,
      "iv_atm_back": 0.3524,
      "iv_term_slope": 0.2405,
      "iv_skew": 0.0312,
      "iv_target_expiry": "2026-07-02",
      "fair_yes": 0.822,
      "market_yes": 0.49,
      "edge_pp": 33.2,
      "spread_pp": 80.0,
      "tradeable_edge_pp": 0.0,
      "liquidity": 888.0,
      "vol_24h": 0,
      "event_slug": "meta-above-in-june-2026",
      "market_id": "2388852"
    },
    {
      "ticker": "NVDA",
      "side": "above",
      "strike": 220.0,
      "close_date": "2026-06-30",
      "days": 17.74,
      "spot": 205.1,
      "sigma_used": 0.4151,
      "sigma_source": "iv_target",
      "rv_30d": 0.4744,
      "rv_60d": 0.4013,
      "iv_atm_target": 0.4151,
      "iv_atm_front": 0.0542,
      "iv_atm_back": 0.4051,
      "iv_term_slope": 0.3509,
      "iv_skew": 0.0312,
      "iv_target_expiry": "2026-07-02",
      "fair_yes": 0.2445,
      "market_yes": 0.575,
      "edge_pp": -33.05,
      "spread_pp": 83.0,
      "tradeable_edge_pp": -0.0,
      "liquidity": 1030.0,
      "vol_24h": 0,
      "event_slug": "nvda-above-in-june-2026",
      "market_id": "2388966"
    },
    {
      "ticker": "AMZN",
      "side": "above",
      "strike": 260.0,
      "close_date": "2026-06-30",
      "days": 17.74,
      "spot": 246.03,
      "sigma_used": 0.3417,
      "sigma_source": "iv_target",
      "rv_30d": 0.2697,
      "rv_60d": 0.3027,
      "iv_atm_target": 0.3417,
      "iv_atm_front": 0.1113,
      "iv_atm_back": 0.3385,
      "iv_term_slope": 0.2272,
      "iv_skew": 0.0078,
      "iv_target_expiry": "2026-07-02",
      "fair_yes": 0.2564,
      "market_yes": 0.585,
      "edge_pp": -32.86,
      "spread_pp": 81.0,
      "tradeable_edge_pp": -0.0,
      "liquidity": 723.0,
      "vol_24h": 14,
      "event_slug": "amzn-above-in-june-2026",
      "market_id": "2388734"
    },
    {
      "ticker": "MSFT",
      "side": "above",
      "strike": 435.0,
      "close_date": "2026-06-30",
      "days": 17.74,
      "spot": 416.67,
      "sigma_used": 0.3017,
      "sigma_source": "iv_target",
      "rv_30d": 0.3332,
      "rv_60d": 0.3166,
      "iv_atm_target": 0.3017,
      "iv_atm_front": 0.0761,
      "iv_atm_back": 0.3118,
      "iv_term_slope": 0.2357,
      "iv_skew": 0.1738,
      "iv_target_expiry": "2026-07-02",
      "fair_yes": 0.2817,
      "market_yes": 0.595,
      "edge_pp": -31.33,
      "spread_pp": 79.0,
      "tradeable_edge_pp": -0.0,
      "liquidity": 731.0,
      "vol_24h": 0,
      "event_slug": "msft-above-in-june-2026",
      "market_id": "2388680"
    },
    {
      "ticker": "NVDA",
      "side": "above",
      "strike": 190.0,
      "close_date": "2026-06-30",
      "days": 17.74,
      "spot": 205.1,
      "sigma_used": 0.4151,
      "sigma_source": "iv_target",
      "rv_30d": 0.4744,
      "rv_60d": 0.4013,
      "iv_atm_target": 0.4151,
      "iv_atm_front": 0.0542,
      "iv_atm_back": 0.4051,
      "iv_term_slope": 0.3509,
      "iv_skew": 0.0312,
      "iv_target_expiry": "2026-07-02",
      "fair_yes": 0.7387,
      "market_yes": 0.435,
      "edge_pp": 30.37,
      "spread_pp": 83.0,
      "tradeable_edge_pp": 0.0,
      "liquidity": 1030.0,
      "vol_24h": 140,
      "event_slug": "nvda-above-in-june-2026",
      "market_id": "2388959"
    },
    {
      "ticker": "META",
      "side": "above",
      "strike": 650.0,
      "close_date": "2026-06-08",
      "days": 2.02,
      "spot": 593.0,
      "sigma_used": 0.3211,
      "sigma_source": "iv_target",
      "rv_30d": 0.4073,
      "rv_60d": 0.4398,
      "iv_atm_target": 0.3211,
      "iv_atm_front": 0.1119,
      "iv_atm_back": 0.3524,
      "iv_term_slope": 0.2405,
      "iv_skew": 0.0312,
      "iv_target_expiry": "2026-06-08",
      "fair_yes": 0.0007,
      "market_yes": 0.28,
      "edge_pp": -27.93,
      "spread_pp": 53.8,
      "tradeable_edge_pp": -0.0,
      "liquidity": 3171.0,
      "vol_24h": 0,
      "event_slug": "meta-close-above-on-june-8-2026",
      "market_id": "2443288"
    },
    {
      "ticker": "META",
      "side": "above",
      "strike": 620.0,
      "close_date": "2026-06-30",
      "days": 17.74,
      "spot": 593.0,
      "sigma_used": 0.3633,
      "sigma_source": "iv_target",
      "rv_30d": 0.4073,
      "rv_60d": 0.4398,
      "iv_atm_target": 0.3633,
      "iv_atm_front": 0.1119,
      "iv_atm_back": 0.3524,
      "iv_term_slope": 0.2405,
      "iv_skew": 0.0312,
      "iv_target_expiry": "2026-07-02",
      "fair_yes": 0.305,
      "market_yes": 0.575,
      "edge_pp": -27.0,
      "spread_pp": 77.0,
      "tradeable_edge_pp": -0.0,
      "liquidity": 888.0,
      "vol_24h": 9.0,
      "event_slug": "meta-above-in-june-2026",
      "market_id": "2388856"
    },
    {
      "ticker": "TSLA",
      "side": "above",
      "strike": 420.0,
      "close_date": "2026-06-30",
      "days": 17.74,
      "spot": 391.0,
      "sigma_used": 0.4881,
      "sigma_source": "iv_target",
      "rv_30d": 0.42,
      "rv_60d": 0.434,
      "iv_atm_target": 0.4881,
      "iv_atm_front": 0.0779,
      "iv_atm_back": 0.4817,
      "iv_term_slope": 0.4039,
      "iv_skew": 0.0742,
      "iv_target_expiry": "2026-07-02",
      "fair_yes": 0.2686,
      "market_yes": 0.515,
      "edge_pp": -24.64,
      "spread_pp": 71.0,
      "tradeable_edge_pp": -0.0,
      "liquidity": 1668.0,
      "vol_24h": 0,
      "event_slug": "tsla-above-in-june-2026",
      "market_id": "2388906"
    },
    {
      "ticker": "TSLA",
      "side": "above",
      "strike": 410.0,
      "close_date": "2026-06-30",
      "days": 17.74,
      "spot": 391.0,
      "sigma_used": 0.4881,
      "sigma_source": "iv_target",
      "rv_30d": 0.42,
      "rv_60d": 0.434,
      "iv_atm_target": 0.4881,
      "iv_atm_front": 0.0779,
      "iv_atm_back": 0.4817,
      "iv_term_slope": 0.4039,
      "iv_skew": 0.0742,
      "iv_target_expiry": "2026-07-02",
      "fair_yes": 0.3332,
      "market_yes": 0.56,
      "edge_pp": -22.68,
      "spread_pp": 68.0,
      "tradeable_edge_pp": -0.0,
      "liquidity": 1668.0,
      "vol_24h": 0,
      "event_slug": "tsla-above-in-june-2026",
      "market_id": "2388905"
    },
    {
      "ticker": "MSFT",
      "side": "above",
      "strike": 410.0,
      "close_date": "2026-06-08",
      "days": 2.02,
      "spot": 416.67,
      "sigma_used": 0.2217,
      "sigma_source": "iv_target",
      "rv_30d": 0.3332,
      "rv_60d": 0.3166,
      "iv_atm_target": 0.2217,
      "iv_atm_front": 0.0761,
      "iv_atm_back": 0.3118,
      "iv_term_slope": 0.2357,
      "iv_skew": 0.1738,
      "iv_target_expiry": "2026-06-08",
      "fair_yes": 0.7888,
      "market_yes": 0.625,
      "edge_pp": 16.38,
      "spread_pp": 37.0,
      "tradeable_edge_pp": 0.0,
      "liquidity": 2347.0,
      "vol_24h": 15.0,
      "event_slug": "msft-close-above-on-june-8-2026",
      "market_id": "2443248"
    },
    {
      "ticker": "SPY",
      "side": "above",
      "strike": 730.0,
      "close_date": "2026-06-08",
      "days": 2.02,
      "spot": 737.55,
      "sigma_used": 0.1116,
      "sigma_source": "iv_target",
      "rv_30d": 0.1228,
      "rv_60d": 0.152,
      "iv_atm_target": 0.1116,
      "iv_atm_front": 0.0393,
      "iv_atm_back": 0.1605,
      "iv_term_slope": 0.1213,
      "iv_skew": 0.0156,
      "iv_target_expiry": "2026-06-08",
      "fair_yes": 0.8469,
      "market_yes": 0.7,
      "edge_pp": 14.69,
      "spread_pp": 36.0,
      "tradeable_edge_pp": 0.0,
      "liquidity": 8297.0,
      "vol_24h": 0,
      "event_slug": "spy-closes-above-on-june-8-2026",
      "market_id": "2443243"
    },
    {
      "ticker": "SPY",
      "side": "above",
      "strike": 735.0,
      "close_date": "2026-06-08",
      "days": 2.02,
      "spot": 737.55,
      "sigma_used": 0.1116,
      "sigma_source": "iv_target",
      "rv_30d": 0.1228,
      "rv_60d": 0.152,
      "iv_atm_target": 0.1116,
      "iv_atm_front": 0.0393,
      "iv_atm_back": 0.1605,
      "iv_term_slope": 0.1213,
      "iv_skew": 0.0156,
      "iv_target_expiry": "2026-06-08",
      "fair_yes": 0.6335,
      "market_yes": 0.5,
      "edge_pp": 13.35,
      "spread_pp": 22.0,
      "tradeable_edge_pp": 0.0,
      "liquidity": 8297.0,
      "vol_24h": 72.0,
      "event_slug": "spy-closes-above-on-june-8-2026",
      "market_id": "2443242"
    },
    {
      "ticker": "NVDA",
      "side": "above",
      "strike": 230.0,
      "close_date": "2026-06-08",
      "days": 2.02,
      "spot": 205.1,
      "sigma_used": 0.3158,
      "sigma_source": "iv_target",
      "rv_30d": 0.4744,
      "rv_60d": 0.4013,
      "iv_atm_target": 0.3158,
      "iv_atm_front": 0.0542,
      "iv_atm_back": 0.4051,
      "iv_term_slope": 0.3509,
      "iv_skew": 0.0312,
      "iv_target_expiry": "2026-06-08",
      "fair_yes": 0.0,
      "market_yes": 0.121,
      "edge_pp": -12.1,
      "spread_pp": 21.6,
      "tradeable_edge_pp": -0.0,
      "liquidity": 2593.0,
      "vol_24h": 39.0,
      "event_slug": "nvda-close-above-on-june-8-2026",
      "market_id": "2443306"
    },
    {
      "ticker": "TSLA",
      "side": "above",
      "strike": 440.0,
      "close_date": "2026-06-08",
      "days": 2.02,
      "spot": 391.0,
      "sigma_used": 0.361,
      "sigma_source": "iv_target",
      "rv_30d": 0.42,
      "rv_60d": 0.434,
      "iv_atm_target": 0.361,
      "iv_atm_front": 0.0779,
      "iv_atm_back": 0.4817,
      "iv_term_slope": 0.4039,
      "iv_skew": 0.0742,
      "iv_target_expiry": "2026-06-08",
      "fair_yes": 0.0001,
      "market_yes": 0.1205,
      "edge_pp": -12.04,
      "spread_pp": 21.9,
      "tradeable_edge_pp": -0.0,
      "liquidity": 3773.0,
      "vol_24h": 0,
      "event_slug": "tsla-close-above-on-june-8-2026",
      "market_id": "2443298"
    },
    {
      "ticker": "MSFT",
      "side": "above",
      "strike": 450.0,
      "close_date": "2026-06-08",
      "days": 2.02,
      "spot": 416.67,
      "sigma_used": 0.2217,
      "sigma_source": "iv_target",
      "rv_30d": 0.3332,
      "rv_60d": 0.3166,
      "iv_atm_target": 0.2217,
      "iv_atm_front": 0.0761,
      "iv_atm_back": 0.3118,
      "iv_term_slope": 0.2357,
      "iv_skew": 0.1738,
      "iv_target_expiry": "2026-06-08",
      "fair_yes": 0.0001,
      "market_yes": 0.12,
      "edge_pp": -11.99,
      "spread_pp": 22.0,
      "tradeable_edge_pp": -0.0,
      "liquidity": 2347.0,
      "vol_24h": 0,
      "event_slug": "msft-close-above-on-june-8-2026",
      "market_id": "2443252"
    },
    {
      "ticker": "AAPL",
      "side": "above",
      "strike": 320.0,
      "close_date": "2026-06-08",
      "days": 2.02,
      "spot": 307.34,
      "sigma_used": 0.2765,
      "sigma_source": "iv_target",
      "rv_30d": 0.2027,
      "rv_60d": 0.223,
      "iv_atm_target": 0.2765,
      "iv_atm_front": 0.0679,
      "iv_atm_back": 0.2557,
      "iv_term_slope": 0.1878,
      "iv_skew": 0.0078,
      "iv_target_expiry": "2026-06-08",
      "fair_yes": 0.0504,
      "market_yes": 0.165,
      "edge_pp": -11.46,
      "spread_pp": 21.0,
      "tradeable_edge_pp": -0.0,
      "liquidity": 2946.0,
      "vol_24h": 0,
      "event_slug": "aapl-close-above-on-june-8-2026",
      "market_id": "2443232"
    },
    {
      "ticker": "MSFT",
      "side": "above",
      "strike": 390.0,
      "close_date": "2026-06-30",
      "days": 17.74,
      "spot": 416.67,
      "sigma_used": 0.3017,
      "sigma_source": "iv_target",
      "rv_30d": 0.3332,
      "rv_60d": 0.3166,
      "iv_atm_target": 0.3017,
      "iv_atm_front": 0.0761,
      "iv_atm_back": 0.3118,
      "iv_term_slope": 0.2357,
      "iv_skew": 0.1738,
      "iv_target_expiry": "2026-07-02",
      "fair_yes": 0.7842,
      "market_yes": 0.672,
      "edge_pp": 11.22,
      "spread_pp": 40.0,
      "tradeable_edge_pp": 0.0,
      "liquidity": 731.0,
      "vol_24h": 0,
      "event_slug": "msft-above-in-june-2026",
      "market_id": "2388664"
    },
    {
      "ticker": "AAPL",
      "side": "above",
      "strike": 310.0,
      "close_date": "2026-06-08",
      "days": 2.02,
      "spot": 307.34,
      "sigma_used": 0.2765,
      "sigma_source": "iv_target",
      "rv_30d": 0.2027,
      "rv_60d": 0.223,
      "iv_atm_target": 0.2765,
      "iv_atm_front": 0.0679,
      "iv_atm_back": 0.2557,
      "iv_term_slope": 0.1878,
      "iv_skew": 0.0078,
      "iv_target_expiry": "2026-06-08",
      "fair_yes": 0.3594,
      "market_yes": 0.465,
      "edge_pp": -10.56,
      "spread_pp": 25.0,
      "tradeable_edge_pp": -0.0,
      "liquidity": 2946.0,
      "vol_24h": 0,
      "event_slug": "aapl-close-above-on-june-8-2026",
      "market_id": "2443228"
    },
    {
      "ticker": "NVDA",
      "side": "above",
      "strike": 225.0,
      "close_date": "2026-06-08",
      "days": 2.02,
      "spot": 205.1,
      "sigma_used": 0.3158,
      "sigma_source": "iv_target",
      "rv_30d": 0.4744,
      "rv_60d": 0.4013,
      "iv_atm_target": 0.3158,
      "iv_atm_front": 0.0542,
      "iv_atm_back": 0.4051,
      "iv_term_slope": 0.3509,
      "iv_skew": 0.0312,
      "iv_target_expiry": "2026-06-08",
      "fair_yes": 0.0005,
      "market_yes": 0.1055,
      "edge_pp": -10.5,
      "spread_pp": 18.9,
      "tradeable_edge_pp": -0.0,
      "liquidity": 2593.0,
      "vol_24h": 0,
      "event_slug": "nvda-close-above-on-june-8-2026",
      "market_id": "2443305"
    },
    {
      "ticker": "NVDA",
      "side": "above",
      "strike": 215.0,
      "close_date": "2026-06-08",
      "days": 2.02,
      "spot": 205.1,
      "sigma_used": 0.3158,
      "sigma_source": "iv_target",
      "rv_30d": 0.4744,
      "rv_60d": 0.4013,
      "iv_atm_target": 0.3158,
      "iv_atm_front": 0.0542,
      "iv_atm_back": 0.4051,
      "iv_term_slope": 0.3509,
      "iv_skew": 0.0312,
      "iv_target_expiry": "2026-06-08",
      "fair_yes": 0.0465,
      "market_yes": 0.15,
      "edge_pp": -10.35,
      "spread_pp": 18.0,
      "tradeable_edge_pp": -0.0,
      "liquidity": 2593.0,
      "vol_24h": 8.0,
      "event_slug": "nvda-close-above-on-june-8-2026",
      "market_id": "2443302"
    },
    {
      "ticker": "AAPL",
      "side": "above",
      "strike": 315.0,
      "close_date": "2026-06-08",
      "days": 2.02,
      "spot": 307.34,
      "sigma_used": 0.2765,
      "sigma_source": "iv_target",
      "rv_30d": 0.2027,
      "rv_60d": 0.223,
      "iv_atm_target": 0.2765,
      "iv_atm_front": 0.0679,
      "iv_atm_back": 0.2557,
      "iv_term_slope": 0.1878,
      "iv_skew": 0.0078,
      "iv_target_expiry": "2026-06-08",
      "fair_yes": 0.1573,
      "market_yes": 0.26,
      "edge_pp": -10.27,
      "spread_pp": 32.0,
      "tradeable_edge_pp": -0.0,
      "liquidity": 2946.0,
      "vol_24h": 0,
      "event_slug": "aapl-close-above-on-june-8-2026",
      "market_id": "2443231"
    },
    {
      "ticker": "MSFT",
      "side": "above",
      "strike": 440.0,
      "close_date": "2026-06-08",
      "days": 2.02,
      "spot": 416.67,
      "sigma_used": 0.2217,
      "sigma_source": "iv_target",
      "rv_30d": 0.3332,
      "rv_60d": 0.3166,
      "iv_atm_target": 0.2217,
      "iv_atm_front": 0.0761,
      "iv_atm_back": 0.3118,
      "iv_term_slope": 0.2357,
      "iv_skew": 0.1738,
      "iv_target_expiry": "2026-06-08",
      "fair_yes": 0.003,
      "market_yes": 0.105,
      "edge_pp": -10.2,
      "spread_pp": 19.0,
      "tradeable_edge_pp": -0.0,
      "liquidity": 2347.0,
      "vol_24h": 0,
      "event_slug": "msft-close-above-on-june-8-2026",
      "market_id": "2443251"
    },
    {
      "ticker": "AAPL",
      "side": "above",
      "strike": 305.0,
      "close_date": "2026-06-08",
      "days": 2.02,
      "spot": 307.34,
      "sigma_used": 0.2765,
      "sigma_source": "iv_target",
      "rv_30d": 0.2027,
      "rv_60d": 0.223,
      "iv_atm_target": 0.2765,
      "iv_atm_front": 0.0679,
      "iv_atm_back": 0.2557,
      "iv_term_slope": 0.1878,
      "iv_skew": 0.0078,
      "iv_target_expiry": "2026-06-08",
      "fair_yes": 0.6164,
      "market_yes": 0.515,
      "edge_pp": 10.14,
      "spread_pp": 81.0,
      "tradeable_edge_pp": 0.0,
      "liquidity": 2946.0,
      "vol_24h": 0,
      "event_slug": "aapl-close-above-on-june-8-2026",
      "market_id": "2443227"
    },
    {
      "ticker": "TSLA",
      "side": "above",
      "strike": 430.0,
      "close_date": "2026-06-08",
      "days": 2.02,
      "spot": 391.0,
      "sigma_used": 0.361,
      "sigma_source": "iv_target",
      "rv_30d": 0.42,
      "rv_60d": 0.434,
      "iv_atm_target": 0.361,
      "iv_atm_front": 0.0779,
      "iv_atm_back": 0.4817,
      "iv_term_slope": 0.4039,
      "iv_skew": 0.0742,
      "iv_target_expiry": "2026-06-08",
      "fair_yes": 0.0016,
      "market_yes": 0.102,
      "edge_pp": -10.04,
      "spread_pp": 18.2,
      "tradeable_edge_pp": -0.0,
      "liquidity": 3773.0,
      "vol_24h": 305.0,
      "event_slug": "tsla-close-above-on-june-8-2026",
      "market_id": "2443297"
    },
    {
      "ticker": "NVDA",
      "side": "above",
      "strike": 220.0,
      "close_date": "2026-06-08",
      "days": 2.02,
      "spot": 205.1,
      "sigma_used": 0.3158,
      "sigma_source": "iv_target",
      "rv_30d": 0.4744,
      "rv_60d": 0.4013,
      "iv_atm_target": 0.3158,
      "iv_atm_front": 0.0542,
      "iv_atm_back": 0.4051,
      "iv_term_slope": 0.3509,
      "iv_skew": 0.0312,
      "iv_target_expiry": "2026-06-08",
      "fair_yes": 0.0064,
      "market_yes": 0.1,
      "edge_pp": -9.36,
      "spread_pp": 8.0,
      "tradeable_edge_pp": -1.36,
      "liquidity": 2593.0,
      "vol_24h": 37.0,
      "event_slug": "nvda-close-above-on-june-8-2026",
      "market_id": "2443304"
    },
    {
      "ticker": "AMZN",
      "side": "above",
      "strike": 250.0,
      "close_date": "2026-06-08",
      "days": 2.02,
      "spot": 246.03,
      "sigma_used": 0.2794,
      "sigma_source": "iv_target",
      "rv_30d": 0.2697,
      "rv_60d": 0.3027,
      "iv_atm_target": 0.2794,
      "iv_atm_front": 0.1113,
      "iv_atm_back": 0.3385,
      "iv_term_slope": 0.2272,
      "iv_skew": 0.0078,
      "iv_target_expiry": "2026-06-08",
      "fair_yes": 0.2573,
      "market_yes": 0.35,
      "edge_pp": -9.27,
      "spread_pp": 22.0,
      "tradeable_edge_pp": -0.0,
      "liquidity": 3301.0,
      "vol_24h": 44,
      "event_slug": "amzn-close-above-on-june-8-2026",
      "market_id": "2443269"
    },
    {
      "ticker": "TSLA",
      "side": "above",
      "strike": 420.0,
      "close_date": "2026-06-08",
      "days": 2.02,
      "spot": 391.0,
      "sigma_used": 0.361,
      "sigma_source": "iv_target",
      "rv_30d": 0.42,
      "rv_60d": 0.434,
      "iv_atm_target": 0.361,
      "iv_atm_front": 0.0779,
      "iv_atm_back": 0.4817,
      "iv_term_slope": 0.4039,
      "iv_skew": 0.0742,
      "iv_target_expiry": "2026-06-08",
      "fair_yes": 0.013,
      "market_yes": 0.105,
      "edge_pp": -9.2,
      "spread_pp": 11.0,
      "tradeable_edge_pp": -0.0,
      "liquidity": 3773.0,
      "vol_24h": 0,
      "event_slug": "tsla-close-above-on-june-8-2026",
      "market_id": "2443296"
    },
    {
      "ticker": "TSLA",
      "side": "above",
      "strike": 400.0,
      "close_date": "2026-06-08",
      "days": 2.02,
      "spot": 391.0,
      "sigma_used": 0.361,
      "sigma_source": "iv_target",
      "rv_30d": 0.42,
      "rv_60d": 0.434,
      "iv_atm_target": 0.361,
      "iv_atm_front": 0.0779,
      "iv_atm_back": 0.4817,
      "iv_term_slope": 0.4039,
      "iv_skew": 0.0742,
      "iv_target_expiry": "2026-06-08",
      "fair_yes": 0.2359,
      "market_yes": 0.32,
      "edge_pp": -8.41,
      "spread_pp": 36.0,
      "tradeable_edge_pp": -0.0,
      "liquidity": 3773.0,
      "vol_24h": 308.0,
      "event_slug": "tsla-close-above-on-june-8-2026",
      "market_id": "2443292"
    },
    {
      "ticker": "AAPL",
      "side": "above",
      "strike": 300.0,
      "close_date": "2026-06-08",
      "days": 2.02,
      "spot": 307.34,
      "sigma_used": 0.2765,
      "sigma_source": "iv_target",
      "rv_30d": 0.2027,
      "rv_60d": 0.223,
      "iv_atm_target": 0.2765,
      "iv_atm_front": 0.0679,
      "iv_atm_back": 0.2557,
      "iv_term_slope": 0.1878,
      "iv_skew": 0.0078,
      "iv_target_expiry": "2026-06-08",
      "fair_yes": 0.8322,
      "market_yes": 0.755,
      "edge_pp": 7.72,
      "spread_pp": 31.0,
      "tradeable_edge_pp": 0.0,
      "liquidity": 2946.0,
      "vol_24h": 0,
      "event_slug": "aapl-close-above-on-june-8-2026",
      "market_id": "2443226"
    },
    {
      "ticker": "SPY",
      "side": "above",
      "strike": 770.0,
      "close_date": "2026-06-08",
      "days": 2.02,
      "spot": 737.55,
      "sigma_used": 0.1116,
      "sigma_source": "iv_target",
      "rv_30d": 0.1228,
      "rv_60d": 0.152,
      "iv_atm_target": 0.1116,
      "iv_atm_front": 0.0393,
      "iv_atm_back": 0.1605,
      "iv_term_slope": 0.1213,
      "iv_skew": 0.0156,
      "iv_target_expiry": "2026-06-08",
      "fair_yes": 0.0,
      "market_yes": 0.07,
      "edge_pp": -7.0,
      "spread_pp": null,
      "tradeable_edge_pp": null,
      "liquidity": 8297.0,
      "vol_24h": 105.0,
      "event_slug": "spy-closes-above-on-june-8-2026",
      "market_id": "2443235"
    },
    {
      "ticker": "AMZN",
      "side": "above",
      "strike": 255.0,
      "close_date": "2026-06-08",
      "days": 2.02,
      "spot": 246.03,
      "sigma_used": 0.2794,
      "sigma_source": "iv_target",
      "rv_30d": 0.2697,
      "rv_60d": 0.3027,
      "iv_atm_target": 0.2794,
      "iv_atm_front": 0.1113,
      "iv_atm_back": 0.3385,
      "iv_term_slope": 0.2272,
      "iv_skew": 0.0078,
      "iv_target_expiry": "2026-06-08",
      "fair_yes": 0.0746,
      "market_yes": 0.14,
      "edge_pp": -6.54,
      "spread_pp": 16.0,
      "tradeable_edge_pp": -0.0,
      "liquidity": 3301.0,
      "vol_24h": 105.0,
      "event_slug": "amzn-close-above-on-june-8-2026",
      "market_id": "2443270"
    },
    {
      "ticker": "MSFT",
      "side": "above",
      "strike": 430.0,
      "close_date": "2026-06-08",
      "days": 2.02,
      "spot": 416.67,
      "sigma_used": 0.2217,
      "sigma_source": "iv_target",
      "rv_30d": 0.3332,
      "rv_60d": 0.3166,
      "iv_atm_target": 0.2217,
      "iv_atm_front": 0.0761,
      "iv_atm_back": 0.3118,
      "iv_term_slope": 0.2357,
      "iv_skew": 0.1738,
      "iv_target_expiry": "2026-06-08",
      "fair_yes": 0.0554,
      "market_yes": 0.12,
      "edge_pp": -6.46,
      "spread_pp": 12.0,
      "tradeable_edge_pp": -0.0,
      "liquidity": 2347.0,
      "vol_24h": 0,
      "event_slug": "msft-close-above-on-june-8-2026",
      "market_id": "2443250"
    },
    {
      "ticker": "SPY",
      "side": "above",
      "strike": 745.0,
      "close_date": "2026-06-08",
      "days": 2.02,
      "spot": 737.55,
      "sigma_used": 0.1116,
      "sigma_source": "iv_target",
      "rv_30d": 0.1228,
      "rv_60d": 0.152,
      "iv_atm_target": 0.1116,
      "iv_atm_front": 0.0393,
      "iv_atm_back": 0.1605,
      "iv_term_slope": 0.1213,
      "iv_skew": 0.0156,
      "iv_target_expiry": "2026-06-08",
      "fair_yes": 0.1564,
      "market_yes": 0.22,
      "edge_pp": -6.36,
      "spread_pp": 36.0,
      "tradeable_edge_pp": -0.0,
      "liquidity": 8297.0,
      "vol_24h": 14.0,
      "event_slug": "spy-closes-above-on-june-8-2026",
      "market_id": "2443240"
    },
    {
      "ticker": "NFLX",
      "side": "above",
      "strike": 20.0,
      "close_date": "2026-06-30",
      "days": 17.74,
      "spot": 82.18,
      "sigma_used": 0.3026,
      "sigma_source": "iv_target",
      "rv_30d": 0.2292,
      "rv_60d": 0.3247,
      "iv_atm_target": 0.3026,
      "iv_atm_front": 0.0962,
      "iv_atm_back": 0.3219,
      "iv_term_slope": 0.2257,
      "iv_skew": 0.0469,
      "iv_target_expiry": "2026-07-02",
      "fair_yes": 1.0,
      "market_yes": 0.942,
      "edge_pp": 5.8,
      "spread_pp": 10.8,
      "tradeable_edge_pp": 0.0,
      "liquidity": 558.0,
      "vol_24h": 146.0,
      "event_slug": "nflx-above-in-june-2026",
      "market_id": "2389015"
    },
    {
      "ticker": "META",
      "side": "above",
      "strike": 610.0,
      "close_date": "2026-06-08",
      "days": 2.02,
      "spot": 593.0,
      "sigma_used": 0.3211,
      "sigma_source": "iv_target",
      "rv_30d": 0.4073,
      "rv_60d": 0.4398,
      "iv_atm_target": 0.3211,
      "iv_atm_front": 0.1119,
      "iv_atm_back": 0.3524,
      "iv_term_slope": 0.2405,
      "iv_skew": 0.0312,
      "iv_target_expiry": "2026-06-08",
      "fair_yes": 0.1595,
      "market_yes": 0.215,
      "edge_pp": -5.55,
      "spread_pp": 27.0,
      "tradeable_edge_pp": -0.0,
      "liquidity": 3171.0,
      "vol_24h": 520.0,
      "event_slug": "meta-close-above-on-june-8-2026",
      "market_id": "2443284"
    },
    {
      "ticker": "META",
      "side": "above",
      "strike": 560.0,
      "close_date": "2026-06-30",
      "days": 17.74,
      "spot": 593.0,
      "sigma_used": 0.3633,
      "sigma_source": "iv_target",
      "rv_30d": 0.4073,
      "rv_60d": 0.4398,
      "iv_atm_target": 0.3633,
      "iv_atm_front": 0.1119,
      "iv_atm_back": 0.3524,
      "iv_term_slope": 0.2405,
      "iv_skew": 0.0312,
      "iv_target_expiry": "2026-07-02",
      "fair_yes": 0.7074,
      "market_yes": 0.76,
      "edge_pp": -5.26,
      "spread_pp": 12.0,
      "tradeable_edge_pp": -0.0,
      "liquidity": 888.0,
      "vol_24h": 8,
      "event_slug": "meta-above-in-june-2026",
      "market_id": "2388853"
    },
    {
      "ticker": "NVDA",
      "side": "above",
      "strike": 210.0,
      "close_date": "2026-06-08",
      "days": 2.02,
      "spot": 205.1,
      "sigma_used": 0.3158,
      "sigma_source": "iv_target",
      "rv_30d": 0.4744,
      "rv_60d": 0.4013,
      "iv_atm_target": 0.3158,
      "iv_atm_front": 0.0542,
      "iv_atm_back": 0.4051,
      "iv_term_slope": 0.3509,
      "iv_skew": 0.0312,
      "iv_target_expiry": "2026-06-08",
      "fair_yes": 0.1982,
      "market_yes": 0.25,
      "edge_pp": -5.18,
      "spread_pp": 38.0,
      "tradeable_edge_pp": -0.0,
      "liquidity": 2593.0,
      "vol_24h": 7.0,
      "event_slug": "nvda-close-above-on-june-8-2026",
      "market_id": "2443301"
    },
    {
      "ticker": "AMZN",
      "side": "above",
      "strike": 260.0,
      "close_date": "2026-06-08",
      "days": 2.02,
      "spot": 246.03,
      "sigma_used": 0.2794,
      "sigma_source": "iv_target",
      "rv_30d": 0.2697,
      "rv_60d": 0.3027,
      "iv_atm_target": 0.2794,
      "iv_atm_front": 0.1113,
      "iv_atm_back": 0.3385,
      "iv_term_slope": 0.2272,
      "iv_skew": 0.0078,
      "iv_target_expiry": "2026-06-08",
      "fair_yes": 0.0133,
      "market_yes": 0.065,
      "edge_pp": -5.17,
      "spread_pp": 3.0,
      "tradeable_edge_pp": -2.17,
      "liquidity": 3301.0,
      "vol_24h": 60.0,
      "event_slug": "amzn-close-above-on-june-8-2026",
      "market_id": "2443271"
    },
    {
      "ticker": "SPY",
      "side": "above",
      "strike": 755.0,
      "close_date": "2026-06-08",
      "days": 2.02,
      "spot": 737.55,
      "sigma_used": 0.1116,
      "sigma_source": "iv_target",
      "rv_30d": 0.1228,
      "rv_60d": 0.152,
      "iv_atm_target": 0.1116,
      "iv_atm_front": 0.0393,
      "iv_atm_back": 0.1605,
      "iv_term_slope": 0.1213,
      "iv_skew": 0.0156,
      "iv_target_expiry": "2026-06-08",
      "fair_yes": 0.0096,
      "market_yes": 0.06,
      "edge_pp": -5.04,
      "spread_pp": 8.0,
      "tradeable_edge_pp": -0.0,
      "liquidity": 8297.0,
      "vol_24h": 51.0,
      "event_slug": "spy-closes-above-on-june-8-2026",
      "market_id": "2443238"
    },
    {
      "ticker": "SPY",
      "side": "above",
      "strike": 765.0,
      "close_date": "2026-06-08",
      "days": 2.02,
      "spot": 737.55,
      "sigma_used": 0.1116,
      "sigma_source": "iv_target",
      "rv_30d": 0.1228,
      "rv_60d": 0.152,
      "iv_atm_target": 0.1116,
      "iv_atm_front": 0.0393,
      "iv_atm_back": 0.1605,
      "iv_term_slope": 0.1213,
      "iv_skew": 0.0156,
      "iv_target_expiry": "2026-06-08",
      "fair_yes": 0.0001,
      "market_yes": 0.0485,
      "edge_pp": -4.84,
      "spread_pp": 8.7,
      "tradeable_edge_pp": -0.0,
      "liquidity": 8297.0,
      "vol_24h": 228.0,
      "event_slug": "spy-closes-above-on-june-8-2026",
      "market_id": "2443236"
    },
    {
      "ticker": "SPY",
      "side": "above",
      "strike": 750.0,
      "close_date": "2026-06-08",
      "days": 2.02,
      "spot": 737.55,
      "sigma_used": 0.1116,
      "sigma_source": "iv_target",
      "rv_30d": 0.1228,
      "rv_60d": 0.152,
      "iv_atm_target": 0.1116,
      "iv_atm_front": 0.0393,
      "iv_atm_back": 0.1605,
      "iv_term_slope": 0.1213,
      "iv_skew": 0.0156,
      "iv_target_expiry": "2026-06-08",
      "fair_yes": 0.0467,
      "market_yes": 0.095,
      "edge_pp": -4.83,
      "spread_pp": 9.0,
      "tradeable_edge_pp": -0.0,
      "liquidity": 8297.0,
      "vol_24h": 101.0,
      "event_slug": "spy-closes-above-on-june-8-2026",
      "market_id": "2443239"
    },
    {
      "ticker": "NVDA",
      "side": "above",
      "strike": 170.0,
      "close_date": "2026-06-30",
      "days": 17.74,
      "spot": 205.1,
      "sigma_used": 0.4151,
      "sigma_source": "iv_target",
      "rv_30d": 0.4744,
      "rv_60d": 0.4013,
      "iv_atm_target": 0.4151,
      "iv_atm_front": 0.0542,
      "iv_atm_back": 0.4051,
      "iv_term_slope": 0.3509,
      "iv_skew": 0.0312,
      "iv_target_expiry": "2026-07-02",
      "fair_yes": 0.9504,
      "market_yes": 0.9095,
      "edge_pp": 4.09,
      "spread_pp": 11.9,
      "tradeable_edge_pp": 0.0,
      "liquidity": 1030.0,
      "vol_24h": 0,
      "event_slug": "nvda-above-in-june-2026",
      "market_id": "2388955"
    },
    {
      "ticker": "NFLX",
      "side": "above",
      "strike": 180.0,
      "close_date": "2026-06-30",
      "days": 17.74,
      "spot": 82.18,
      "sigma_used": 0.3026,
      "sigma_source": "iv_target",
      "rv_30d": 0.2292,
      "rv_60d": 0.3247,
      "iv_atm_target": 0.3026,
      "iv_atm_front": 0.0962,
      "iv_atm_back": 0.3219,
      "iv_term_slope": 0.2257,
      "iv_skew": 0.0469,
      "iv_target_expiry": "2026-07-02",
      "fair_yes": 0.0,
      "market_yes": 0.0395,
      "edge_pp": -3.95,
      "spread_pp": 6.5,
      "tradeable_edge_pp": -0.0,
      "liquidity": 558.0,
      "vol_24h": 196.0,
      "event_slug": "nflx-above-in-june-2026",
      "market_id": "2389035"
    },
    {
      "ticker": "SPY",
      "side": "above",
      "strike": 760.0,
      "close_date": "2026-06-08",
      "days": 2.02,
      "spot": 737.55,
      "sigma_used": 0.1116,
      "sigma_source": "iv_target",
      "rv_30d": 0.1228,
      "rv_60d": 0.152,
      "iv_atm_target": 0.1116,
      "iv_atm_front": 0.0393,
      "iv_atm_back": 0.1605,
      "iv_term_slope": 0.1213,
      "iv_skew": 0.0156,
      "iv_target_expiry": "2026-06-08",
      "fair_yes": 0.0013,
      "market_yes": 0.0345,
      "edge_pp": -3.32,
      "spread_pp": 4.9,
      "tradeable_edge_pp": -0.0,
      "liquidity": 8297.0,
      "vol_24h": 347.0,
      "event_slug": "spy-closes-above-on-june-8-2026",
      "market_id": "2443237"
    },
    {
      "ticker": "SPY",
      "side": "above",
      "strike": 740.0,
      "close_date": "2026-06-08",
      "days": 2.02,
      "spot": 737.55,
      "sigma_used": 0.1116,
      "sigma_source": "iv_target",
      "rv_30d": 0.1228,
      "rv_60d": 0.152,
      "iv_atm_target": 0.1116,
      "iv_atm_front": 0.0393,
      "iv_atm_back": 0.1605,
      "iv_term_slope": 0.1213,
      "iv_skew": 0.0156,
      "iv_target_expiry": "2026-06-08",
      "fair_yes": 0.3683,
      "market_yes": 0.4,
      "edge_pp": -3.17,
      "spread_pp": 32.0,
      "tradeable_edge_pp": -0.0,
      "liquidity": 8297.0,
      "vol_24h": 33.0,
      "event_slug": "spy-closes-above-on-june-8-2026",
      "market_id": "2443241"
    },
    {
      "ticker": "TSLA",
      "side": "above",
      "strike": 410.0,
      "close_date": "2026-06-08",
      "days": 2.02,
      "spot": 391.0,
      "sigma_used": 0.361,
      "sigma_source": "iv_target",
      "rv_30d": 0.42,
      "rv_60d": 0.434,
      "iv_atm_target": 0.361,
      "iv_atm_front": 0.0779,
      "iv_atm_back": 0.4817,
      "iv_term_slope": 0.4039,
      "iv_skew": 0.0742,
      "iv_target_expiry": "2026-06-08",
      "fair_yes": 0.0691,
      "market_yes": 0.1,
      "edge_pp": -3.09,
      "spread_pp": 8.0,
      "tradeable_edge_pp": -0.0,
      "liquidity": 3773.0,
      "vol_24h": 89.0,
      "event_slug": "tsla-close-above-on-june-8-2026",
      "market_id": "2443295"
    },
    {
      "ticker": "AMZN",
      "side": "above",
      "strike": 265.0,
      "close_date": "2026-06-08",
      "days": 2.02,
      "spot": 246.03,
      "sigma_used": 0.2794,
      "sigma_source": "iv_target",
      "rv_30d": 0.2697,
      "rv_60d": 0.3027,
      "iv_atm_target": 0.2794,
      "iv_atm_front": 0.1113,
      "iv_atm_back": 0.3385,
      "iv_term_slope": 0.2272,
      "iv_skew": 0.0078,
      "iv_target_expiry": "2026-06-08",
      "fair_yes": 0.0015,
      "market_yes": 0.031,
      "edge_pp": -2.95,
      "spread_pp": 3.8,
      "tradeable_edge_pp": -0.0,
      "liquidity": 3301.0,
      "vol_24h": 31.0,
      "event_slug": "amzn-close-above-on-june-8-2026",
      "market_id": "2443272"
    },
    {
      "ticker": "AAPL",
      "side": "above",
      "strike": 370.0,
      "close_date": "2026-06-30",
      "days": 17.74,
      "spot": 307.34,
      "sigma_used": 0.258,
      "sigma_source": "iv_target",
      "rv_30d": 0.2027,
      "rv_60d": 0.223,
      "iv_atm_target": 0.258,
      "iv_atm_front": 0.0679,
      "iv_atm_back": 0.2557,
      "iv_term_slope": 0.1878,
      "iv_skew": 0.0078,
      "iv_target_expiry": "2026-07-02",
      "fair_yes": 0.003,
      "market_yes": 0.0305,
      "edge_pp": -2.75,
      "spread_pp": 3.9,
      "tradeable_edge_pp": -0.0,
      "liquidity": 634.0,
      "vol_24h": 0,
      "event_slug": "aapl-above-in-june-2026",
      "market_id": "2388619"
    },
    {
      "ticker": "NFLX",
      "side": "above",
      "strike": 200.0,
      "close_date": "2026-06-30",
      "days": 17.74,
      "spot": 82.18,
      "sigma_used": 0.3026,
      "sigma_source": "iv_target",
      "rv_30d": 0.2292,
      "rv_60d": 0.3247,
      "iv_atm_target": 0.3026,
      "iv_atm_front": 0.0962,
      "iv_atm_back": 0.3219,
      "iv_term_slope": 0.2257,
      "iv_skew": 0.0469,
      "iv_target_expiry": "2026-07-02",
      "fair_yes": 0.0,
      "market_yes": 0.026,
      "edge_pp": -2.6,
      "spread_pp": 4.8,
      "tradeable_edge_pp": -0.0,
      "liquidity": 558.0,
      "vol_24h": 10.0,
      "event_slug": "nflx-above-in-june-2026",
      "market_id": "2389036"
    },
    {
      "ticker": "NFLX",
      "side": "above",
      "strike": 40.0,
      "close_date": "2026-06-30",
      "days": 17.74,
      "spot": 82.18,
      "sigma_used": 0.3026,
      "sigma_source": "iv_target",
      "rv_30d": 0.2292,
      "rv_60d": 0.3247,
      "iv_atm_target": 0.3026,
      "iv_atm_front": 0.0962,
      "iv_atm_back": 0.3219,
      "iv_term_slope": 0.2257,
      "iv_skew": 0.0469,
      "iv_target_expiry": "2026-07-02",
      "fair_yes": 1.0,
      "market_yes": 0.9745,
      "edge_pp": 2.55,
      "spread_pp": 4.9,
      "tradeable_edge_pp": 0.0,
      "liquidity": 558.0,
      "vol_24h": 16,
      "event_slug": "nflx-above-in-june-2026",
      "market_id": "2389019"
    },
    {
      "ticker": "NVDA",
      "side": "above",
      "strike": 180.0,
      "close_date": "2026-06-30",
      "days": 17.74,
      "spot": 205.1,
      "sigma_used": 0.4151,
      "sigma_source": "iv_target",
      "rv_30d": 0.4744,
      "rv_60d": 0.4013,
      "iv_atm_target": 0.4151,
      "iv_atm_front": 0.0542,
      "iv_atm_back": 0.4051,
      "iv_term_slope": 0.3509,
      "iv_skew": 0.0312,
      "iv_target_expiry": "2026-07-02",
      "fair_yes": 0.8708,
      "market_yes": 0.8945,
      "edge_pp": -2.37,
      "spread_pp": 8.9,
      "tradeable_edge_pp": -0.0,
      "liquidity": 1030.0,
      "vol_24h": 0,
      "event_slug": "nvda-above-in-june-2026",
      "market_id": "2388957"
    },
    {
      "ticker": "AMZN",
      "side": "above",
      "strike": 245.0,
      "close_date": "2026-06-08",
      "days": 2.02,
      "spot": 246.03,
      "sigma_used": 0.2794,
      "sigma_source": "iv_target",
      "rv_30d": 0.2697,
      "rv_60d": 0.3027,
      "iv_atm_target": 0.2794,
      "iv_atm_front": 0.1113,
      "iv_atm_back": 0.3385,
      "iv_term_slope": 0.2272,
      "iv_skew": 0.0078,
      "iv_target_expiry": "2026-06-08",
      "fair_yes": 0.5616,
      "market_yes": 0.54,
      "edge_pp": 2.16,
      "spread_pp": 42.0,
      "tradeable_edge_pp": 0.0,
      "liquidity": 3301.0,
      "vol_24h": 14.0,
      "event_slug": "amzn-close-above-on-june-8-2026",
      "market_id": "2443268"
    },
    {
      "ticker": "SPY",
      "side": "above",
      "strike": 775.0,
      "close_date": "2026-06-08",
      "days": 2.02,
      "spot": 737.55,
      "sigma_used": 0.1116,
      "sigma_source": "iv_target",
      "rv_30d": 0.1228,
      "rv_60d": 0.152,
      "iv_atm_target": 0.1116,
      "iv_atm_front": 0.0393,
      "iv_atm_back": 0.1605,
      "iv_term_slope": 0.1213,
      "iv_skew": 0.0156,
      "iv_target_expiry": "2026-06-08",
      "fair_yes": 0.0,
      "market_yes": 0.0205,
      "edge_pp": -2.05,
      "spread_pp": 3.9,
      "tradeable_edge_pp": -0.0,
      "liquidity": 8297.0,
      "vol_24h": 492.0,
      "event_slug": "spy-closes-above-on-june-8-2026",
      "market_id": "2443233"
    },
    {
      "ticker": "AAPL",
      "side": "above",
      "strike": 300.0,
      "close_date": "2026-06-30",
      "days": 17.74,
      "spot": 307.34,
      "sigma_used": 0.258,
      "sigma_source": "iv_target",
      "rv_30d": 0.2027,
      "rv_60d": 0.223,
      "iv_atm_target": 0.258,
      "iv_atm_front": 0.0679,
      "iv_atm_back": 0.2557,
      "iv_term_slope": 0.1878,
      "iv_skew": 0.0078,
      "iv_target_expiry": "2026-07-02",
      "fair_yes": 0.6251,
      "market_yes": 0.605,
      "edge_pp": 2.01,
      "spread_pp": 23.0,
      "tradeable_edge_pp": 0.0,
      "liquidity": 634.0,
      "vol_24h": 0,
      "event_slug": "aapl-above-in-june-2026",
      "market_id": "2388584"
    },
    {
      "ticker": "TSLA",
      "side": "above",
      "strike": 400.0,
      "close_date": "2026-06-30",
      "days": 17.74,
      "spot": 391.0,
      "sigma_used": 0.4881,
      "sigma_source": "iv_target",
      "rv_30d": 0.42,
      "rv_60d": 0.434,
      "iv_atm_target": 0.4881,
      "iv_atm_front": 0.0779,
      "iv_atm_back": 0.4817,
      "iv_term_slope": 0.4039,
      "iv_skew": 0.0742,
      "iv_target_expiry": "2026-07-02",
      "fair_yes": 0.405,
      "market_yes": 0.425,
      "edge_pp": -2.0,
      "spread_pp": 19.0,
      "tradeable_edge_pp": -0.0,
      "liquidity": 1668.0,
      "vol_24h": 0,
      "event_slug": "tsla-above-in-june-2026",
      "market_id": "2388904"
    },
    {
      "ticker": "AAPL",
      "side": "above",
      "strike": 310.0,
      "close_date": "2026-06-30",
      "days": 17.74,
      "spot": 307.34,
      "sigma_used": 0.258,
      "sigma_source": "iv_target",
      "rv_30d": 0.2027,
      "rv_60d": 0.223,
      "iv_atm_target": 0.258,
      "iv_atm_front": 0.0679,
      "iv_atm_back": 0.2557,
      "iv_term_slope": 0.1878,
      "iv_skew": 0.0078,
      "iv_target_expiry": "2026-07-02",
      "fair_yes": 0.4364,
      "market_yes": 0.455,
      "edge_pp": -1.86,
      "spread_pp": 15.0,
      "tradeable_edge_pp": -0.0,
      "liquidity": 634.0,
      "vol_24h": 0,
      "event_slug": "aapl-above-in-june-2026",
      "market_id": "2388591"
    },
    {
      "ticker": "MSFT",
      "side": "above",
      "strike": 405.0,
      "close_date": "2026-06-30",
      "days": 17.74,
      "spot": 416.67,
      "sigma_used": 0.3017,
      "sigma_source": "iv_target",
      "rv_30d": 0.3332,
      "rv_60d": 0.3166,
      "iv_atm_target": 0.3017,
      "iv_atm_front": 0.0761,
      "iv_atm_back": 0.3118,
      "iv_term_slope": 0.2357,
      "iv_skew": 0.1738,
      "iv_target_expiry": "2026-07-02",
      "fair_yes": 0.6236,
      "market_yes": 0.605,
      "edge_pp": 1.86,
      "spread_pp": 25.0,
      "tradeable_edge_pp": 0.0,
      "liquidity": 731.0,
      "vol_24h": 0,
      "event_slug": "msft-above-in-june-2026",
      "market_id": "2388670"
    },
    {
      "ticker": "META",
      "side": "above",
      "strike": 580.0,
      "close_date": "2026-06-30",
      "days": 17.74,
      "spot": 593.0,
      "sigma_used": 0.3633,
      "sigma_source": "iv_target",
      "rv_30d": 0.4073,
      "rv_60d": 0.4398,
      "iv_atm_target": 0.3633,
      "iv_atm_front": 0.1119,
      "iv_atm_back": 0.3524,
      "iv_term_slope": 0.2405,
      "iv_skew": 0.0312,
      "iv_target_expiry": "2026-07-02",
      "fair_yes": 0.5721,
      "market_yes": 0.59,
      "edge_pp": -1.79,
      "spread_pp": 26.0,
      "tradeable_edge_pp": -0.0,
      "liquidity": 888.0,
      "vol_24h": 22.0,
      "event_slug": "meta-above-in-june-2026",
      "market_id": "2388854"
    },
    {
      "ticker": "NFLX",
      "side": "above",
      "strike": 80.0,
      "close_date": "2026-06-30",
      "days": 17.74,
      "spot": 82.18,
      "sigma_used": 0.3026,
      "sigma_source": "iv_target",
      "rv_30d": 0.2292,
      "rv_60d": 0.3247,
      "iv_atm_target": 0.3026,
      "iv_atm_front": 0.0962,
      "iv_atm_back": 0.3219,
      "iv_term_slope": 0.2257,
      "iv_skew": 0.0469,
      "iv_target_expiry": "2026-07-02",
      "fair_yes": 0.6159,
      "market_yes": 0.6,
      "edge_pp": 1.59,
      "spread_pp": 22.0,
      "tradeable_edge_pp": 0.0,
      "liquidity": 558.0,
      "vol_24h": 94.0,
      "event_slug": "nflx-above-in-june-2026",
      "market_id": "2389025"
    },
    {
      "ticker": "META",
      "side": "above",
      "strike": 620.0,
      "close_date": "2026-06-08",
      "days": 2.02,
      "spot": 593.0,
      "sigma_used": 0.3211,
      "sigma_source": "iv_target",
      "rv_30d": 0.4073,
      "rv_60d": 0.4398,
      "iv_atm_target": 0.3211,
      "iv_atm_front": 0.1119,
      "iv_atm_back": 0.3524,
      "iv_term_slope": 0.2405,
      "iv_skew": 0.0312,
      "iv_target_expiry": "2026-06-08",
      "fair_yes": 0.0592,
      "market_yes": 0.075,
      "edge_pp": -1.58,
      "spread_pp": 5.0,
      "tradeable_edge_pp": -0.0,
      "liquidity": 3171.0,
      "vol_24h": 712.0,
      "event_slug": "meta-close-above-on-june-8-2026",
      "market_id": "2443285"
    },
    {
      "ticker": "AMZN",
      "side": "above",
      "strike": 250.0,
      "close_date": "2026-06-30",
      "days": 17.74,
      "spot": 246.03,
      "sigma_used": 0.3417,
      "sigma_source": "iv_target",
      "rv_30d": 0.2697,
      "rv_60d": 0.3027,
      "iv_atm_target": 0.3417,
      "iv_atm_front": 0.1113,
      "iv_atm_back": 0.3385,
      "iv_term_slope": 0.2272,
      "iv_skew": 0.0078,
      "iv_target_expiry": "2026-07-02",
      "fair_yes": 0.4122,
      "market_yes": 0.425,
      "edge_pp": -1.28,
      "spread_pp": 21.0,
      "tradeable_edge_pp": -0.0,
      "liquidity": 723.0,
      "vol_24h": 0,
      "event_slug": "amzn-above-in-june-2026",
      "market_id": "2388731"
    },
    {
      "ticker": "META",
      "side": "above",
      "strike": 600.0,
      "close_date": "2026-06-30",
      "days": 17.74,
      "spot": 593.0,
      "sigma_used": 0.3633,
      "sigma_source": "iv_target",
      "rv_30d": 0.4073,
      "rv_60d": 0.4398,
      "iv_atm_target": 0.3633,
      "iv_atm_front": 0.1119,
      "iv_atm_back": 0.3524,
      "iv_term_slope": 0.2405,
      "iv_skew": 0.0312,
      "iv_target_expiry": "2026-07-02",
      "fair_yes": 0.4325,
      "market_yes": 0.445,
      "edge_pp": -1.25,
      "spread_pp": 27.0,
      "tradeable_edge_pp": -0.0,
      "liquidity": 888.0,
      "vol_24h": 17.0,
      "event_slug": "meta-above-in-june-2026",
      "market_id": "2388855"
    },
    {
      "ticker": "MSFT",
      "side": "above",
      "strike": 420.0,
      "close_date": "2026-06-08",
      "days": 2.02,
      "spot": 416.67,
      "sigma_used": 0.2217,
      "sigma_source": "iv_target",
      "rv_30d": 0.3332,
      "rv_60d": 0.3166,
      "iv_atm_target": 0.2217,
      "iv_atm_front": 0.0761,
      "iv_atm_back": 0.3118,
      "iv_term_slope": 0.2357,
      "iv_skew": 0.1738,
      "iv_target_expiry": "2026-06-08",
      "fair_yes": 0.3407,
      "market_yes": 0.33,
      "edge_pp": 1.07,
      "spread_pp": 34.0,
      "tradeable_edge_pp": 0.0,
      "liquidity": 2347.0,
      "vol_24h": 14.0,
      "event_slug": "msft-close-above-on-june-8-2026",
      "market_id": "2443249"
    },
    {
      "ticker": "META",
      "side": "above",
      "strike": 640.0,
      "close_date": "2026-06-08",
      "days": 2.02,
      "spot": 593.0,
      "sigma_used": 0.3211,
      "sigma_source": "iv_target",
      "rv_30d": 0.4073,
      "rv_60d": 0.4398,
      "iv_atm_target": 0.3211,
      "iv_atm_front": 0.1119,
      "iv_atm_back": 0.3524,
      "iv_term_slope": 0.2405,
      "iv_skew": 0.0312,
      "iv_target_expiry": "2026-06-08",
      "fair_yes": 0.0039,
      "market_yes": 0.014,
      "edge_pp": -1.01,
      "spread_pp": 2.2,
      "tradeable_edge_pp": -0.0,
      "liquidity": 3171.0,
      "vol_24h": 108.0,
      "event_slug": "meta-close-above-on-june-8-2026",
      "market_id": "2443287"
    },
    {
      "ticker": "MSFT",
      "side": "above",
      "strike": 420.0,
      "close_date": "2026-06-30",
      "days": 17.74,
      "spot": 416.67,
      "sigma_used": 0.3017,
      "sigma_source": "iv_target",
      "rv_30d": 0.3332,
      "rv_60d": 0.3166,
      "iv_atm_target": 0.3017,
      "iv_atm_front": 0.0761,
      "iv_atm_back": 0.3118,
      "iv_term_slope": 0.2357,
      "iv_skew": 0.1738,
      "iv_target_expiry": "2026-07-02",
      "fair_yes": 0.4445,
      "market_yes": 0.435,
      "edge_pp": 0.95,
      "spread_pp": 23.0,
      "tradeable_edge_pp": 0.0,
      "liquidity": 731.0,
      "vol_24h": 0,
      "event_slug": "msft-above-in-june-2026",
      "market_id": "2388675"
    },
    {
      "ticker": "META",
      "side": "above",
      "strike": 630.0,
      "close_date": "2026-06-08",
      "days": 2.02,
      "spot": 593.0,
      "sigma_used": 0.3211,
      "sigma_source": "iv_target",
      "rv_30d": 0.4073,
      "rv_60d": 0.4398,
      "iv_atm_target": 0.3211,
      "iv_atm_front": 0.1119,
      "iv_atm_back": 0.3524,
      "iv_term_slope": 0.2405,
      "iv_skew": 0.0312,
      "iv_target_expiry": "2026-06-08",
      "fair_yes": 0.0171,
      "market_yes": 0.0255,
      "edge_pp": -0.84,
      "spread_pp": 4.3,
      "tradeable_edge_pp": -0.0,
      "liquidity": 3171.0,
      "vol_24h": 514.0,
      "event_slug": "meta-close-above-on-june-8-2026",
      "market_id": "2443286"
    },
    {
      "ticker": "TSLA",
      "side": "above",
      "strike": 380.0,
      "close_date": "2026-06-30",
      "days": 17.74,
      "spot": 391.0,
      "sigma_used": 0.4881,
      "sigma_source": "iv_target",
      "rv_30d": 0.42,
      "rv_60d": 0.434,
      "iv_atm_target": 0.4881,
      "iv_atm_front": 0.0779,
      "iv_atm_back": 0.4817,
      "iv_term_slope": 0.4039,
      "iv_skew": 0.0742,
      "iv_target_expiry": "2026-07-02",
      "fair_yes": 0.5618,
      "market_yes": 0.57,
      "edge_pp": -0.82,
      "spread_pp": 22.0,
      "tradeable_edge_pp": -0.0,
      "liquidity": 1668.0,
      "vol_24h": 0,
      "event_slug": "tsla-above-in-june-2026",
      "market_id": "2388902"
    },
    {
      "ticker": "SPY",
      "side": "above",
      "strike": 780.0,
      "close_date": "2026-06-08",
      "days": 2.02,
      "spot": 737.55,
      "sigma_used": 0.1116,
      "sigma_source": "iv_target",
      "rv_30d": 0.1228,
      "rv_60d": 0.152,
      "iv_atm_target": 0.1116,
      "iv_atm_front": 0.0393,
      "iv_atm_back": 0.1605,
      "iv_term_slope": 0.1213,
      "iv_skew": 0.0156,
      "iv_target_expiry": "2026-06-08",
      "fair_yes": 0.0,
      "market_yes": 0.008,
      "edge_pp": -0.8,
      "spread_pp": 1.4,
      "tradeable_edge_pp": -0.0,
      "liquidity": 8297.0,
      "vol_24h": 261.0,
      "event_slug": "spy-closes-above-on-june-8-2026",
      "market_id": "2443229"
    },
    {
      "ticker": "NVDA",
      "side": "above",
      "strike": 200.0,
      "close_date": "2026-06-30",
      "days": 17.74,
      "spot": 205.1,
      "sigma_used": 0.4151,
      "sigma_source": "iv_target",
      "rv_30d": 0.4744,
      "rv_60d": 0.4013,
      "iv_atm_target": 0.4151,
      "iv_atm_front": 0.0542,
      "iv_atm_back": 0.4051,
      "iv_term_slope": 0.3509,
      "iv_skew": 0.0312,
      "iv_target_expiry": "2026-07-02",
      "fair_yes": 0.5689,
      "market_yes": 0.575,
      "edge_pp": -0.61,
      "spread_pp": 21.0,
      "tradeable_edge_pp": -0.0,
      "liquidity": 1030.0,
      "vol_24h": 210,
      "event_slug": "nvda-above-in-june-2026",
      "market_id": "2388961"
    },
    {
      "ticker": "AMZN",
      "side": "above",
      "strike": 240.0,
      "close_date": "2026-06-30",
      "days": 17.74,
      "spot": 246.03,
      "sigma_used": 0.3417,
      "sigma_source": "iv_target",
      "rv_30d": 0.2697,
      "rv_60d": 0.3027,
      "iv_atm_target": 0.3417,
      "iv_atm_front": 0.1113,
      "iv_atm_back": 0.3385,
      "iv_term_slope": 0.2272,
      "iv_skew": 0.0078,
      "iv_target_expiry": "2026-07-02",
      "fair_yes": 0.5903,
      "market_yes": 0.585,
      "edge_pp": 0.53,
      "spread_pp": 21.0,
      "tradeable_edge_pp": 0.0,
      "liquidity": 723.0,
      "vol_24h": 0,
      "event_slug": "amzn-above-in-june-2026",
      "market_id": "2388728"
    },
    {
      "ticker": "TSLA",
      "side": "above",
      "strike": 390.0,
      "close_date": "2026-06-30",
      "days": 17.74,
      "spot": 391.0,
      "sigma_used": 0.4881,
      "sigma_source": "iv_target",
      "rv_30d": 0.42,
      "rv_60d": 0.434,
      "iv_atm_target": 0.4881,
      "iv_atm_front": 0.0779,
      "iv_atm_back": 0.4817,
      "iv_term_slope": 0.4039,
      "iv_skew": 0.0742,
      "iv_target_expiry": "2026-07-02",
      "fair_yes": 0.4821,
      "market_yes": 0.48,
      "edge_pp": 0.21,
      "spread_pp": 18.0,
      "tradeable_edge_pp": 0.0,
      "liquidity": 1668.0,
      "vol_24h": 0,
      "event_slug": "tsla-above-in-june-2026",
      "market_id": "2388903"
    },
    {
      "ticker": "NVDA",
      "side": "above",
      "strike": 210.0,
      "close_date": "2026-06-30",
      "days": 17.74,
      "spot": 205.1,
      "sigma_used": 0.4151,
      "sigma_source": "iv_target",
      "rv_30d": 0.4744,
      "rv_60d": 0.4013,
      "iv_atm_target": 0.4151,
      "iv_atm_front": 0.0542,
      "iv_atm_back": 0.4051,
      "iv_term_slope": 0.3509,
      "iv_skew": 0.0312,
      "iv_target_expiry": "2026-07-02",
      "fair_yes": 0.3938,
      "market_yes": 0.395,
      "edge_pp": -0.12,
      "spread_pp": 21.0,
      "tradeable_edge_pp": -0.0,
      "liquidity": 1030.0,
      "vol_24h": 209.0,
      "event_slug": "nvda-above-in-june-2026",
      "market_id": "2388963"
    }
  ]
}